Workbook

Sheet README
A1: H₂ Transmission Pipeline Cost Model — Transition Accelerator Extraction Framework
A3: Purpose | B3: Intended Use
A4: This workbook reconstructs and documents the engineering and cost models for new-build gaseous hydrogen transmission pipelines and associated compression systems. It reproduces source calculations from the Transition Accelerator pipeline and compression technical briefs, uses the Ziqi Wei thesis as an implementation and validation reference, converts source costs into a consistent currency and unit basis, and prepares the resulting capital, fixed operating, variable operating, and electricity requirements for mapping into CANOE/TEMOA | B4: The workbook is designed to support transparent extraction, validation, sensitivity analysis, and implementation of hydrogen transmission cost parameters. It is not intended to calculate a single levelized cost of hydrogen for direct use in CANOE/TEMOA. Instead, it separates investment, fixed operating, variable operating, and energy requirements so that the optimization model can apply its own capacity, activity, lifetime, discounting, and temporal structure. | D4: TEMOA Cost Structure
A5: Sheet | B5: Role | D5: Parameter | E5: Economic Meaning | F5: Units | G5: Note
A6: Source_Index | B6: Records source information used for parameters, including source document, section, table or equation, original unit, extraction status, and interpretation notes.
A7: Assumptions and Parameters, Pipe | B7: Stores source-derived and explicitly assumed physical, hydraulic, economic, and conversion inputs used by the pipeline model.
A8: Transition Accelerator Pipe | B8: Reconstructs pipeline capacity, capital cost, fixed operating cost, and related outputs across the selected pipeline design cases.
A9: Assumptions and Parameters, Comp | B9: Stores source-derived and explicitly assumed thermodynamic, equipment, economic, and conversion inputs used by the compressor model.
A10: Transition Accelerator Comp | B10: Reconstructs compressor staging, power, capital cost, fixed operating cost, and electricity requirements for each pipeline capacity case.
A11: Normalized Transmission Costs | B11: Combines pipeline and compressor outputs into a consistent capacity-indexed transmission dataset using common currency, distance, capacity, and time conventions.
A12: Temoa cost structure | B12: Maps normalized transmission outputs into CANOE/TEMOA parameter definitions and units, including piecewise capacity-cost segments, fixed costs, variable costs, electricity inputs, and lifetime.
A14: System Boundary
A15: Included | B15: Excluded
A16: new-build gaseous hydrogen transmission pipelines | B16: Hydrogen production
A17: Pipeline material, labour, miscellaneous, installation, right-of-way costs included by the transition accelerator source | B17: Hydrogen storage
A18: Pipeline capital, fixed and variable costs | B18: End-use distribution networks
A19: Inlet compression | B19: Fueling station compression
A20: Compressor capital, fixed and variable costs | B20: Terminal end-fuel infrastructure
A21: En-route recompression normalized per km | B21: Seasonal operating dyanmics
A22: Compressor electricity requirements | B22: Geographic consutrction cost multipliers
A23: Capacity-dependent economies of scale | B23: Natural-gas pipeline repurposing
A24: Currency conversion and cost normalization | B24: Financing and discount (performed by TEMOA across all cost models)
A25: Mapping to TEMOA cost and efficicency parameters | B25: Taxes, subsidies, carbon pricing, or policy incentives

Sheet Source_Index
A1: Source Extraction Log: Transmission Pipeline Component
A2: Source_ID | B2: Source_Type | C2: Title | D2: Year/Version | E2: Section | F2: Source Page | G2: Table / Equation / Figure | H2: Default Value | I2: Unit | J2: Workbook symbol | K2: Workbook Section | L2: Notes | M2: Source URL
A3: TA-PIPE-001 | B3: Primary technical source | C3: The Techno-Economics of Hydrogen Pipelines | D3: 2021 / Version 2 | E3: 5.3 Pipeline Levelized Cost | F3: 20 | G3: Table 5.2 | H3: 50 | I3: years | J3: pipeline_lifetime | K3: Assumptions and Parameters Pipe – Pipeline lifetime | L3: Physical pipeline lifetime reported by the source. Use as the technology lifetime; do not embed a capital recovery factor in CostInvest. | M3: https://transitionaccelerator.ca/wp-content/uploads/2023/06/The-Techno-Economics-of-Hydrogen-Pipelines-v2.pdf
A4: TA-PIPE-002 | B4: Primary technical source | C4: The Techno-Economics of Hydrogen Pipelines | D4: 2021 / Version 2 | E4: 5.1 Pipeline Capital Costs | F4: 17 | G4: Table 5.1 notes | H4: 1.1 | I4: multiplier | J4: hydrogen_pipeline_cost_multiplier | K4: Assumptions and Parameters Pipe – Hydrogen pipeline cost multiplier | L4: Source applies a 1.1 hydrogen adjustment to the material, construction-labour, and miscellaneous transmission-pipeline correlations, but not to right-of-way. Retain for source reproduction and sensitivity analysis. | M4: https://transitionaccelerator.ca/wp-content/uploads/2023/06/The-Techno-Economics-of-Hydrogen-Pipelines-v2.pdf
A5: TA-PIPE-003 | B5: Primary technical source | C5: The Techno-Economics of Hydrogen Pipelines | D5: 2021 / Version 2 | E5: 5.1 Pipeline Capital Costs | F5: 18 | G5: Equation 14 | H5: 0.4 | I5: fraction of TIC | J5: indirect_capex_fraction | K5: Assumptions and Parameters Pipe – Indirect CAPEX cost assumption multiplier | L5: Indirect capital costs are calculated as 40% of total installed cost. The listed components total 28%, so the source also contains an unexplained residual of 12 percentage points. | M5: https://transitionaccelerator.ca/wp-content/uploads/2023/06/The-Techno-Economics-of-Hydrogen-Pipelines-v2.pdf
A6: TA-PIPE-004 | B6: Primary technical source | C6: The Techno-Economics of Hydrogen Pipelines | D6: 2021 / Version 2 | E6: 5.1 Pipeline Capital Costs | F6: 18 | G6: Indirect-capital-cost breakdown | H6: 0.05 | I6: fraction of TIC | J6: site_preparation_fraction | K6: Assumptions and Parameters Pipe – Site preparation | L6: Includes land purchase, grading, excavation, utilities, internal roads, walkways, and parking areas. Component of the 40% total indirect-cost assumption. | M6: https://transitionaccelerator.ca/wp-content/uploads/2023/06/The-Techno-Economics-of-Hydrogen-Pipelines-v2.pdf
A7: TA-PIPE-005 | B7: Primary technical source | C7: The Techno-Economics of Hydrogen Pipelines | D7: 2021 / Version 2 | E7: 5.1 Pipeline Capital Costs | F7: 18 | G7: Indirect-capital-cost breakdown | H7: 0.1 | I7: fraction of TIC | J7: engineering_design_fraction | K7: Assumptions and Parameters Pipe – Engineering and Design | L7: Includes engineering, drafting, project management, salaries, and associated overhead. Component of the 40% total indirect-cost assumption. | M7: https://transitionaccelerator.ca/wp-content/uploads/2023/06/The-Techno-Economics-of-Hydrogen-Pipelines-v2.pdf
A8: TA-PIPE-006 | B8: Primary technical source | C8: The Techno-Economics of Hydrogen Pipelines | D8: 2021 / Version 2 | E8: 5.1 Pipeline Capital Costs | F8: 18 | G8: Indirect-capital-cost breakdown | H8: 0.1 | I8: fraction of TIC | J8: project_contingency_fraction | K8: Assumptions and Parameters Pipe – Project Contingency | L8: Covers unforeseen circumstances, project risks, design changes, delays, and unexpected price increases. Component of the 40% total indirect-cost assumption. | M8: https://transitionaccelerator.ca/wp-content/uploads/2023/06/The-Techno-Economics-of-Hydrogen-Pipelines-v2.pdf
A9: TA-PIPE-007 | B9: Primary technical source | C9: The Techno-Economics of Hydrogen Pipelines | D9: 2021 / Version 2 | E9: 5.1 Pipeline Capital Costs | F9: 18 | G9: Indirect-capital-cost breakdown | H9: 0.03 | I9: fraction of TIC | J9: capital_permitting_fraction | K9: Assumptions and Parameters Pipe – Permitting | L9: One-time capital permitting allowance. Distinct from recurring annual licensing and permitting OPEX. Component of the 40% total indirect-cost assumption. | M9: https://transitionaccelerator.ca/wp-content/uploads/2023/06/The-Techno-Economics-of-Hydrogen-Pipelines-v2.pdf
A10: TA-PIPE-008 | B10: Primary technical source | C10: The Techno-Economics of Hydrogen Pipelines | D10: 2021 / Version 2 | E10: 5.1 Pipeline Capital Costs | F10: 17 | G10: Table 5.1 | H10: 1.1 × 63027 × exp(0.0697D) × L | I10: 2009 USD | J10: material_cost_pipeline | K10: Assumptions and Parameters Pipe – Transmission Pipeline Material | L10: D is nominal pipeline diameter in inches and L is pipeline length in miles. Until pipeline thickness is considered, nominal size equates to inner diameter | M10: https://transitionaccelerator.ca/wp-content/uploads/2023/06/The-Techno-Economics-of-Hydrogen-Pipelines-v2.pdf
A11: TA-PIPE-009 | B11: Primary technical source | C11: The Techno-Economics of Hydrogen Pipelines | D11: 2021 / Version 2 | E11: 5.1 Pipeline Capital Costs | F11: 17 | G11: Table 5.1 | H11: 1.1 × (-51.393D² + 43523D + 16171) × L | I11: 2009 USD | J11: construction_labor_cost_pipeline | K11: Assumptions and Parameters Pipe – Transmission Pipeline Labor | L11: D is nominal pipeline diameter in inches and L is pipeline length in miles.. | M11: https://transitionaccelerator.ca/wp-content/uploads/2023/06/The-Techno-Economics-of-Hydrogen-Pipelines-v2.pdf
A12: TA-PIPE-010 | B12: Primary technical source | C12: The Techno-Economics of Hydrogen Pipelines | D12: 2021 / Version 2 | E12: 5.1 Pipeline Capital Costs | F12: 17 | G12: Table 5.1 | H12: 1.1 × (303.13D² + 12908D + 123245) × L | I12: 2009 USD | J12: miscellaneous_cost_pipeline | K12: Assumptions and Parameters Pipe – Transmission Pipeline Miscellaneous | L12: D is nominal pipeline diameter in inches and L is pipeline length in miles. | M12: https://transitionaccelerator.ca/wp-content/uploads/2023/06/The-Techno-Economics-of-Hydrogen-Pipelines-v2.pdf
A13: TA-PIPE-011 | B13: Primary technical source | C13: The Techno-Economics of Hydrogen Pipelines | D13: 2021 / Version 2 | E13: 5.1 Pipeline Capital Costs | F13: 17 | G13: Table 5.1 | H13: (-9E-13D² + 4417.1D + 164241) × L | I13: 2009 USD | J13: right_of_way_cost_pipeline | K13: Assumptions and Parameters Pipe – Transmission Pipeline Right-of-Way | L13: The source does not apply the 1.1 hydrogen cost multiplier to right-of-way. The quadratic coefficient is effectively zero over the modelled diameter range. | M13: https://transitionaccelerator.ca/wp-content/uploads/2023/06/The-Techno-Economics-of-Hydrogen-Pipelines-v2.pdf
A14: TA-PIPE-012 | B14: Primary technical source | C14: The Techno-Economics of Hydrogen Pipelines | D14: 2021 / Version 2 | E14: 5.1 Pipeline Capital Costs | F14: 18 | G14: Equation 14 | H14: TIC + 0.40 × TIC | I14: 2009 USD | J14: total_capital_investment_pipeline | K14: Transition Accelerator Pipe – Total Capital Investment | L14: TCI equals total installed cost plus indirect capital costs. Equivalent to 1.40 × TIC under the source assumption. | M14: https://transitionaccelerator.ca/wp-content/uploads/2023/06/The-Techno-Economics-of-Hydrogen-Pipelines-v2.pdf
A15: TA-PIPE-013 | B15: Primary technical source | C15: The Techno-Economics of Hydrogen Pipelines | D15: 2021 / Version 2 | E15: 5.2 Pipeline Operating Costs | F15: 18 | G15: Equation 15 | H15: Direct labour + indirect labour + insurance + property tax + licensing and permits + O&M | I15: USD/year or converted CAD/year | J15: total_non_energy_opex_pipeline | K15: Transition Accelerator Pipe – Total non-energy OPEX | L15: Source groups labour and annual TCI-based expenses into non-energy pipeline operating cost. Workbook separates labour as variable and the TCI-based items as fixed for TEMOA mapping. | M15: https://transitionaccelerator.ca/wp-content/uploads/2023/06/The-Techno-Economics-of-Hydrogen-Pipelines-v2.pdf
A16: TA-PIPE-014 | B16: Primary technical source | C16: The Techno-Economics of Hydrogen Pipelines | D16: 2021 / Version 2 | E16: 5.2 Pipeline Operating Costs | F16: 18 | G16: Equation 16 | H16: Annual labour hours × labour rate | I16: currency/year | J16: direct_labor_cost_pipeline | K16: Assumptions and Parameters Pipe – Direct labour costs | L16: Calculated annual direct labour expense. Currency year must remain consistent with the labour-rate input. | M16: https://transitionaccelerator.ca/wp-content/uploads/2023/06/The-Techno-Economics-of-Hydrogen-Pipelines-v2.pdf
A17: TA-PIPE-015 | B17: Primary technical source | C17: The Techno-Economics of Hydrogen Pipelines | D17: 2021 / Version 2 | E17: 5.2 Pipeline Operating Costs | F17: 18 | G17: Equation 17 | H17: 8760 × (x / 100000)^0.25 | I17: hours/year | J17: annual_labor_hours_pipeline | K17: Assumptions and Parameters Pipe – Annual labour hours | L17: x is average pipeline use in kg H2/day with a total 8760 hrs used in the model. 8230 hrs should be considered to represent a proper 40-hour work week annually | M17: https://transitionaccelerator.ca/wp-content/uploads/2023/06/The-Techno-Economics-of-Hydrogen-Pipelines-v2.pdf
A18: TA-PIPE-016 | B18: Primary technical source | C18: The Techno-Economics of Hydrogen Pipelines | D18: 2021 / Version 2 | E18: 5.2 Pipeline Operating Costs | F18: 18 | G18: Equation 18 | H18: 0.5 | I18: fraction of direct labour cost | J18: indirect_labor_factor | K18: Assumptions and Parameters Pipe – Indirect labor factor | L18: Applied to annual direct labour cost to represent overhead, head-office, and personnel expenses. | M18: https://transitionaccelerator.ca/wp-content/uploads/2023/06/The-Techno-Economics-of-Hydrogen-Pipelines-v2.pdf
A19: TA-PIPE-017 | B19: Primary technical source | C19: The Techno-Economics of Hydrogen Pipelines | D19: 2021 / Version 2 | E19: 5.2 Pipeline Operating Costs | F19: 18 | G19: Equation 18 | H19: Direct labour × 0.50 | I19: currency/year | J19: indirect_labor_cost_pipeline | K19: Assumptions and Parameters Pipe – Indirect labour costs | L19: Calculated annual indirect labour cost. | M19: https://transitionaccelerator.ca/wp-content/uploads/2023/06/The-Techno-Economics-of-Hydrogen-Pipelines-v2.pdf
A20: TA-PIPE-018 | B20: Primary technical source | C20: The Techno-Economics of Hydrogen Pipelines | D20: 2021 / Version 2 | E20: 5.2 Pipeline Operating Costs | F20: 18–19 | G20: Equation 19 | H20: 0.01 | I20: fraction of TCI per year | J20: insurance_fraction_pipeline | K20: Assumptions and Parameters Pipe – Insurance | L20: Annual fixed cost equal to 1% of pipeline TCI. | M20: https://transitionaccelerator.ca/wp-content/uploads/2023/06/The-Techno-Economics-of-Hydrogen-Pipelines-v2.pdf
A21: TA-PIPE-019 | B21: Primary technical source | C21: The Techno-Economics of Hydrogen Pipelines | D21: 2021 / Version 2 | E21: 5.2 Pipeline Operating Costs | F21: 18–19 | G21: Equation 19 | H21: 0.01 | I21: fraction of TCI per year | J21: property_tax_fraction_pipeline | K21: Assumptions and Parameters Pipe – Property tax | L21: Annual fixed cost equal to 1% of pipeline TCI. | M21: https://transitionaccelerator.ca/wp-content/uploads/2023/06/The-Techno-Economics-of-Hydrogen-Pipelines-v2.pdf
A22: TA-PIPE-020 | B22: Primary technical source | C22: The Techno-Economics of Hydrogen Pipelines | D22: 2021 / Version 2 | E22: 5.2 Pipeline Operating Costs | F22: 18–19 | G22: Equation 19 | H22: 0.001 | I22: fraction of TCI per year | J22: licensing_permitting_fraction_pipeline | K22: Assumptions and Parameters Pipe – Licensing and permitting | L22: Recurring annual licensing and permitting cost equal to 0.1% of TCI. Distinct from the 3% one-time capital permitting allowance. | M22: https://transitionaccelerator.ca/wp-content/uploads/2023/06/The-Techno-Economics-of-Hydrogen-Pipelines-v2.pdf
A23: TA-PIPE-021 | B23: Primary technical source | C23: The Techno-Economics of Hydrogen Pipelines | D23: 2021 / Version 2 | E23: 5.2 Pipeline Operating Costs | F23: 18–19 | G23: Equation 19 | H23: 0.005 | I23: fraction of TCI per year | J23: operations_maintenance_fraction_pipeline | K23: Assumptions and Parameters Pipe – Operating, maintenance and repairs | L23: Recurring annual O&M cost equal to 0.5% of pipeline TCI. | M23: https://transitionaccelerator.ca/wp-content/uploads/2023/06/The-Techno-Economics-of-Hydrogen-Pipelines-v2.pdf
A24: TA-PIPE-022 | B24: Primary technical source | C24: The Techno-Economics of Hydrogen Pipelines | D24: 2021 / Version 2 | E24: 5.2 Pipeline Operating Costs | F24: 19 | G24: Equation 21 | H24: Insurance + property tax + licensing and permits + O&M | I24: currency/year | J24: total_fixed_opex_pipeline | K24: Transition Accelerator Pipe – Total Fixed OPEX | L24: Workbook maps these non-labour annual costs to CostFixed after normalizing by installed capacity and distance. | M24: https://transitionaccelerator.ca/wp-content/uploads/2023/06/The-Techno-Economics-of-Hydrogen-Pipelines-v2.pdf
A25: TA-PIPE-023 | B25: Primary technical source | C25: The Techno-Economics of Hydrogen Pipelines | D25: 2021 / Version 2 | E25: 5.3 Pipeline Levelized Cost | F25: 20 | G25: Table 5.2 | H25: 0.75 | I25: USD/CAD | J25: exchange_rate_usd_per_cad | K25: Assumptions and Parameters Pipe – Exchange rate | L25: 2019 average exchange rate. Because the ratio is USD per CAD, convert USD to CAD by dividing by 0.75. | M25: https://transitionaccelerator.ca/wp-content/uploads/2023/06/The-Techno-Economics-of-Hydrogen-Pipelines-v2.pdf
A26: TA-PIPE-024 | B26: Primary technical source | C26: The Techno-Economics of Hydrogen Pipelines | D26: 2021 / Version 2 | E26: 5.3 Pipeline Levelized Cost | F26: 20 | G26: Table 5.2 | H26: 49.6 | I26: 2019 CAD/hour | J26: pipeline_labor_rate | K26: Assumptions and Parameters Pipe – Labor Rate | L26: The transition reports this as 2019 $CAD but derived from a 2019 US HDSAM model. Should consider updating this with a Canadian representative value | M26: https://transitionaccelerator.ca/wp-content/uploads/2023/06/The-Techno-Economics-of-Hydrogen-Pipelines-v2.pdf
A27: STATCAN-001 | B27: External conversion source | C27: Gross domestic product implicit price indexes | D27: Statistics Canada data used in workbook | E27: Canada GDP implicit price index | F27: N/A | G27: Table 36-10-0130-01 | H27: 88.5 | I27: index | J27: gdp_deflator_2009 | K27: Assumptions and Parameters Pipe – GDP Deflator 2009 | L27: Used as the source-year price index for escalation of 2009 costs. Confirm that the same series and base-year convention are used for all years. | M27: https://www150.statcan.gc.ca/t1/tbl1/en/tv.action?pid=3610013001
A28: STATCAN-002 | B28: External conversion source | C28: Gross domestic product implicit price indexes | D28: Statistics Canada data used in workbook | E28: Canada GDP implicit price index | F28: N/A | G28: Table 36-10-0130-01 | H28: 103.3 | I28: index | J28: gdp_deflator_2019 | K28: Assumptions and Parameters Pipe – GDP Deflator 2019 | L28: Used for conversion of cost inputs originally expressed in 2019 currency. | M28: https://www150.statcan.gc.ca/t1/tbl1/en/tv.action?pid=3610013001
A29: STATCAN-003 | B29: External conversion source | C29: Gross domestic product implicit price indexes | D29: Statistics Canada data used in workbook | E29: Canada GDP implicit price index | F29: N/A | G29: Table 36-10-0130-01 | H29: 105 | I29: index | J29: gdp_deflator_2020 | K29: Assumptions and Parameters Pipe – GDP Deflator 2020 | L29: Workbook target price-year index. Final normalized cost outputs are currently expressed in real 2020 CAD. | M29: https://www150.statcan.gc.ca/t1/tbl1/en/tv.action?pid=3610013001
A30: NRCAN-001 | B30: External economic source | C30: Energy data and analysis – Canadian electricity prices | D30: 2019 | E30: Alberta electricity price | F30: N/A | G30: Provincial electricity-price data | H30: 0.11 | I30: 2019 CAD/kWh | J30: electricity_price_alberta | K30: Assumptions and Parameters Pipe – Electricity Cost | L30: Used to reproduce monetary compressor electricity OPEX. The preferred CANOE/TEMOA mapping retains electricity as a physical input coefficient rather than embedding this price permanently in CostVariable. | M30: https://natural-resources.canada.ca/science-data/data-analysis/energy-data-analysis
A31: WEI-PIPE-001 | B31: Secondary implementation source | C31: Evaluating Environmental and Economic Trade-offs in Centralized and Decentralized Hydrogen Production — A Case Study on Canadian Steel | D31: 2026 | E31: 2.5.1 Pipeline LCA | F31: 55–56 | G31: Equation 2.10 | H31: (P × D) / (2 × S × F × L × J × T) | I31: mm | J31: t_required | K31: Transition Accelerator Pipe | L31: Minimum required pipeline wall thickness. In the thesis, P and S are in MPa and D is outside diameter in mm. The current workbook does not consider outer diameter into costs. Must validate how this is factored into costs.
A32: WEI-PIPE-002 | B32: Secondary implementation source | C32: Evaluating Environmental and Economic Trade-offs in Centralized and Decentralized Hydrogen Production — A Case Study on Canadian Steel | D32: 2026 | E32: 2.5.1 Pipeline LCA | F32: 55–56 | G32: Equation 2.10 | H32: 483 | I32: MPa | J32: S_yield | K32: Assumptions and Parameters Pipe | L32: Specified minimum yield strength of the selected pipeline steel. The thesis identifies this as an assumption adapted from prior CO2 pipeline literature.
A33: WEI-PIPE-003 | B33: Secondary implementation source | C33: Evaluating Environmental and Economic Trade-offs in Centralized and Decentralized Hydrogen Production — A Case Study on Canadian Steel | D33: 2026 | E33: 2.5.1 Pipeline LCA | F33: 55–56 | G33: Equation 2.10 | H33: 0.72 | I33: dimensionless | J33: F_design | K33: Assumptions and Parameters Pipe | L33: Design factor used in the wall-thickness calculation. The thesis notes that this factor varies with location and pipeline class.
A34: WEI-PIPE-004 | B34: Secondary implementation source | C34: Evaluating Environmental and Economic Trade-offs in Centralized and Decentralized Hydrogen Production — A Case Study on Canadian Steel | D34: 2026 | E34: 2.5.1 Pipeline LCA | F34: 55–56 | G34: Equation 2.10 | H34: 1 | I34: dimensionless | J34: L_location | K34: Assumptions and Parameters Pipe | L34: Locational factor. The thesis holds this at 1.0 and addresses geographic differences separately through routing or cost penalties. Do not confuse this symbol L with physical pipeline length.
A35: WEI-PIPE-005 | B35: Secondary implementation source | C35: Evaluating Environmental and Economic Trade-offs in Centralized and Decentralized Hydrogen Production — A Case Study on Canadian Steel | D35: 2026 | E35: 2.5.1 Pipeline LCA | F35: 55–56 | G35: Equation 2.10 | H35: 1 | I35: dimensionless | J35: J_joint | K35: Assumptions and Parameters Pipe | L35: Joint factor based on seamless pipe.
A36: WEI-PIPE-006 | B36: Secondary implementation source | C36: Evaluating Environmental and Economic Trade-offs in Centralized and Decentralized Hydrogen Production — A Case Study on Canadian Steel | D36: 2026 | E36: 2.5.1 Pipeline LCA | F36: 55–56 | G36: Equation 2.10 | H36: 1 | I36: dimensionless | J36: T_temperature_factor | K36: Assumptions and Parameters Pipe | L36: Temperature derating factor. Set to 1.0 because the pipeline is assumed not to operate above the applicable temperature threshold. This is not a temperature in kelvin despite the current workbook unit label.
A37: TA-PIPE-025 | B37: Primary technical source | C37: The Techno-Economics of Hydrogen Pipelines | D37: 2021 / Version 2 | E37: 4 Gas Pipeline Hydraulics | F37: 10–11 | G37: Equation 1 | H37: 1.1494 × 10^-3 × (Tb/Pb) × [((P1² - exp(s)P2²)/(G × Tf × Le × Z × f))^0.5] × D^2.5 | I37: Sm3/day | J37: Q | K37: Transition Accelerator Pipe | L37: General Flow Equation used to calculate standard volumetric hydrogen flow. D is inside diameter in mm; P1 and P2 must be absolute pressures in kPa. | M37: https://transitionaccelerator.ca/wp-content/uploads/2023/06/The-Techno-Economics-of-Hydrogen-Pipelines-v2.pdf
A38: TA-PIPE-026 | B38: Primary technical source | C38: The Techno-Economics of Hydrogen Pipelines | D38: 2021 / Version 2 | E38: 4 Gas Pipeline Hydraulics | F38: 10–11 | G38: Equation 1 | H38: Variable | I38: mm | J38: D_inner | K38: Transition Accelerator Pipe | L38: Inside pipeline diameter used by the General Flow Equation. This is not automatically equal to nominal pipe size or outside diameter. The current workbook assumes equality for the cost cases and should flag this approximation. | M38: https://transitionaccelerator.ca/wp-content/uploads/2023/06/The-Techno-Economics-of-Hydrogen-Pipelines-v2.pdf
A39: TA-PIPE-027 | B39: Primary technical source | C39: The Techno-Economics of Hydrogen Pipelines | D39: 2021 / Version 2 | E39: 4 Gas Pipeline Hydraulics | F39: 10–11 | G39: Equation 1 variable definition | H39: 288.706 | I39: K | J39: T_b | K39: Assumptions and Parameters Pipe | L39: Base temperature associated with the standard volumetric flow convention. Workbook rounds the value to 288.7 K. | M39: https://transitionaccelerator.ca/wp-content/uploads/2023/06/The-Techno-Economics-of-Hydrogen-Pipelines-v2.pdf
A40: TA-PIPE-028 | B40: Primary technical source | C40: The Techno-Economics of Hydrogen Pipelines | D40: 2021 / Version 2 | E40: 4 Gas Pipeline Hydraulics | F40: 10–11 | G40: Equation 1 variable definition | H40: 101.352 | I40: kPa absolute | J40: P_b | K40: Assumptions and Parameters Pipe | L40: Base pressure associated with the standard volumetric flow convention. The workbook currently uses 101.325 kPa; this small discrepancy should be documented rather than silently treated as identical. | M40: https://transitionaccelerator.ca/wp-content/uploads/2023/06/The-Techno-Economics-of-Hydrogen-Pipelines-v2.pdf
A41: TA-PIPE-029 | B41: Primary technical source | C41: The Techno-Economics of Hydrogen Pipelines | D41: 2021 / Version 2 | E41: 6.1 Case Study: Input Parameters | F41: 21 | G41: Table 6.1 | H41: 70 | I41: bar absolute | J41: P_1 | K41: Assumptions and Parameters Pipe | L41: Inlet pipeline pressure. Workbook converts this to 7000 kPa. The source explicitly defines pipeline pressures in the flow equation as absolute rather than gauge pressure. | M41: https://transitionaccelerator.ca/wp-content/uploads/2023/06/The-Techno-Economics-of-Hydrogen-Pipelines-v2.pdf
A42: MODEL-PIPE-001 | B42: Modeller assumption | C42: Workbook methodology | D42: Current workbook | E42: Reference 250 km pipeline segment | F42: N/A | G42: Selected outlet-pressure assumption | H42: 28 | I42: bar absolute | J42: P_2 | K42: Assumptions and Parameters Pipe | L42: Outlet pressure selected to match the compressor suction pressure and the 28-to-70 bar recompression cycle used in the thesis implementation. Workbook converts this to 2800 kPa. This is not the Table 6.1 outlet-velocity assumption from the Transition Accelerator case study.
A43: MODEL-PIPE-002 | B43: Modeller assumption | C43: Workbook methodology | D43: Current workbook | E43: Reference elevation profile | F43: N/A | G43: Inlet elevation | H43: 2 | I43: m | J43: H_1 | K43: Assumptions and Parameters Pipe | L43: Arbitrary near-flat reference elevation used to avoid a zero elevation-adjustment case. This is not a source-derived geographic elevation. Replace with corridor-specific elevations or set both elevations equal when appropriate.
A44: MODEL-PIPE-003 | B44: Modeller assumption | C44: Workbook methodology | D44: Current workbook | E44: Reference elevation profile | F44: N/A | G44: Outlet elevation | H44: 1 | I44: m | J44: H_2 | K44: Assumptions and Parameters Pipe | L44: Arbitrary near-flat reference elevation paired with H1. The resulting elevation effect is negligible but nonzero.
A45: WEI-PIPE-007 | B45: Secondary implementation source | C45: Evaluating Environmental and Economic Trade-offs in Centralized and Decentralized Hydrogen Production — A Case Study on Canadian Steel | D45: 2026 | E45: 2.5.1 Pipeline LCA | F45: 54–55 | G45: Equation 2.7 assumptions | H45: 288.7 | I45: K | J45: T_f | K45: Assumptions and Parameters Pipe | L45: Average flowing temperature assumed equal to ambient temperature for a 250 km segment. The Transition Accelerator Table 6.1 case study instead reports 288.15 K. The workbook follows the thesis implementation.
A46: WEI-PIPE-008 | B46: Secondary implementation source | C46: Evaluating Environmental and Economic Trade-offs in Centralized and Decentralized Hydrogen Production — A Case Study on Canadian Steel | D46: 2026 | E46: 2.5.1 Pipeline LCA | F46: 54–55 | G46: Equation 2.6 / compressibility assumption | H46: 1.03 | I46: dimensionless | J46: Z | K46: Assumptions and Parameters Pipe | L46: Average hydrogen compressibility factor selected for the assumed average pressure and temperature. Z should be recalculated if pressure or temperature assumptions change.
A47: TA-PIPE-030 | B47: Primary technical source | C47: The Techno-Economics of Hydrogen Pipelines | D47: 2021 / Version 2 | E47: 4 Gas Pipeline Hydraulics / 6.1 Case Study | F47: 11 and 21 | G47: Equation 1 variable definition / Table 6.1 | H47: 0.0696 | I47: dimensionless | J47: G | K47: Assumptions and Parameters Pipe | L47: Hydrogen specific gravity relative to air. Used in the elevation, flow, and erosional-velocity equations. | M47: https://transitionaccelerator.ca/wp-content/uploads/2023/06/The-Techno-Economics-of-Hydrogen-Pipelines-v2.pdf
A48: WEI-PIPE-009 | B48: Secondary implementation source | C48: Evaluating Environmental and Economic Trade-offs in Centralized and Decentralized Hydrogen Production — A Case Study on Canadian Steel | D48: 2026 | E48: 2.5.1 Pipeline LCA | F48: 54–55 | G48: Pipeline-segment assumption | H48: 250 | I48: km | J48: L_pipe | K48: Assumptions and Parameters Pipe | L48: Physical length of one pipeline and recompression segment. The thesis models a compressor at the beginning of each 250 km segment. The Transition Accelerator case study uses 500 km pipe sections within a 1500 km system.
A49: TA-PIPE-031 | B49: Primary technical source | C49: The Techno-Economics of Hydrogen Pipelines | D49: 2021 / Version 2 | E49: 4.1 Key Parameters for Calculating Hydrogen Flow | F49: 13 | G49: Equations 5–6 / adopted case-study value | H49: 0.0094 | I49: dimensionless | J49: f_Darcy | K49: Assumptions and Parameters Pipe | L49: Darcy friction factor adopted as a fixed value. The source explains that friction factor depends on Reynolds number, roughness, and diameter and normally requires iterative solution using the Colebrook–White equation. It should be recalculated when the hydraulic design changes. | M49: https://transitionaccelerator.ca/wp-content/uploads/2023/06/The-Techno-Economics-of-Hydrogen-Pipelines-v2.pdf
A50: TA-PIPE-032 | B50: Primary technical source | C50: The Techno-Economics of Hydrogen Pipelines | D50: 2021 / Version 2 | E50: 4.1 Key Parameters for Calculating Hydrogen Flow | F50: 14 | G50: Equation 8 variable definition | H50: 8.314 | I50: kPa·m3/(kmol·K) | J50: R | K50: Assumptions and Parameters Pipe | L50: Universal gas constant in the unit basis used by the erosional-velocity equation. | M50: https://transitionaccelerator.ca/wp-content/uploads/2023/06/The-Techno-Economics-of-Hydrogen-Pipelines-v2.pdf
A51: TA-PIPE-033 | B51: Primary technical source | C51: The Techno-Economics of Hydrogen Pipelines | D51: 2021 / Version 2 | E51: 4.1 Key Parameters for Calculating Hydrogen Flow | F51: 14 | G51: Equation 9 | H51: 0.0834 | I51: kg H2/Sm3 | J51: rho_H2_b | K51: Assumptions and Parameters Pipe | L51: Hydrogen density or mass-conversion factor at the report’s standard conditions. Multiplied by Q to calculate daily hydrogen mass capacity. | M51: https://transitionaccelerator.ca/wp-content/uploads/2023/06/The-Techno-Economics-of-Hydrogen-Pipelines-v2.pdf
A52: MODEL-PIPE-004 | B52: Modeller convention | C52: Workbook methodology | D52: Current workbook | E52: Annual capacity conversion | F52: N/A | G52: Calendar-year conversion | H52: 365 | I52: days/year | J52: n_days | K52: Assumptions and Parameters Pipe | L52: Converts daily design capacity to annual capacity. This assumes continuous operation and is a unit conversion, not an availability or capacity-factor assumption. Availability should be represented separately if required.
A53: TA-PIPE-034 | B53: Primary technical source | C53: The Techno-Economics of Hydrogen Pipelines | D53: 2021 / Version 2 | E53: 4 Gas Pipeline Hydraulics | F53: 11 | G53: Equation 2 | H53: 0.0684 × G × ((H2 - H1)/(Tf × Z)) | I53: dimensionless | J53: s | K53: Transition Accelerator Pipe | L53: Elevation adjustment parameter used in the General Flow Equation. The workbook’s near-flat elevation assumptions make this term very small. | M53: https://transitionaccelerator.ca/wp-content/uploads/2023/06/The-Techno-Economics-of-Hydrogen-Pipelines-v2.pdf
A54: TA-PIPE-035 | B54: Primary technical source | C54: The Techno-Economics of Hydrogen Pipelines | D54: 2021 / Version 2 | E54: 4 Gas Pipeline Hydraulics | F54: 11 | G54: Equation 3 | H54: L × ((exp(s) - 1)/s) | I54: km | J54: L_e | K54: Transition Accelerator Pipe | L54: Equivalent pipeline length after accounting for elevation. For s approaching zero, the mathematical limit is Le = L; spreadsheet implementations should guard against direct division by zero. | M54: https://transitionaccelerator.ca/wp-content/uploads/2023/06/The-Techno-Economics-of-Hydrogen-Pipelines-v2.pdf
A55: WEI-PIPE-010 | B55: Secondary implementation source | C55: Evaluating Environmental and Economic Trade-offs in Centralized and Decentralized Hydrogen Production — A Case Study on Canadian Steel | D55: 2026 | E55: 2.5.1 Pipeline LCA | F55: 54–55 | G55: Equation 2.8 | H55: (2/3) × ((P1^3 - P2^3)/(P1^2 - P2^2)) | I55: kPa | J55: P_avg | K55: Transition Accelerator Pipe | L55: Average pipeline pressure used to select the compressibility factor and in the wall-thickness implementation. The workbook formula follows the thesis equation.
A56: TA-PIPE-036 | B56: Primary technical source | C56: The Techno-Economics of Hydrogen Pipelines | D56: 2021 / Version 2 | E56: 4.1 Key Parameters for Calculating Hydrogen Flow | F56: 14 | G56: Equation 8 | H56: 100 × sqrt(0.05131 × Z × R × T/(G × P)) | I56: m/s | J56: V_max | K56: Transition Accelerator Pipe | L56: Approximate erosional velocity representing an upper bound on allowable gas velocity. The workbook evaluates the expression using inlet pressure, which is conservative relative to using a lower pressure but should be stated explicitly. | M56: https://transitionaccelerator.ca/wp-content/uploads/2023/06/The-Techno-Economics-of-Hydrogen-Pipelines-v2.pdf
A57: TA-PIPE-037 | B57: Primary technical source | C57: The Techno-Economics of Hydrogen Pipelines | D57: 2021 / Version 2 | E57: 4 Gas Pipeline Hydraulics | F57: 10–11 | G57: Equation 1 | H57: Calculated | I57: Sm3/day | J57: Q | K57: Transition Accelerator Pipe | L57: Calculated standard volumetric flow for each selected inner-diameter case. This is an output rather than an independently sourced default parameter. | M57: https://transitionaccelerator.ca/wp-content/uploads/2023/06/The-Techno-Economics-of-Hydrogen-Pipelines-v2.pdf
A58: TA-PIPE-038 | B58: Primary technical source | C58: The Techno-Economics of Hydrogen Pipelines | D58: 2021 / Version 2 | E58: 4.1 Key Parameters for Calculating Hydrogen Flow | F58: 14 | G58: Equation 9 | H58: Q × 0.0834 | I58: kg H2/day | J58: C_day | K58: Transition Accelerator Pipe | L58: Daily hydrogen mass capacity corresponding to the calculated standard volumetric flow. | M58: https://transitionaccelerator.ca/wp-content/uploads/2023/06/The-Techno-Economics-of-Hydrogen-Pipelines-v2.pdf
A59: MODEL-PIPE-005 | B59: Derived workbook output | C59: Workbook methodology | D59: Current workbook | E59: Annual capacity conversion | F59: N/A | G59: Cday × 365 | H59: kg H2/year | I59: C_year_kg | J59: Transition Accelerator Pipe | K59: Annual hydrogen capacity before conversion from kilograms to tonnes. Assumes full-year operation.
A60: MODEL-PIPE-006 | B60: Derived workbook output | C60: Workbook methodology | D60: Current workbook | E60: Annual capacity conversion | F60: N/A | G60: (Cday × 365) / 1000 | H60: t H2/year | I60: C_year_t | J60: Transition Accelerator Pipe | K60: Annual hydrogen capacity in metric tonnes per year. This is the capacity basis subsequently used for pipeline cost normalization.
A62: Source Extraction Log: H2 Compressor Stations
A63: Source_ID | B63: Source_Type | C63: Title | D63: Year/Version | E63: Section | F63: Source Page | G63: Table / Equation / Figure | H63: Default Value | I63: Unit | J63: Workbook symbol | K63: Workbook Section | L63: Notes | M63: Source URL
A64: TA-COMP-001 | B64: Primary technical source | C64: The Techno-Economics of Hydrogen Compression | D64: 2021 / Version 2.0 | E64: 3.1 Power Calculation for Single-Stage Compressors | F64: 13 | G64: Power-equation variable definition | H64: 0.002 | I64: kg/mol | J64: M_H2 | K64: Transition Accelerator Compress | L64: Hydrogen molar mass used to convert mass flow into molar flow. The workbook rounds the physical molar mass to 0.002 kg/mol; a more precise value could be retained if consistency is maintained throughout. | M64: https://transitionaccelerator.ca/wp-content/uploads/2023/06/The-Techno-Economics-of-Hydrogen-Compression.pdf
A65: TA-COMP-002 | B65: Primary technical source | C65: The Techno-Economics of Hydrogen Compression | D65: 2021 / Version 2.0 | E65: 3.1 Power Calculation for Single-Stage Compressors | F65: 13 | G65: Power-equation variable definition | H65: 1.41 | I65: dimensionless | J65: k | K65: Transition Accelerator Compress | L65: Ratio of hydrogen specific heat at constant pressure to specific heat at constant volume. The workbook uses 1.405, which is a minor refinement from the source-rounded value of 1.41. | M65: https://transitionaccelerator.ca/wp-content/uploads/2023/06/The-Techno-Economics-of-Hydrogen-Compression.pdf
A66: WEI-COMP-001 | B66: Secondary implementation source | C66: Evaluating Environmental and Economic Trade-offs in Centralized and Decentralized Hydrogen Production — A Case Study on Canadian Steel | D66: 2026 | E66: 2.5.2 Compressor LCA | F66: 58–60 | G66: Equation 2.11 assumptions | H66: 1.03 | I66: dimensionless | J66: Z_comp | K66: Transition Accelerator Compress | L66: Average hydrogen compressibility factor used by the compressor calculation. The workbook applies the same value used in the pipeline model. It should correspond to the assumed pressure and temperature range.
A67: TA-COMP-003 | B67: Primary technical source | C67: The Techno-Economics of Hydrogen Compression | D67: 2021 / Version 2.0 | E67: 3.2 Power Calculation for Multistage Compressors | F67: 13–15 | G67: Multistage compressor assumptions | H67: 2.1 | I67: maximum pressure ratio per stage | J67: x_stage_max | K67: Transition Accelerator Compress | L67: Maximum target pressure ratio per compressor stage for the reference pipeline compressor. The report notes that the case-study reciprocating compressor uses a per-stage ratio of approximately 2.1. | M67: https://transitionaccelerator.ca/wp-content/uploads/2023/06/The-Techno-Economics-of-Hydrogen-Compression.pdf
A68: TA-COMP-004 | B68: Primary technical source | C68: The Techno-Economics of Hydrogen Compression | D68: 2021 / Version 2.0 | E68: 3.1 Power Calculation for Single-Stage Compressors | F68: 13 | G68: Power-equation variable definition | H68: 8.314 | I68: J/(mol·K) | J68: R_comp | K68: Transition Accelerator Compress | L68: Universal gas constant in the compressor power-equation unit basis. This is the same physical constant used in the pipeline sheet but expressed in J/(mol·K). | M68: https://transitionaccelerator.ca/wp-content/uploads/2023/06/The-Techno-Economics-of-Hydrogen-Compression.pdf
A69: WEI-COMP-002 | B69: Secondary implementation source | C69: Evaluating Environmental and Economic Trade-offs in Centralized and Decentralized Hydrogen Production — A Case Study on Canadian Steel | D69: 2026 | E69: 2.5.2 Compressor LCA | F69: 58–60 | G69: Compressor inlet-temperature assumption | H69: 289 | I69: K | J69: T_suction | K69: Transition Accelerator Compress | L69: Suction temperature assumed approximately equal to ambient temperature. The workbook uses 289 K, while the pipeline flowing-temperature assumption is 288.7 K.
A70: WEI-COMP-003 | B70: Secondary implementation source | C70: Evaluating Environmental and Economic Trade-offs in Centralized and Decentralized Hydrogen Production — A Case Study on Canadian Steel | D70: 2026 | E70: 2.5.2 Compressor LCA | F70: 58–60 | G70: Reference pressure cycle | H70: 28 | I70: bar absolute | J70: P_suction | K70: Transition Accelerator Compress | L70: Compressor suction pressure corresponding to the pipeline outlet pressure. The Transition Accelerator pipeline case study uses 20 bar for some compressor calculations, while the workbook follows the thesis 28-to-70 bar cycle.
A71: WEI-COMP-004 | B71: Secondary implementation source | C71: Evaluating Environmental and Economic Trade-offs in Centralized and Decentralized Hydrogen Production — A Case Study on Canadian Steel | D71: 2026 | E71: 2.5.2 Compressor LCA | F71: 58–60 | G71: Reference pressure cycle | H71: 70 | I71: bar absolute | J71: P_discharge | K71: Transition Accelerator Compress | L71: Compressor discharge pressure corresponding to the pipeline inlet pressure. Used with 28 bar suction pressure to restore pipeline pressure after each 250 km segment.
A72: TA-COMP-005 | B72: Primary technical source | C72: The Techno-Economics of Hydrogen Compression | D72: 2021 / Version 2.0 | E72: 4.1 Assumptions Used | F72: 17 | G72: Prime-mover assumption | H72: 0.95 | I72: dimensionless | J72: eta_motor | K72: Transition Accelerator Compress | L72: Electric-motor efficiency. Rated electrical motor power is calculated by dividing compressor shaft power by motor efficiency. | M72: https://transitionaccelerator.ca/wp-content/uploads/2023/06/The-Techno-Economics-of-Hydrogen-Compression.pdf
A73: TA-COMP-006 | B73: Primary technical source | C73: The Techno-Economics of Hydrogen Compression | D73: 2021 / Version 2.0 | E73: 4.1 Assumptions Used | F73: 17 | G73: Pipeline-compressor assumption | H73: 0.8 | I73: dimensionless | J73: eta_isen_reference | K73: Transition Accelerator Compress | L73: Reference isentropic efficiency used for large hydrogen pipeline compressors in the compression brief. The current workbook instead applies a capacity-dependent efficiency derived from the thesis implementation. | M73: https://transitionaccelerator.ca/wp-content/uploads/2023/06/The-Techno-Economics-of-Hydrogen-Compression.pdf
A74: WEI-COMP-005 | B74: Secondary implementation source | C74: Evaluating Environmental and Economic Trade-offs in Centralized and Decentralized Hydrogen Production — A Case Study on Canadian Steel | D74: 2026 | E74: 3.3 Hydrogen Distribution LCA | F74: 91–92 | G74: Figure 3.10 / efficiency scaling method | H74: 0.88 | I74: dimensionless | J74: eta_isen_max | K74: Transition Accelerator Compress | L74: Maximum isentropic-efficiency cap. The thesis allows efficiency to increase with compressor scale until it reaches 0.88, after which it remains constant. This differs from the Transition Accelerator fixed 0.80 assumption.
A75: TA-COMP-007 | B75: Primary technical source | C75: The Techno-Economics of Hydrogen Compression | D75: 2021 / Version 2.0 | E75: 4.1 Assumptions Used | F75: 17 | G75: Maximum pipeline-compressor capacity | H75: 16000 | I75: kW per compressor | J75: P_unit_max | K75: Transition Accelerator Compress | L75: Maximum rated capacity of one large pipeline compressor assumed by the report. Above this size, multiple compressor units should be represented. The current workbook calculates stations substantially above 16 MW without explicitly splitting them into parallel units, which should be reviewed. | M75: https://transitionaccelerator.ca/wp-content/uploads/2023/06/The-Techno-Economics-of-Hydrogen-Compression.pdf
A76: TA-COMP-008 | B76: Primary technical source | C76: The Techno-Economics of Hydrogen Compression | D76: 2021 / Version 2.0 | E76: 3.2 Power Calculation for Multistage Compressors | F76: 13–15 | G76: Multistage assumptions | H76: Equal work per stage | I76: dimensionless | J76: multistage_equal_work | K76: Transition Accelerator Compress | L76: Assumes that compressor work is equal at each stage. This is a methodological assumption rather than a numeric input. | M76: https://transitionaccelerator.ca/wp-content/uploads/2023/06/The-Techno-Economics-of-Hydrogen-Compression.pdf
A77: TA-COMP-009 | B77: Primary technical source | C77: The Techno-Economics of Hydrogen Compression | D77: 2021 / Version 2.0 | E77: 3.2 Power Calculation for Multistage Compressors | F77: 13–15 | G77: Multistage assumptions | H77: Equal pressure ratio per stage | I77: dimensionless | J77: multistage_equal_ratio | K77: Transition Accelerator Compress | L77: Assumes the same pressure ratio across each compressor stage. | M77: https://transitionaccelerator.ca/wp-content/uploads/2023/06/The-Techno-Economics-of-Hydrogen-Compression.pdf
A78: TA-COMP-010 | B78: Primary technical source | C78: The Techno-Economics of Hydrogen Compression | D78: 2021 / Version 2.0 | E78: 3.2 Power Calculation for Multistage Compressors | F78: 13–15 | G78: Multistage assumptions | H78: Intercool to original suction temperature | I78: K | J78: multistage_intercooling | K78: Transition Accelerator Compress | L78: Assumes that hydrogen is cooled back to the original first-stage suction temperature after each compression stage. | M78: https://transitionaccelerator.ca/wp-content/uploads/2023/06/The-Techno-Economics-of-Hydrogen-Compression.pdf
A79: TA-COMP-011 | B79: Primary technical source | C79: The Techno-Economics of Hydrogen Compression | D79: 2021 / Version 2.0 | E79: 3.2 Power Calculation for Multistage Compressors | F79: 13–15 | G79: Multistage assumptions | H79: No intercooler pressure drop or heat loss | I79: dimensionless | J79: ideal_intercooler | K79: Transition Accelerator Compress | L79: Assumes no pressure drop and no additional heat loss in the intercoolers. This makes the thermodynamic calculation idealized. | M79: https://transitionaccelerator.ca/wp-content/uploads/2023/06/The-Techno-Economics-of-Hydrogen-Compression.pdf
A80: MODEL-COMP-001 | B80: Derived workbook parameter | C80: Workbook methodology | D80: Current workbook | E80: Compressor staging | F80: N/A | G80: Overall compression ratio | H80: P_discharge / P_suction | I80: dimensionless | J80: r_p | K80: Transition Accelerator Compress | L80: Overall compressor pressure ratio. With 70 bar discharge and 28 bar suction, the workbook obtains 2.5.
A81: TA-COMP-012 | B81: Primary technical source | C81: The Techno-Economics of Hydrogen Compression | D81: 2021 / Version 2.0 | E81: 3.2 Power Calculation for Multistage Compressors | F81: 13–15 | G81: Stage-count equation | H81: ln(r_p) / ln(x_stage_max) | I81: stages | J81: N_raw | K81: Transition Accelerator Compress | L81: Unrounded number of compressor stages required so the per-stage pressure ratio does not exceed the selected maximum. | M81: https://transitionaccelerator.ca/wp-content/uploads/2023/06/The-Techno-Economics-of-Hydrogen-Compression.pdf
A82: TA-COMP-013 | B82: Primary technical source | C82: The Techno-Economics of Hydrogen Compression | D82: 2021 / Version 2.0 | E82: 3.2 Power Calculation for Multistage Compressors | F82: 13–15 | G82: Stage-count equation | H82: CEILING(N_raw) | I82: stages | J82: N_stages | K82: Transition Accelerator Compress | L82: Compressor stage count rounded upward to the nearest integer. The workbook obtains two stages for the 28-to-70 bar reference cycle. | M82: https://transitionaccelerator.ca/wp-content/uploads/2023/06/The-Techno-Economics-of-Hydrogen-Compression.pdf
A83: MODEL-COMP-002 | B83: Derived workbook parameter | C83: Workbook methodology | D83: Current workbook | E83: Mass-to-molar-flow conversion | F83: N/A | G83: (C_day / M_H2) / 86400 | H83: mol H2/s | I83: q_M | J83: Transition Accelerator Compress | K83: Converts daily hydrogen mass capacity into molar flow. The 86,400 denominator converts days to seconds.
A84: TA-COMP-014 | B84: Primary technical source | C84: The Techno-Economics of Hydrogen Compression | D84: 2021 / Version 2.0 | E84: 3.2 Power Calculation for Multistage Compressors | F84: 13–15 | G84: Multistage isentropic power equation | H84: N × [k/(k−1)] × [Z/eta_isen] × T_suction × q_M × R × [(P_discharge/P_suction)^((k−1)/(N×k)) − 1] | I84: W | J84: P_comp | K84: Transition Accelerator Compress | L84: Isentropic multistage compressor shaft-power equation with ideal intercooling. Pressure values may be used as a ratio in consistent units. | M84: https://transitionaccelerator.ca/wp-content/uploads/2023/06/The-Techno-Economics-of-Hydrogen-Compression.pdf
A85: TA-COMP-015 | B85: Primary technical source | C85: The Techno-Economics of Hydrogen Compression | D85: 2021 / Version 2.0 | E85: 4.1 Assumptions Used | F85: 17 | G85: Motor-power conversion | H85: P_comp / eta_motor | I85: kW | J85: P_rated | K85: Transition Accelerator Compress | L85: Rated electrical motor power after accounting for the 95% motor efficiency. Confirm that the compressor power is converted from W to kW before applying the cost correlation. | M85: https://transitionaccelerator.ca/wp-content/uploads/2023/06/The-Techno-Economics-of-Hydrogen-Compression.pdf
A86: MODEL-COMP-003 | B86: Derived workbook output | C86: Workbook methodology | D86: Current workbook | E86: Compressor electricity intensity | F86: N/A | G86: P_rated × 24 / C_day | H86: kWh/kg H2 | I86: electricity_intensity | J86: Transition Accelerator Compress | K86: Electrical energy consumed per kilogram of hydrogen at full daily design throughput. Equivalent numerically to MWh per tonne H2.
A87: TA-COMP-016 | B87: Primary technical source | C87: The Techno-Economics of Hydrogen Compression | D87: 2021 / Version 2.0 | E87: 4.2 Determining the Capital Cost of a Hydrogen Compressor | F87: 18 | G87: Table 4.1 | H87: 3083.3 | I87: 2019 CAD coefficient | J87: UC_coefficient_pipeline | K87: Transition Accelerator Compress | L87: Cost coefficient for a high-flow, moderate-compression-ratio pipeline compressor. The coefficient already incorporates escalation to 2019 and conversion to Canadian dollars. | M87: https://transitionaccelerator.ca/wp-content/uploads/2023/06/The-Techno-Economics-of-Hydrogen-Compression.pdf
A88: TA-COMP-017 | B88: Primary technical source | C88: The Techno-Economics of Hydrogen Compression | D88: 2021 / Version 2.0 | E88: 4.2 Determining the Capital Cost of a Hydrogen Compressor | F88: 18 | G88: Table 4.1 | H88: 0.8335 | I88: dimensionless | J88: SF_pipeline | K88: Transition Accelerator Compress | L88: Economies-of-scale exponent for the pipeline-compressor uninstalled-cost correlation. | M88: https://transitionaccelerator.ca/wp-content/uploads/2023/06/The-Techno-Economics-of-Hydrogen-Compression.pdf
A89: TA-COMP-018 | B89: Primary technical source | C89: The Techno-Economics of Hydrogen Compression | D89: 2021 / Version 2.0 | E89: 4.2 Determining the Capital Cost of a Hydrogen Compressor | F89: 18 | G89: Table 4.1 | H89: 2 | I89: multiplier | J89: IF_pipeline | K89: Transition Accelerator Compress | L89: Installation factor used to convert compressor uninstalled cost into total installed cost. | M89: https://transitionaccelerator.ca/wp-content/uploads/2023/06/The-Techno-Economics-of-Hydrogen-Compression.pdf
A90: TA-COMP-019 | B90: Primary technical source | C90: The Techno-Economics of Hydrogen Compression | D90: 2021 / Version 2.0 | E90: 4.2 Determining the Capital Cost of a Hydrogen Compressor | F90: 18 | G90: Table 4.1 | H90: 3083.3 × P_rated^0.8335 | I90: 2019 CAD/compressor station | J90: UC_pipeline | K90: Transition Accelerator Compress | L90: Uninstalled compressor cost. P_rated is rated motor power in kW. The workbook should not apply the separate 1.179 CEPCI factor or 0.75 exchange rate again because these are already embedded in the published 2019 CAD coefficient. | M90: https://transitionaccelerator.ca/wp-content/uploads/2023/06/The-Techno-Economics-of-Hydrogen-Compression.pdf
A91: TA-COMP-020 | B91: Primary technical source | C91: The Techno-Economics of Hydrogen Compression | D91: 2021 / Version 2.0 | E91: 4.2 Determining the Capital Cost of a Hydrogen Compressor | F91: 18 | G91: Table 4.1 | H91: UC_pipeline × IF_pipeline | I91: 2019 CAD/compressor station | J91: TIC_comp | K91: Transition Accelerator Compress | L91: Total installed compressor cost, including equipment purchase and installation labour and parts. | M91: https://transitionaccelerator.ca/wp-content/uploads/2023/06/The-Techno-Economics-of-Hydrogen-Compression.pdf
A92: WEI-COMP-006 | B92: Secondary implementation source | C92: Evaluating Environmental and Economic Trade-offs in Centralized and Decentralized Hydrogen Production — A Case Study on Canadian Steel | D92: 2026 | E92: 2.5.4.2 Compressor Costing | F92: 62–63 | G92: Equation 2.19 | H92: 3083.3 × P_rated^0.8335 × 2 | I92: 2019 CAD/compressor station | J92: TIC_comp | K92: Transition Accelerator Compress | L92: Thesis implementation of the Transition Accelerator pipeline-compressor cost correlation. The thesis text describes the output as 2019 USD in one location, but the Transition Accelerator Table 4.1 explicitly presents the correlation in 2019 CAD; use the primary source currency definition.
A93: TA-COMP-021 | B93: Primary technical source | C93: The Techno-Economics of Hydrogen Compression | D93: 2021 / Version 2.0 | E93: 4.2 Determining the Capital Cost of a Hydrogen Compressor | F93: 18 | G93: CEPCI escalation embedded in Table 4.1 | H93: 619.2 / 525.4 = 1.179 | I93: multiplier | J93: CEPCI_2007_to_2019 | K93: Assumptions and Parameter Comp | L93: Escalation factor used by the report when deriving the published 2019 CAD cost coefficient from the underlying 2007 HDSAM correlation. This factor is provenance for the coefficient and should not be applied again to 3083.3. | M93: https://transitionaccelerator.ca/wp-content/uploads/2023/06/The-Techno-Economics-of-Hydrogen-Compression.pdf
A94: TA-COMP-022 | B94: Primary technical source | C94: The Techno-Economics of Hydrogen Compression | D94: 2021 / Version 2.0 | E94: 4.2 Determining the Capital Cost of a Hydrogen Compressor | F94: 18 | G94: Table 4.1 conversion note | H94: 0.75 | I94: USD/CAD | J94: exchange_rate_2019 | K94: Assumptions and Parameter Comp | L94: 2019 average exchange rate used when the report converted the underlying HDSAM compressor correlation into 2019 CAD. Already embedded in the 3083.3 coefficient. | M94: https://transitionaccelerator.ca/wp-content/uploads/2023/06/The-Techno-Economics-of-Hydrogen-Compression.pdf
A95: WEI-COMP-007 | B95: Secondary implementation source | C95: Evaluating Environmental and Economic Trade-offs in Centralized and Decentralized Hydrogen Production — A Case Study on Canadian Steel | D95: 2026 | E95: 2.5.4.2 Compressor Costing | F95: 62–63 | G95: Compressor financial assumption | H95: 15 | I95: years | J95: compressor_lifetime | K95: Assumptions and Parameter Comp | L95: Physical or financial compressor lifetime used in the thesis cost model. For TEMOA mapping, use as technology lifetime without embedding annualization in CostInvest.
A96: MODEL-COMP-004 | B96: Modeller convention | C96: Workbook methodology | D96: Current workbook | E96: Compressor utilization | F96: N/A | G96: Availability assumption | H96: 1 | I96: fraction | J96: availability_factor_comp | K96: Assumptions and Parameter Comp | L96: Assumes full-year compressor operation at design throughput. Suitable for reproducing normalized source costs, but potentially too restrictive for endogenous CANOE operation.
A97: MODEL-COMP-005 | B97: Modeller convention | C97: Workbook methodology | D97: Current workbook | E97: Calendar-year energy conversion | F97: N/A | G97: Annual operating hours | H97: 8760 | I97: hours/year | J97: annual_operating_hours | K97: Assumptions and Parameter Comp | L97: Used to convert rated compressor power into annual electricity consumption at 100% availability. For TEMOA, electricity should preferably be tied to activity through an efficiency or input coefficient rather than fixed annual operation.

Sheet Assumptions and Parameters Pipe
A1: Source Assumptions and Core Equations
A3: Assumptions
A4: Category | B4: Parameter | C4: Value | D4: Unit | E4: Source location | F4: Status/ note
A5: Economic and temporal | B5: Pipeline lifetime | C5: 50 | D5: years | E5: https://transitionaccelerator.ca/wp-content/uploads/2023/06/The-Techno-Economics-of-Hydrogen-Pipelines-v2.pdf | F5: This is a technological physcial lifetime
A6: Economic and temporal | B6: Exchange rate | C6: 0.75 | D6: USD/CAD | E6: https://transitionaccelerator.ca/wp-content/uploads/2023/06/The-Techno-Economics-of-Hydrogen-Pipelines-v2.pdf | F6: Convert USD to CAD by dividing by the USD/CAD exchange rate; 2019 average
A7: Economic and temporal | B7: GDP Deflator 2009 | C7: 88.5 | D7: price index | E7: https://www150.statcan.gc.ca/t1/tbl1/en/tv.action?pid=3610013001&pickMembers%5B0%5D=2.1&cubeTimeFrame.startYear=2009&cubeTimeFrame.endYear=2020&referencePeriods=20090101%2C20200101 | F7: 2017 base year covention
A8: Economic and temporal | B8: GDP Deflator 2019 | C8: 103.3 | D8: price index | E8: https://www150.statcan.gc.ca/t1/tbl1/en/tv.action?pid=3610013001&pickMembers%5B0%5D=2.1&cubeTimeFrame.startYear=2009&cubeTimeFrame.endYear=2020&referencePeriods=20090101%2C20200101 | F8: 2017 base year covention
A9: Economic and temporal | B9: GDP Deflator 2020 | C9: 105 | D9: price index | E9: https://www150.statcan.gc.ca/t1/tbl1/en/tv.action?pid=3610013001&pickMembers%5B0%5D=2.1&cubeTimeFrame.startYear=2009&cubeTimeFrame.endYear=2020&referencePeriods=20090101%2C20200101 | F9: 2017 base year covention
A10: Direct CAPEX assumptions | C10: 1.1 | D10: multiplier | E10: https://transitionaccelerator.ca/wp-content/uploads/2023/06/The-Techno-Economics-of-Hydrogen-Pipelines-v2.pdf | F10: The 1.1 hydrogen pipeline cost multiplier is a weakly supported source assumption and may overlap conceptually with the cost consequences of increased hydrogen-compatible wall thickness. Retain for source reproduction, but test its inclusion in sensitivity analysis. This increased cost burden is effectively addressed via the higher costs and such that are modelled via the thickened pipeline wall needs (thicker than needed for CO2 or nat gas, for e.g.,) though this might not be updated in the version of code shared to you yet. Ill share a final copy once I'm done (since some additional fixes were done as I amended my thesis to its submission state)
A11: Direct CAPEX assumptions | B11: Indirect CAPEX cost assumption multiplier | C11: 0.4 | D11: dimensionless | E11: https://transitionaccelerator.ca/wp-content/uploads/2023/06/The-Techno-Economics-of-Hydrogen-Pipelines-v2.pdf | F11: Source adjustment applied to selected HDSAM transmission-pipeline cost correlations to represent anticipated additional hydrogen-pipeline costs. Retained for source reproduction but flagged for sensitivity analysis
A12: Indirect CAPEX assumptions | B12: Site preparation | C12: 0.05 | D12: fraction of TIC | E12: https://transitionaccelerator.ca/wp-content/uploads/2023/06/The-Techno-Economics-of-Hydrogen-Pipelines-v2.pdf | F12: Includes the purchase of land; grading and excavation of the site; installation and hookup of electrical, water, and sewer systems; and construction of all internal roads, walkways, and parking lots
A13: Indirect CAPEX assumptions | B13: Engineering and Design | C13: 0.1 | D13: fraction of TIC | E13: https://transitionaccelerator.ca/wp-content/uploads/2023/06/The-Techno-Economics-of-Hydrogen-Pipelines-v2.pdf | F13: Includes salaries and overhead for the engineering, drafting, and project management personnel on the project
A14: Indirect CAPEX assumptions | B14: Project Contingency | C14: 0.1 | D14: fraction of TIC | E14: https://transitionaccelerator.ca/wp-content/uploads/2023/06/The-Techno-Economics-of-Hydrogen-Pipelines-v2.pdf | F14: A factor to cover unforeseen circumstances, including project risks or uncertainties). These may include loss of time due to storms and strikes, small changes in the design, and unexpected price increases
A15: Indirect CAPEX assumptions | B15: Permitting | C15: 0.03 | D15: fraction of TIC | E15: https://transitionaccelerator.ca/wp-content/uploads/2023/06/The-Techno-Economics-of-Hydrogen-Pipelines-v2.pdf | F15: The permitting costs are costs borne by the facilities to obtain the necessary approvals to design and install the control equipment. This is a site-specific cost where the costs borne by one facility may not translate well into another facility. However, because of the potential for delay, re-design, and other considerations, permitting costs should be included in the overall cost assessment
A16: Indirect CAPEX assumptions | B16: Unallocated residual | C16: 0.12 | D16: fraction of TIC | E16: https://transitionaccelerator.ca/wp-content/uploads/2023/06/The-Techno-Economics-of-Hydrogen-Pipelines-v2.pdf | F16: Addition 12% associated with the 40% used by the accelerator model.
A17: Labour OPEX assumptions | B17: Labor Rate | C17: 49.6 | D17: $2019 CAD / hr | E17: https://transitionaccelerator.ca/wp-content/uploads/2023/06/The-Techno-Economics-of-Hydrogen-Pipelines-v2.pdf, https://hdsam.es.anl.gov/index.php?content=hdsam | F17: Derived from 2019 US HDSAM model
A18: Labour OPEX assumptions | B18: Indirect labor factor | C18: 0.5 | D18: dimensionless | E18: https://transitionaccelerator.ca/wp-content/uploads/2023/06/The-Techno-Economics-of-Hydrogen-Pipelines-v2.pdf, https://hdsam.es.anl.gov/index.php?content=hdsam | F18: used to consider the cost of overhead (i.e., head office, personnel)
A21: CAPEX, h2_pipe
A22: Category | B22: Parameter | C22: Equation | D22: Unit | E22: Source location | F22: Status / note
A23: CAPEX | B23: Transmission Pipeline Material | C23: 1.1 * 63027*exp(Diameter, in.*0.0697) * (Length, miles) | D23: 2009 $US | E23: https://transitionaccelerator.ca/wp-content/uploads/2023/06/The-Techno-Economics-of-Hydrogen-Pipelines-v2.pdf, https://hdsam.es.anl.gov/index.php?content=hdsam | F23: 2009 $US HDSAM model
A24: CAPEX | B24: Transmission Pipeline Labor | C24: 1.1 * ([-51.393 * (Diameter, in.)2 + 43,523 * (Diameter, in.) + 16,171] * (Length, miles)) | D24: 2009 $US | E24: https://transitionaccelerator.ca/wp-content/uploads/2023/06/The-Techno-Economics-of-Hydrogen-Pipelines-v2.pdf, https://hdsam.es.anl.gov/index.php?content=hdsam | F24: 2009 $US HDSAM model
A25: CAPEX | B25: Transmission Pipeline Miscellaneous | C25: 1.1 * ([303.13 * (Diameter, in.)2 + 12,908 * (Diameter, in.) + 123,245] * (Length, miles)) | D25: 2009 $US | E25: https://transitionaccelerator.ca/wp-content/uploads/2023/06/The-Techno-Economics-of-Hydrogen-Pipelines-v2.pdf, https://hdsam.es.anl.gov/index.php?content=hdsam | F25: 2009 $US HDSAM model
A26: CAPEX | B26: Transmission Pipeline Right-of Way | C26: ([-9E-13 * (Diameter, in.)2 + 4,417.1 * (Diameter, in.) + 164,241] * (Length, miles)) | D26: 2009 $US | E26: https://transitionaccelerator.ca/wp-content/uploads/2023/06/The-Techno-Economics-of-Hydrogen-Pipelines-v2.pdf, https://hdsam.es.anl.gov/index.php?content=hdsam | F26: 2009 $US HDSAM model
A27: Indirect CAPEX | B27: see table above | C27: 40% of TIC | D27: 2009 $US | E27: https://transitionaccelerator.ca/wp-content/uploads/2023/06/The-Techno-Economics-of-Hydrogen-Pipelines-v2.pdf, https://hdsam.es.anl.gov/index.php?content=hdsam | F27: 2009 $US HDSAM model
A30: Capacity-dependent Labour OPEX, h2_pipe
A31: Category | B31: Parameter | C31: Equation | D31: Unit | E31: Source location | F31: Status / note
A32: OPEX, variable | B32: Direct labour costs | C32: Direct labor, pipe ( $ / yr) = Annual hours (hrs / yr ) ∗ Labor rate ( $ / hrs) | D32: $CAD / yr | E32: https://transitionaccelerator.ca/wp-content/uploads/2023/06/The-Techno-Economics-of-Hydrogen-Pipelines-v2.pdf, https://hdsam.es.anl.gov/index.php?content=hdsam | F32: Depends on annual labour hours; 2019 $US
A33: OPEX, variable | B33: Annual labour hours | C33: Annual labor hours (hr / yr) = 8760 ∗ ( x / 100,000) ^ 0.25 | D33: hrs / yr | E33: https://transitionaccelerator.ca/wp-content/uploads/2023/06/The-Techno-Economics-of-Hydrogen-Pipelines-v2.pdf, https://hdsam.es.anl.gov/index.php?content=hdsam
C34: x is avg pipeline use (kg H2 / day)
A35: OPEX, variable | B35: Indirect labour costs | C35: Indirect labor, pipe ( $ / yr) = Direct laborpipe ( $ / yr) ∗ Indirect labor factor (%) | D35: $CAD / yr | F35: 2019 $US
A37: OPEX, Fixed, h2_pipe
A38: Category | B38: Parameter | C38: Equation | D38: Unit | E38: Source location | F38: Status / note
A39: OPEX, fixed | B39: Insurance | C39: 1% of TCI, pipe | D39: fraction of TCI / yr | E39: https://transitionaccelerator.ca/wp-content/uploads/2023/06/The-Techno-Economics-of-Hydrogen-Pipelines-v2.pdf, https://hdsam.es.anl.gov/index.php?content=hdsam | F39: All non-labor fixed O&M costs ($/yr) are calculated as a fraction of the TCI to reflect that the larger and more complex, and therefore more expensive, projects have higher upkeep costs throughout the project life
A40: OPEX, fixed | B40: Property tax | C40: 1% of TCI, pipe | D40: fraction of TCI / yr | E40: https://transitionaccelerator.ca/wp-content/uploads/2023/06/The-Techno-Economics-of-Hydrogen-Pipelines-v2.pdf, https://hdsam.es.anl.gov/index.php?content=hdsam
A41: OPEX, fixed | B41: Licensing and permitting | C41: 0.1% of TCI, pipe | D41: fraction of TCI / yr | E41: https://transitionaccelerator.ca/wp-content/uploads/2023/06/The-Techno-Economics-of-Hydrogen-Pipelines-v2.pdf, https://hdsam.es.anl.gov/index.php?content=hdsam
A42: OPEX, fixed | B42: Operating, maintenance and repairs | C42: 0.5% of TCI, pipe | D42: fraction of TCI / yr | E42: https://transitionaccelerator.ca/wp-content/uploads/2023/06/The-Techno-Economics-of-Hydrogen-Pipelines-v2.pdf, https://hdsam.es.anl.gov/index.php?content=hdsam
A45: Notes about hydrogen cost factor from Ziqi:

Sheet Transition Accelerator Pipe
A1: General Overview | B1: Diameter treatment used in this workbook
A2: This worksheet represents a reference gaseous hydrogen transmission pipeline segment. The current reference length is 250 km. Hydraulic and cost parameters must be revised if the segment length, pressure cycle, pipeline material, or geographic assumptions change. Cost outputs are normalized per kilometre only after the complete segment cost has been calculated | B2: The General Flow Equation uses pipeline inner diameter to determine hydrogen flow capacity. Required wall thickness is calculated from the selected pressure and material-design assumptions, and outside diameter is then calculated as inner diameter plus twice the required wall thickness. The resulting outside diameter is used as the diameter input to the HDSAM-derived pipeline CAPEX correlations. This adaptation introduces the effect of wall thickness into the cost-capacity relationship. It differs from a strict reproduction of the source correlations, which are reported using pipeline diameter without fully distinguishing nominal, inner, and outside diameter. The assumption is therefore documented and should be tested in sensitivity analysis.
A4: Pipeline Thickness Requirements (currently not considered but may influence material costs)
A5: Variable | B5: Description | C5: Default Value | D5: Units | E5: Notes | F5: Source
A6: P | B6: Design Pressure | C6: =C22/1000 -> 7 | D6: Mpa | E6: Unclear if max pressure should be used over average pipeline pressure | F6: Equation 2.9 from https://transitionaccelerator.ca/wp-content/uploads/2023/06/The-Techno-Economics-of-Hydrogen-Pipelines-v2.pdf
A7: S | B7: Specified minimum yield strength | C7: 483 | D7: Mpa | E7: Proxy from a CO2 pipeline TEA by McCoy and Rubin | F7: https://www.sciencedirect.com/science/article/pii/S1750583607001193
A8: F | B8: Design factor | C8: 0.72 | D8: dimensionless | E8: Proxy from a CO2 pipeline TEA by McCoy and Rubin; can vary spatially | F8: https://www.sciencedirect.com/science/article/pii/S1750583607001193
A9: L | B9: Locational factor | C9: 1 | D9: dimensionless | E9: This would be accounted for by a cost surface c(i,j) modifier
A10: J | B10: Joint factor | C10: 1 | D10: dimensionless | E10: Based on seemless welded pipe | F10: https://www.csagroup.org/standards/areas-of-focus/petroleum-natural-gas/standards-for-pipeline-safety/?srsltid=AfmBOoqOn1XJkHisMlvYtqmtJ2wq0C18E_Xcenv9L9HZob5a6nou7gJT
A11: T | B11: Temperature factor | C11: 1 | D11: dimensionless | E11: Pipelines are not operated above 120C thus temperature factor is set to 1 | F11: https://www.csagroup.org/standards/areas-of-focus/petroleum-natural-gas/standards-for-pipeline-safety/?srsltid=AfmBOoqOn1XJkHisMlvYtqmtJ2wq0C18E_Xcenv9L9HZob5a6nou7gJT
A18: Model Units
A19: Variable | B19: Description | C19: Default Value | D19: Units | E19: Status | F19: Notes | G19: Source
A20: Tb | B20: Base temperature | C20: 288.7 | D20: K | E20: Input | F20: Ambient conditions not assuming outdoor temperature varaibility, realistically this would differ in the winter
A21: Pb | B21: Base pressure | C21: 101.325 | D21: kPa | E21: Input | F21: Ambient conditions
A22: P1 | B22: Inlet pressure | C22: 7000 | D22: kPa | E22: Input | F22: Converted from 70 bar | G22: https://transitionaccelerator.ca/wp-content/uploads/2023/06/The-Techno-Economics-of-Hydrogen-Pipelines-v2.pdf, https://hdsam.es.anl.gov/index.php?content=hdsam
A23: P2 | B23: Outlet pressure | C23: 2800 | D23: kPa | E23: Input | F23: Converted from 28 bar | G23: https://transitionaccelerator.ca/wp-content/uploads/2023/06/The-Techno-Economics-of-Hydrogen-Pipelines-v2.pdf, https://hdsam.es.anl.gov/index.php?content=hdsam
A24: H1 | B24: Inlet elevation | C24: 2 | D24: m | E24: Input | F24: Arbitrary assumption to get a baseline reference for a near-flat pipe over 250km
A25: H2 | B25: Outlet elevation | C25: 1 | D25: m | E25: Input
A26: Tf | B26: Average flowing temperature | C26: 288.7 | D26: K | E26: Input | F26: Ambient conditions not assuming outdoor temperature varaibility, realistically this would differ in the winter | G26: Using Tf and https://h2tools.org/hyarc/hydrogen-data/hydrogen-compressibility-different-temperatures-and-pressures
A27: Z | B27: Average gas compressibility factor | C27: 1.03 | D27: dimensionless | E27: Input | F27: Should correspond to P and T conditions of pipe | G27: https://www.engineeringtoolbox.com/specific-gravities-gases-d_334.html
A28: G | B28: H2 gas specific gravity relative to air | C28: 0.0696 | D28: dimensionless | E28: Input | F28: Used by the general flow equation | G28: https://www.sciencedirect.com/science/article/pii/S095965261832170X?via%3Dihub
A29: L | B29: Pipeline segment length | C29: 250 | D29: km | E29: Input | F29: Reference engineering case, should be checked for sensitivity | G29: Assumed from https://transitionaccelerator.ca/wp-content/uploads/2023/06/The-Techno-Economics-of-Hydrogen-Pipelines-v2.pdf
A30: f | B30: Darcy fricton factor | C30: 0.0094 | D30: dimensionless | E30: Input | F30: Dervied from Reynolds numbers and iterative solving; need to be re-solved if parameters are changed | G30: https://transitionaccelerator.ca/wp-content/uploads/2023/06/The-Techno-Economics-of-Hydrogen-Pipelines-v2.pdf, https://hdsam.es.anl.gov/index.php?content=hdsam
A31: R | B31: Universal Gas Constant | C31: 8.314 | D31: kPa*m^3/k*mol | E31: Input constant | G31: https://transitionaccelerator.ca/wp-content/uploads/2023/06/The-Techno-Economics-of-Hydrogen-Pipelines-v2.pdf, https://hdsam.es.anl.gov/index.php?content=hdsam
A32: rho H2,b | B32: Hydrogen density at base conditions | C32: 0.0834 | D32: kg H2/Sm^3 | E32: Conversion factor | F32: Used to convert Q to mass capacity | G32: https://transitionaccelerator.ca/wp-content/uploads/2023/06/The-Techno-Economics-of-Hydrogen-Pipelines-v2.pdf, https://hdsam.es.anl.gov/index.php?content=hdsam
A33: nd | B33: days per representative year | C33: 365 | D33: days/year | E33: CANOE conversion | F33: Converts daily capacity into annual capcity
A36: Derived Hydraulic Parameters
A37: Variable | B37: Description | C37: Default Value | D37: Units | E37: Status | F37: Notes | G37: Source
A38: s | B38: Elevation adjustment parameter | C38: =0.0684*C28*((C25-C24)/(C26*C27)) -> -1.6009631e-05 | D38: dimensionless | E38: Derived input | F38: Derived from elevation, G, Tf, and Z | G38: Equation 2.7 from https://transitionaccelerator.ca/wp-content/uploads/2023/06/The-Techno-Economics-of-Hydrogen-Pipelines-v2.pdf
A39: Le | B39: Equivalent pipeline length | C39: =C29*((EXP(C38)-1)/C38) -> 249.998 | D39: km | E39: Derived input | F39: Derived from L and s | G39: https://transitionaccelerator.ca/wp-content/uploads/2023/06/The-Techno-Economics-of-Hydrogen-Pipelines-v2.pdf, https://hdsam.es.anl.gov/index.php?content=hdsam
A40: Pavg | B40: Average pipeline pressure | C40: =(2/3)*(((C22^3)-(C23^3))/((C22^2)-(C23^2))) -> 5200 | D40: kPa | E40: Derived input | F40: Dervied from P1 and P2 | G40: Equation 2.9 from https://transitionaccelerator.ca/wp-content/uploads/2023/06/The-Techno-Economics-of-Hydrogen-Pipelines-v2.pdf
A41: Vmax | B41: Erosional Velocity | C41: =100*SQRT((0.05131*((C27*C31*C26)/(C28*C22)))) -> 51.026336 | D41: m/s | E41: Derived input | F41: Equation 8 in transition accelerator | G41: https://transitionaccelerator.ca/wp-content/uploads/2023/06/The-Techno-Economics-of-Hydrogen-Pipelines-v2.pdf, https://hdsam.es.anl.gov/index.php?content=hdsam
A42: Cday | B42: Daily mass capacity | C42: Output | D42: kg H2/day | E42: Derived input
A43: Cyr | B43: Annual mass capacity | C43: Output | D43: t H2/yr | E43: Derived input
A46: Transmission Pipeline Capacity Estimation
A47: Design_ID | B47: Inner pipeline Diameter (inch, inner diameter) | C47: Inner pipeline diameter (mm) | D47: Required pipeline thickness (mm) | E47: Outer Pipeline Diameter (mm) | F47: Gas flow rate (Sm^3/day) | G47: Daily Capacity (kg H2 / day) | H47: Annual Capacity (kg H2 / year) | I47: Annual Capacity (t H2 / year)
A48: H2_PIPE_8 | B48: 8 | C48: =B48*25.4 -> 203.2 | D48: =($C$6*(B48*25.4))/(2*$C$7*$C$8*$C$9*$C$10*$C$11) -> 2.0450886 | E48: =D48+C48 -> 205.24509 | F48: =1.1494*(10^(-3))*($C$20/$C$21)*(((($C$22^2)-EXP($C$38)*($C$23^2))/($C$28*$C$26*$C$39*$C$27*$C$30))^0.5)*(C48^2.5) -> 1773250.7 | G48: =F48*0.0834 -> 147889.11 | H48: =G48*$C$33 -> 53979526 | I48: =H48/1000 -> 53979.526
A49: H2_PIPE_10 | B49: 10 | C49: =B49*25.4 -> 254 | D49: =($C$6*(B49*25.4))/(2*$C$7*$C$8*$C$9*$C$10*$C$11) -> 2.5563607 | E49: =D49+C49 -> 256.55636 | F49: =1.1494*(10^(-3))*($C$20/$C$21)*(((($C$22^2)-EXP($C$38)*($C$23^2))/($C$28*$C$26*$C$39*$C$27*$C$30))^0.5)*(C49^2.5) -> 3097741.6 | G49: =F49*0.0834 -> 258351.65 | H49: =G49*$C$33 -> 94298351 | I49: =H49/1000 -> 94298.351
A50: H2_PIPE_12 | B50: 12 | C50: =B50*25.4 -> 304.8 | D50: =($C$6*(B50*25.4))/(2*$C$7*$C$8*$C$9*$C$10*$C$11) -> 3.0676329 | E50: =D50+C50 -> 307.86763 | F50: =1.1494*(10^(-3))*($C$20/$C$21)*(((($C$22^2)-EXP($C$38)*($C$23^2))/($C$28*$C$26*$C$39*$C$27*$C$30))^0.5)*(C50^2.5) -> 4886504.5 | G50: =F50*0.0834 -> 407534.47 | H50: =G50*$C$33 -> 1.4875008e+08 | I50: =H50/1000 -> 148750.08
A51: H2_PIPE_14 | B51: 14 | C51: =B51*25.4 -> 355.6 | D51: =($C$6*(B51*25.4))/(2*$C$7*$C$8*$C$9*$C$10*$C$11) -> 3.578905 | E51: =D51+C51 -> 359.1789 | F51: =1.1494*(10^(-3))*($C$20/$C$21)*(((($C$22^2)-EXP($C$38)*($C$23^2))/($C$28*$C$26*$C$39*$C$27*$C$30))^0.5)*(C51^2.5) -> 7183982.6 | G51: =F51*0.0834 -> 599144.15 | H51: =G51*$C$33 -> 2.1868762e+08 | I51: =H51/1000 -> 218687.62
A52: H2_PIPE_16 | B52: 16 | C52: =B52*25.4 -> 406.4 | D52: =($C$6*(B52*25.4))/(2*$C$7*$C$8*$C$9*$C$10*$C$11) -> 4.0901771 | E52: =D52+C52 -> 410.49018 | F52: =1.1494*(10^(-3))*($C$20/$C$21)*(((($C$22^2)-EXP($C$38)*($C$23^2))/($C$28*$C$26*$C$39*$C$27*$C$30))^0.5)*(C52^2.5) -> 10031021 | G52: =F52*0.0834 -> 836587.15 | H52: =G52*$C$33 -> 3.0535431e+08 | I52: =H52/1000 -> 305354.31
A53: H2_PIPE_18 | B53: 18 | C53: =B53*25.4 -> 457.2 | D53: =($C$6*(B53*25.4))/(2*$C$7*$C$8*$C$9*$C$10*$C$11) -> 4.6014493 | E53: =D53+C53 -> 461.80145 | F53: =1.1494*(10^(-3))*($C$20/$C$21)*(((($C$22^2)-EXP($C$38)*($C$23^2))/($C$28*$C$26*$C$39*$C$27*$C$30))^0.5)*(C53^2.5) -> 13465623 | G53: =F53*0.0834 -> 1123032.9 | H53: =G53*$C$33 -> 4.0990703e+08 | I53: =H53/1000 -> 409907.03
A54: H2_PIPE_20 | B54: 20 | C54: =B54*25.4 -> 508 | D54: =($C$6*(B54*25.4))/(2*$C$7*$C$8*$C$9*$C$10*$C$11) -> 5.1127214 | E54: =D54+C54 -> 513.11272 | F54: =1.1494*(10^(-3))*($C$20/$C$21)*(((($C$22^2)-EXP($C$38)*($C$23^2))/($C$28*$C$26*$C$39*$C$27*$C$30))^0.5)*(C54^2.5) -> 17523473 | G54: =F54*0.0834 -> 1461457.6 | H54: =G54*$C$33 -> 5.3343203e+08 | I54: =H54/1000 -> 533432.03
A55: H2_PIPE_22 | B55: 22 | C55: =B55*25.4 -> 558.8 | D55: =($C$6*(B55*25.4))/(2*$C$7*$C$8*$C$9*$C$10*$C$11) -> 5.6239936 | E55: =D55+C55 -> 564.42399 | F55: =1.1494*(10^(-3))*($C$20/$C$21)*(((($C$22^2)-EXP($C$38)*($C$23^2))/($C$28*$C$26*$C$39*$C$27*$C$30))^0.5)*(C55^2.5) -> 22238315 | G55: =F55*0.0834 -> 1854675.5 | H55: =G55*$C$33 -> 6.7695656e+08 | I55: =H55/1000 -> 676956.56
A56: H2_PIPE_24 | B56: 24 | C56: =B56*25.4 -> 609.6 | D56: =($C$6*(B56*25.4))/(2*$C$7*$C$8*$C$9*$C$10*$C$11) -> 6.1352657 | E56: =D56+C56 -> 615.73527 | F56: =1.1494*(10^(-3))*($C$20/$C$21)*(((($C$22^2)-EXP($C$38)*($C$23^2))/($C$28*$C$26*$C$39*$C$27*$C$30))^0.5)*(C56^2.5) -> 27642243 | G56: =F56*0.0834 -> 2305363.1 | H56: =G56*$C$33 -> 8.4145753e+08 | I56: =H56/1000 -> 841457.53
A57: H2_PIPE_26 | B57: 26 | C57: =B57*25.4 -> 660.4 | D57: =($C$6*(B57*25.4))/(2*$C$7*$C$8*$C$9*$C$10*$C$11) -> 6.6465378 | E57: =D57+C57 -> 667.04654 | F57: =1.1494*(10^(-3))*($C$20/$C$21)*(((($C$22^2)-EXP($C$38)*($C$23^2))/($C$28*$C$26*$C$39*$C$27*$C$30))^0.5)*(C57^2.5) -> 33765917 | G57: =F57*0.0834 -> 2816077.5 | H57: =G57*$C$33 -> 1.0278683e+09 | I57: =H57/1000 -> 1027868.3
A58: H2_PIPE_28 | B58: 28 | C58: =B58*25.4 -> 711.2 | D58: =($C$6*(B58*25.4))/(2*$C$7*$C$8*$C$9*$C$10*$C$11) -> 7.15781 | E58: =D58+C58 -> 718.35781 | F58: =1.1494*(10^(-3))*($C$20/$C$21)*(((($C$22^2)-EXP($C$38)*($C$23^2))/($C$28*$C$26*$C$39*$C$27*$C$30))^0.5)*(C58^2.5) -> 40638743 | G58: =F58*0.0834 -> 3389271.1 | H58: =G58*$C$33 -> 1.237084e+09 | I58: =H58/1000 -> 1237084
A59: H2_PIPE_30 | B59: 30 | C59: =B59*25.4 -> 762 | D59: =($C$6*(B59*25.4))/(2*$C$7*$C$8*$C$9*$C$10*$C$11) -> 7.6690821 | E59: =D59+C59 -> 769.66908 | F59: =1.1494*(10^(-3))*($C$20/$C$21)*(((($C$22^2)-EXP($C$38)*($C$23^2))/($C$28*$C$26*$C$39*$C$27*$C$30))^0.5)*(C59^2.5) -> 48289012 | G59: =F59*0.0834 -> 4027303.6 | H59: =G59*$C$33 -> 1.4699658e+09 | I59: =H59/1000 -> 1469965.8
A60: H2_PIPE_32 | B60: 32 | C60: =B60*25.4 -> 812.8 | D60: =($C$6*(B60*25.4))/(2*$C$7*$C$8*$C$9*$C$10*$C$11) -> 8.1803543 | E60: =D60+C60 -> 820.98035 | F60: =1.1494*(10^(-3))*($C$20/$C$21)*(((($C$22^2)-EXP($C$38)*($C$23^2))/($C$28*$C$26*$C$39*$C$27*$C$30))^0.5)*(C60^2.5) -> 56744024 | G60: =F60*0.0834 -> 4732451.6 | H60: =G60*$C$33 -> 1.7273448e+09 | I60: =H60/1000 -> 1727344.8
A63: H2 Transmission Pipeline CAPEX
A64: Outer pipeline diameter (mm) | B64: Daily Capacity (kg H2 / day) | C64: Material Costs ($ 2009 US / km) | D64: Construction Labour ($ 2009 US / km) | E64: Miscellaneous ($ 2009 US / km) | F64: Right-of-way ($ 2009 US / km) | G64: Total Installed Cost ($ 2009 US / km) | H64: Total Capital Investment ($ 2009 US / km) | I64: Total Capital Investment ($ 2020 CAD / km)
A65: =E48 -> 205.24509 | B65: =G48 -> 147889.11 | C65: =('Assumptions and Parameters Pipe'!$C$10*63027*EXP((A65/25.4)*0.0697))/1.609 -> 75676.86 | D65: =('Assumptions and Parameters Pipe'!$C$10*(-51.393*((A65/25.4)^2)+43523*(A65/25.4)+16171))/1.609 -> 249194.49 | E65: ='Assumptions and Parameters Pipe'!$C$10*(303.13*((A65/25.4)^2)+12908*(A65/25.4)+123245)/1.609 -> 169095.83 | F65: =(-9*(10^(-13))*((A65/25.4)^2)+4417.1*(A65/25.4)+164241)/1.609 -> 124259.44 | G65: =SUM(C65:F65) -> 618226.62 | H65: =G65+(G65*'Assumptions and Parameters Pipe'!$C$11) -> 865517.27 | I65: =H65*(1/'Assumptions and Parameters Pipe'!$C$6)*('Assumptions and Parameters Pipe'!$C$9/'Assumptions and Parameters Pipe'!$C$7) -> 1369179.9
A66: =E49 -> 256.55636 | B66: =G49 -> 258351.65 | C66: =('Assumptions and Parameters Pipe'!$C$10*63027*EXP((A66/25.4)*0.0697))/1.609 -> 87119.036 | D66: =('Assumptions and Parameters Pipe'!$C$10*(-51.393*((A66/25.4)^2)+43523*(A66/25.4)+16171))/1.609 -> 308012.35 | E66: ='Assumptions and Parameters Pipe'!$C$10*(303.13*((A66/25.4)^2)+12908*(A66/25.4)+123245)/1.609 -> 194534.11 | F66: =(-9*(10^(-13))*((A66/25.4)^2)+4417.1*(A66/25.4)+164241)/1.609 -> 129805.19 | G66: =SUM(C66:F66) -> 719470.69 | H66: =G66+(G66*'Assumptions and Parameters Pipe'!$C$11) -> 1007259 | I66: =H66*(1/'Assumptions and Parameters Pipe'!$C$6)*('Assumptions and Parameters Pipe'!$C$9/'Assumptions and Parameters Pipe'!$C$7) -> 1593404
A67: =E50 -> 307.86763 | B67: =G50 -> 407534.47 | C67: =('Assumptions and Parameters Pipe'!$C$10*63027*EXP((A67/25.4)*0.0697))/1.609 -> 100291.24 | D67: =('Assumptions and Parameters Pipe'!$C$10*(-51.393*((A67/25.4)^2)+43523*(A67/25.4)+16171))/1.609 -> 366543.45 | E67: ='Assumptions and Parameters Pipe'!$C$10*(303.13*((A67/25.4)^2)+12908*(A67/25.4)+123245)/1.609 -> 221663.82 | F67: =(-9*(10^(-13))*((A67/25.4)^2)+4417.1*(A67/25.4)+164241)/1.609 -> 135350.94 | G67: =SUM(C67:F67) -> 823849.45 | H67: =G67+(G67*'Assumptions and Parameters Pipe'!$C$11) -> 1153389.2 | I67: =H67*(1/'Assumptions and Parameters Pipe'!$C$6)*('Assumptions and Parameters Pipe'!$C$9/'Assumptions and Parameters Pipe'!$C$7) -> 1824570.5
A68: =E51 -> 359.1789 | B68: =G51 -> 599144.15 | C68: =('Assumptions and Parameters Pipe'!$C$10*63027*EXP((A68/25.4)*0.0697))/1.609 -> 115455.06 | D68: =('Assumptions and Parameters Pipe'!$C$10*(-51.393*((A68/25.4)^2)+43523*(A68/25.4)+16171))/1.609 -> 424787.77 | E68: ='Assumptions and Parameters Pipe'!$C$10*(303.13*((A68/25.4)^2)+12908*(A68/25.4)+123245)/1.609 -> 250484.96 | F68: =(-9*(10^(-13))*((A68/25.4)^2)+4417.1*(A68/25.4)+164241)/1.609 -> 140896.69 | G68: =SUM(C68:F68) -> 931624.49 | H68: =G68+(G68*'Assumptions and Parameters Pipe'!$C$11) -> 1304274.3 | I68: =H68*(1/'Assumptions and Parameters Pipe'!$C$6)*('Assumptions and Parameters Pipe'!$C$9/'Assumptions and Parameters Pipe'!$C$7) -> 2063258.7
A69: =E52 -> 410.49018 | B69: =G52 -> 836587.15 | C69: =('Assumptions and Parameters Pipe'!$C$10*63027*EXP((A69/25.4)*0.0697))/1.609 -> 132911.61 | D69: =('Assumptions and Parameters Pipe'!$C$10*(-51.393*((A69/25.4)^2)+43523*(A69/25.4)+16171))/1.609 -> 482745.33 | E69: ='Assumptions and Parameters Pipe'!$C$10*(303.13*((A69/25.4)^2)+12908*(A69/25.4)+123245)/1.609 -> 280997.53 | F69: =(-9*(10^(-13))*((A69/25.4)^2)+4417.1*(A69/25.4)+164241)/1.609 -> 146442.44 | G69: =SUM(C69:F69) -> 1043096.9 | H69: =G69+(G69*'Assumptions and Parameters Pipe'!$C$11) -> 1460335.7 | I69: =H69*(1/'Assumptions and Parameters Pipe'!$C$6)*('Assumptions and Parameters Pipe'!$C$9/'Assumptions and Parameters Pipe'!$C$7) -> 2310135.5
A70: =E53 -> 461.80145 | B70: =G53 -> 1123032.9 | C70: =('Assumptions and Parameters Pipe'!$C$10*63027*EXP((A70/25.4)*0.0697))/1.609 -> 153007.56 | D70: =('Assumptions and Parameters Pipe'!$C$10*(-51.393*((A70/25.4)^2)+43523*(A70/25.4)+16171))/1.609 -> 540416.13 | E70: ='Assumptions and Parameters Pipe'!$C$10*(303.13*((A70/25.4)^2)+12908*(A70/25.4)+123245)/1.609 -> 313201.52 | F70: =(-9*(10^(-13))*((A70/25.4)^2)+4417.1*(A70/25.4)+164241)/1.609 -> 151988.19 | G70: =SUM(C70:F70) -> 1158613.4 | H70: =G70+(G70*'Assumptions and Parameters Pipe'!$C$11) -> 1622058.8 | I70: =H70*(1/'Assumptions and Parameters Pipe'!$C$6)*('Assumptions and Parameters Pipe'!$C$9/'Assumptions and Parameters Pipe'!$C$7) -> 2565968.7
A71: =E54 -> 513.11272 | B71: =G54 -> 1461457.6 | C71: =('Assumptions and Parameters Pipe'!$C$10*63027*EXP((A71/25.4)*0.0697))/1.609 -> 176141.97 | D71: =('Assumptions and Parameters Pipe'!$C$10*(-51.393*((A71/25.4)^2)+43523*(A71/25.4)+16171))/1.609 -> 597800.16 | E71: ='Assumptions and Parameters Pipe'!$C$10*(303.13*((A71/25.4)^2)+12908*(A71/25.4)+123245)/1.609 -> 347096.95 | F71: =(-9*(10^(-13))*((A71/25.4)^2)+4417.1*(A71/25.4)+164241)/1.609 -> 157533.94 | G71: =SUM(C71:F71) -> 1278573 | H71: =G71+(G71*'Assumptions and Parameters Pipe'!$C$11) -> 1790002.2 | I71: =H71*(1/'Assumptions and Parameters Pipe'!$C$6)*('Assumptions and Parameters Pipe'!$C$9/'Assumptions and Parameters Pipe'!$C$7) -> 2831641.9
A72: =E55 -> 564.42399 | B72: =G55 -> 1854675.5 | C72: =('Assumptions and Parameters Pipe'!$C$10*63027*EXP((A72/25.4)*0.0697))/1.609 -> 202774.25 | D72: =('Assumptions and Parameters Pipe'!$C$10*(-51.393*((A72/25.4)^2)+43523*(A72/25.4)+16171))/1.609 -> 654897.42 | E72: ='Assumptions and Parameters Pipe'!$C$10*(303.13*((A72/25.4)^2)+12908*(A72/25.4)+123245)/1.609 -> 382683.8 | F72: =(-9*(10^(-13))*((A72/25.4)^2)+4417.1*(A72/25.4)+164241)/1.609 -> 163079.69 | G72: =SUM(C72:F72) -> 1403435.2 | H72: =G72+(G72*'Assumptions and Parameters Pipe'!$C$11) -> 1964809.2 | I72: =H72*(1/'Assumptions and Parameters Pipe'!$C$6)*('Assumptions and Parameters Pipe'!$C$9/'Assumptions and Parameters Pipe'!$C$7) -> 3108172.8
A73: =E56 -> 615.73527 | B73: =G56 -> 2305363.1 | C73: =('Assumptions and Parameters Pipe'!$C$10*63027*EXP((A73/25.4)*0.0697))/1.609 -> 233433.27 | D73: =('Assumptions and Parameters Pipe'!$C$10*(-51.393*((A73/25.4)^2)+43523*(A73/25.4)+16171))/1.609 -> 711707.91 | E73: ='Assumptions and Parameters Pipe'!$C$10*(303.13*((A73/25.4)^2)+12908*(A73/25.4)+123245)/1.609 -> 419962.08 | F73: =(-9*(10^(-13))*((A73/25.4)^2)+4417.1*(A73/25.4)+164241)/1.609 -> 168625.44 | G73: =SUM(C73:F73) -> 1533728.7 | H73: =G73+(G73*'Assumptions and Parameters Pipe'!$C$11) -> 2147220.2 | I73: =H73*(1/'Assumptions and Parameters Pipe'!$C$6)*('Assumptions and Parameters Pipe'!$C$9/'Assumptions and Parameters Pipe'!$C$7) -> 3396732.5
A74: =E57 -> 667.04654 | B74: =G57 -> 2816077.5 | C74: =('Assumptions and Parameters Pipe'!$C$10*63027*EXP((A74/25.4)*0.0697))/1.609 -> 268727.87 | D74: =('Assumptions and Parameters Pipe'!$C$10*(-51.393*((A74/25.4)^2)+43523*(A74/25.4)+16171))/1.609 -> 768231.64 | E74: ='Assumptions and Parameters Pipe'!$C$10*(303.13*((A74/25.4)^2)+12908*(A74/25.4)+123245)/1.609 -> 458931.79 | F74: =(-9*(10^(-13))*((A74/25.4)^2)+4417.1*(A74/25.4)+164241)/1.609 -> 174171.19 | G74: =SUM(C74:F74) -> 1670062.5 | H74: =G74+(G74*'Assumptions and Parameters Pipe'!$C$11) -> 2338087.5 | I74: =H74*(1/'Assumptions and Parameters Pipe'!$C$6)*('Assumptions and Parameters Pipe'!$C$9/'Assumptions and Parameters Pipe'!$C$7) -> 3698669.5
A75: =E58 -> 718.35781 | B75: =G58 -> 3389271.1 | C75: =('Assumptions and Parameters Pipe'!$C$10*63027*EXP((A75/25.4)*0.0697))/1.609 -> 309358.94 | D75: =('Assumptions and Parameters Pipe'!$C$10*(-51.393*((A75/25.4)^2)+43523*(A75/25.4)+16171))/1.609 -> 824468.6 | E75: ='Assumptions and Parameters Pipe'!$C$10*(303.13*((A75/25.4)^2)+12908*(A75/25.4)+123245)/1.609 -> 499592.93 | F75: =(-9*(10^(-13))*((A75/25.4)^2)+4417.1*(A75/25.4)+164241)/1.609 -> 179716.94 | G75: =SUM(C75:F75) -> 1813137.4 | H75: =G75+(G75*'Assumptions and Parameters Pipe'!$C$11) -> 2538392.4 | I75: =H75*(1/'Assumptions and Parameters Pipe'!$C$6)*('Assumptions and Parameters Pipe'!$C$9/'Assumptions and Parameters Pipe'!$C$7) -> 4015536
A76: =E59 -> 769.66908 | B76: =G59 -> 4027303.6 | C76: =('Assumptions and Parameters Pipe'!$C$10*63027*EXP((A76/25.4)*0.0697))/1.609 -> 356133.34 | D76: =('Assumptions and Parameters Pipe'!$C$10*(-51.393*((A76/25.4)^2)+43523*(A76/25.4)+16171))/1.609 -> 880418.8 | E76: ='Assumptions and Parameters Pipe'!$C$10*(303.13*((A76/25.4)^2)+12908*(A76/25.4)+123245)/1.609 -> 541945.5 | F76: =(-9*(10^(-13))*((A76/25.4)^2)+4417.1*(A76/25.4)+164241)/1.609 -> 185262.69 | G76: =SUM(C76:F76) -> 1963760.3 | H76: =G76+(G76*'Assumptions and Parameters Pipe'!$C$11) -> 2749264.5 | I76: =H76*(1/'Assumptions and Parameters Pipe'!$C$6)*('Assumptions and Parameters Pipe'!$C$9/'Assumptions and Parameters Pipe'!$C$7) -> 4349118.9
A77: =E60 -> 820.98035 | B77: =G60 -> 4732451.6 | C77: =('Assumptions and Parameters Pipe'!$C$10*63027*EXP((A77/25.4)*0.0697))/1.609 -> 409979.92 | D77: =('Assumptions and Parameters Pipe'!$C$10*(-51.393*((A77/25.4)^2)+43523*(A77/25.4)+16171))/1.609 -> 936082.22 | E77: ='Assumptions and Parameters Pipe'!$C$10*(303.13*((A77/25.4)^2)+12908*(A77/25.4)+123245)/1.609 -> 585989.5 | F77: =(-9*(10^(-13))*((A77/25.4)^2)+4417.1*(A77/25.4)+164241)/1.609 -> 190808.44 | G77: =SUM(C77:F77) -> 2122860.1 | H77: =G77+(G77*'Assumptions and Parameters Pipe'!$C$11) -> 2972004.1 | I77: =H77*(1/'Assumptions and Parameters Pipe'!$C$6)*('Assumptions and Parameters Pipe'!$C$9/'Assumptions and Parameters Pipe'!$C$7) -> 4701475.4
A80: H2 Transmission Pipeline Capacity-dependent annual labour Fixed OPEX
A81: Inner pipeline diameter (mm) | B81: Daily Capacity (kg H2 / day) | C81: Annual Capacity (t H2 / yr) | D81: Annual Labor Hours (hrs) | E81: Direct Labor Costs ($ 2019 CAD / yr) | F81: Indirect Labour Costs ($ 2019 CAD/ yr) | G81: Total Labour Costs ($ 2019 CAD/ yr) | H81: Total Labour Costs ($ 2019 CAD/ t H2) | I81: Total Labour Costs ($ 2020 CAD/ t H2*km)
A82: =C48 -> 203.2 | B82: =G48 -> 147889.11 | C82: =I48 -> 53979.526 | D82: =8760*((B82/100000)^0.25) -> 9660.2453 | E82: =D82*'Assumptions and Parameters Pipe'!$C$17 -> 479148.17 | F82: =E82*'Assumptions and Parameters Pipe'!$C$18 -> 239574.08 | G82: =SUM(E82:F82) -> 718722.25 | H82: =G82/C82 -> 13.31472 | I82: =(H82*('Assumptions and Parameters Pipe'!$C$9/'Assumptions and Parameters Pipe'!$C$8))/$C$39 -> 0.054135789
A83: =C49 -> 254 | B83: =G49 -> 258351.65 | C83: =I49 -> 94298.351 | D83: =8760*((B83/100000)^0.25) -> 11105.981 | E83: =D83*'Assumptions and Parameters Pipe'!$C$17 -> 550856.64 | F83: =E83*'Assumptions and Parameters Pipe'!$C$18 -> 275428.32 | G83: =SUM(E83:F83) -> 826284.96 | H83: =G83/C83 -> 8.762454 | I83: =(H83*('Assumptions and Parameters Pipe'!$C$9/'Assumptions and Parameters Pipe'!$C$8))/$C$39 -> 0.035626913
A84: =C50 -> 304.8 | B84: =G50 -> 407534.47 | C84: =I50 -> 148750.08 | D84: =8760*((B84/100000)^0.25) -> 12446.441 | E84: =D84*'Assumptions and Parameters Pipe'!$C$17 -> 617343.49 | F84: =E84*'Assumptions and Parameters Pipe'!$C$18 -> 308671.74 | G84: =SUM(E84:F84) -> 926015.23 | H84: =G84/C84 -> 6.225309 | I84: =(H84*('Assumptions and Parameters Pipe'!$C$9/'Assumptions and Parameters Pipe'!$C$8))/$C$39 -> 0.025311236
A85: =C51 -> 355.6 | B85: =G51 -> 599144.15 | C85: =I51 -> 218687.62 | D85: =8760*((B85/100000)^0.25) -> 13705.249 | E85: =D85*'Assumptions and Parameters Pipe'!$C$17 -> 679780.36 | F85: =E85*'Assumptions and Parameters Pipe'!$C$18 -> 339890.18 | G85: =SUM(E85:F85) -> 1019670.5 | H85: =G85/C85 -> 4.6626808 | I85: =(H85*('Assumptions and Parameters Pipe'!$C$9/'Assumptions and Parameters Pipe'!$C$8))/$C$39 -> 0.018957808
A86: =C52 -> 406.4 | B86: =G52 -> 836587.15 | C86: =I52 -> 305354.31 | D86: =8760*((B86/100000)^0.25) -> 14898.135 | E86: =D86*'Assumptions and Parameters Pipe'!$C$17 -> 738947.49 | F86: =E86*'Assumptions and Parameters Pipe'!$C$18 -> 369473.75 | G86: =SUM(E86:F86) -> 1108421.2 | H86: =G86/C86 -> 3.6299512 | I86: =(H86*('Assumptions and Parameters Pipe'!$C$9/'Assumptions and Parameters Pipe'!$C$8))/$C$39 -> 0.014758874
A87: =C53 -> 457.2 | B87: =G53 -> 1123032.9 | C87: =I53 -> 409907.03 | D87: =8760*((B87/100000)^0.25) -> 16036.228 | E87: =D87*'Assumptions and Parameters Pipe'!$C$17 -> 795396.92 | F87: =E87*'Assumptions and Parameters Pipe'!$C$18 -> 397698.46 | G87: =SUM(E87:F87) -> 1193095.4 | H87: =G87/C87 -> 2.9106488 | I87: =(H87*('Assumptions and Parameters Pipe'!$C$9/'Assumptions and Parameters Pipe'!$C$8))/$C$39 -> 0.011834291
A88: =C54 -> 508 | B88: =G54 -> 1461457.6 | C88: =I54 -> 533432.03 | D88: =8760*((B88/100000)^0.25) -> 17127.764 | E88: =D88*'Assumptions and Parameters Pipe'!$C$17 -> 849537.08 | F88: =E88*'Assumptions and Parameters Pipe'!$C$18 -> 424768.54 | G88: =SUM(E88:F88) -> 1274305.6 | H88: =G88/C88 -> 2.388881 | I88: =(H88*('Assumptions and Parameters Pipe'!$C$9/'Assumptions and Parameters Pipe'!$C$8))/$C$39 -> 0.0097128561
A89: =C55 -> 558.8 | B89: =G55 -> 1854675.5 | C89: =I55 -> 676956.56 | D89: =8760*((B89/100000)^0.25) -> 18179.046 | E89: =D89*'Assumptions and Parameters Pipe'!$C$17 -> 901680.69 | F89: =E89*'Assumptions and Parameters Pipe'!$C$18 -> 450840.34 | G89: =SUM(E89:F89) -> 1352521 | H89: =G89/C89 -> 1.9979436 | I89: =(H89*('Assumptions and Parameters Pipe'!$C$9/'Assumptions and Parameters Pipe'!$C$8))/$C$39 -> 0.0081233594
A90: =C56 -> 609.6 | B90: =G56 -> 2305363.1 | C90: =I56 -> 841457.53 | D90: =8760*((B90/100000)^0.25) -> 19195.036 | E90: =D90*'Assumptions and Parameters Pipe'!$C$17 -> 952073.81 | F90: =E90*'Assumptions and Parameters Pipe'!$C$18 -> 476036.9 | G90: =SUM(E90:F90) -> 1428110.7 | H90: =G90/C90 -> 1.6971869 | I90: =(H90*('Assumptions and Parameters Pipe'!$C$9/'Assumptions and Parameters Pipe'!$C$8))/$C$39 -> 0.0069005248
A91: =C57 -> 660.4 | B91: =G57 -> 2816077.5 | C91: =I57 -> 1027868.3 | D91: =8760*((B91/100000)^0.25) -> 20179.726 | E91: =D91*'Assumptions and Parameters Pipe'!$C$17 -> 1000914.4 | F91: =E91*'Assumptions and Parameters Pipe'!$C$18 -> 500457.2 | G91: =SUM(E91:F91) -> 1501371.6 | H91: =G91/C91 -> 1.4606653 | I91: =(H91*('Assumptions and Parameters Pipe'!$C$9/'Assumptions and Parameters Pipe'!$C$8))/$C$39 -> 0.0059388611
A92: =C58 -> 711.2 | B92: =G58 -> 3389271.1 | C92: =I58 -> 1237084 | D92: =8760*((B92/100000)^0.25) -> 21136.384 | E92: =D92*'Assumptions and Parameters Pipe'!$C$17 -> 1048364.6 | F92: =E92*'Assumptions and Parameters Pipe'!$C$18 -> 524182.32 | G92: =SUM(E92:F92) -> 1572546.9 | H92: =G92/C92 -> 1.2711724 | I92: =(H92*('Assumptions and Parameters Pipe'!$C$9/'Assumptions and Parameters Pipe'!$C$8))/$C$39 -> 0.0051684092
A93: =C59 -> 762 | B93: =G59 -> 4027303.6 | C93: =I59 -> 1469965.8 | D93: =8760*((B93/100000)^0.25) -> 22067.732 | E93: =D93*'Assumptions and Parameters Pipe'!$C$17 -> 1094559.5 | F93: =E93*'Assumptions and Parameters Pipe'!$C$18 -> 547279.75 | G93: =SUM(E93:F93) -> 1641839.3 | H93: =G93/C93 -> 1.1169234 | I93: =(H93*('Assumptions and Parameters Pipe'!$C$9/'Assumptions and Parameters Pipe'!$C$8))/$C$39 -> 0.0045412545
A94: =C60 -> 812.8 | B94: =G60 -> 4732451.6 | C94: =I60 -> 1727344.8 | D94: =8760*((B94/100000)^0.25) -> 22976.065 | E94: =D94*'Assumptions and Parameters Pipe'!$C$17 -> 1139612.8 | F94: =E94*'Assumptions and Parameters Pipe'!$C$18 -> 569806.41 | G94: =SUM(E94:F94) -> 1709419.2 | H94: =G94/C94 -> 0.98962246 | I94: =(H94*('Assumptions and Parameters Pipe'!$C$9/'Assumptions and Parameters Pipe'!$C$8))/$C$39 -> 0.0040236666
A97: H2 Transmission Pipeline Fixed OPEX
A98: Inner pipeline diameter (mm) | B98: Capacity (kg H2 / day) | C98: Annual Capacity (t H2 / yr) | D98: Insurance ($ 2009 US/km*yr) | E98: Property Tax ($ 2009 US/ km*yr) | F98: Permitting ($ 2009 US/ km*yr) | G98: Operating, Maintenance, Repairs ($ 2009 US/ km*yr) | H98: Total Fixed OPEX ($ 2009 US / km*yr) | I98: Total Fixed OPEX ($ 2009 US / km* t H2) | J98: Total Fixed OPEX ($ 2020 CAD per year / km* t H2 per year capacity)
A99: =C48 -> 203.2 | B99: =G48 -> 147889.11 | C99: =I48 -> 53979.526 | D99: =0.01*H65 -> 8655.1727 | E99: =0.01*H65 -> 8655.1727 | F99: =0.001*H65 -> 865.51727 | G99: =0.005*H65 -> 4327.5864 | H99: =SUM(D99:G99) -> 22503.449 | I99: =H99/C99 -> 0.4168886 | J99: =I99*(1/'Assumptions and Parameters Pipe'!$C$6)*('Assumptions and Parameters Pipe'!$C$9/'Assumptions and Parameters Pipe'!$C$7) -> 0.65948479
A100: =C49 -> 254 | B100: =G49 -> 258351.65 | C100: =I49 -> 94298.351 | D100: =0.01*H66 -> 10072.59 | E100: =0.01*H66 -> 10072.59 | F100: =0.001*H66 -> 1007.259 | G100: =0.005*H66 -> 5036.2948 | H100: =SUM(D100:G100) -> 26188.733 | I100: =H100/C100 -> 0.27772207 | J100: =I100*(1/'Assumptions and Parameters Pipe'!$C$6)*('Assumptions and Parameters Pipe'!$C$9/'Assumptions and Parameters Pipe'!$C$7) -> 0.43933435
A101: =C50 -> 304.8 | B101: =G50 -> 407534.47 | C101: =I50 -> 148750.08 | D101: =0.01*H67 -> 11533.892 | E101: =0.01*H67 -> 11533.892 | F101: =0.001*H67 -> 1153.3892 | G101: =0.005*H67 -> 5766.9462 | H101: =SUM(D101:G101) -> 29988.12 | I101: =H101/C101 -> 0.2016007 | J101: =I101*(1/'Assumptions and Parameters Pipe'!$C$6)*('Assumptions and Parameters Pipe'!$C$9/'Assumptions and Parameters Pipe'!$C$7) -> 0.31891636
A102: =C51 -> 355.6 | B102: =G51 -> 599144.15 | C102: =I51 -> 218687.62 | D102: =0.01*H68 -> 13042.743 | E102: =0.01*H68 -> 13042.743 | F102: =0.001*H68 -> 1304.2743 | G102: =0.005*H68 -> 6521.3714 | H102: =SUM(D102:G102) -> 33911.131 | I102: =H102/C102 -> 0.15506654 | J102: =I102*(1/'Assumptions and Parameters Pipe'!$C$6)*('Assumptions and Parameters Pipe'!$C$9/'Assumptions and Parameters Pipe'!$C$7) -> 0.245303
A103: =C52 -> 406.4 | B103: =G52 -> 836587.15 | C103: =I52 -> 305354.31 | D103: =0.01*H69 -> 14603.357 | E103: =0.01*H69 -> 14603.357 | F103: =0.001*H69 -> 1460.3357 | G103: =0.005*H69 -> 7301.6784 | H103: =SUM(D103:G103) -> 37968.728 | I103: =H103/C103 -> 0.12434319 | J103: =I103*(1/'Assumptions and Parameters Pipe'!$C$6)*('Assumptions and Parameters Pipe'!$C$9/'Assumptions and Parameters Pipe'!$C$7) -> 0.19670108
A104: =C53 -> 457.2 | B104: =G53 -> 1123032.9 | C104: =I53 -> 409907.03 | D104: =0.01*H70 -> 16220.588 | E104: =0.01*H70 -> 16220.588 | F104: =0.001*H70 -> 1622.0588 | G104: =0.005*H70 -> 8110.2938 | H104: =SUM(D104:G104) -> 42173.528 | I104: =H104/C104 -> 0.10288559 | J104: =I104*(1/'Assumptions and Parameters Pipe'!$C$6)*('Assumptions and Parameters Pipe'!$C$9/'Assumptions and Parameters Pipe'!$C$7) -> 0.16275687
A105: =C54 -> 508 | B105: =G54 -> 1461457.6 | C105: =I54 -> 533432.03 | D105: =0.01*H71 -> 17900.022 | E105: =0.01*H71 -> 17900.022 | F105: =0.001*H71 -> 1790.0022 | G105: =0.005*H71 -> 8950.0111 | H105: =SUM(D105:G105) -> 46540.058 | I105: =H105/C105 -> 0.087246463 | J105: =I105*(1/'Assumptions and Parameters Pipe'!$C$6)*('Assumptions and Parameters Pipe'!$C$9/'Assumptions and Parameters Pipe'!$C$7) -> 0.138017
A106: =C55 -> 558.8 | B106: =G55 -> 1854675.5 | C106: =I55 -> 676956.56 | D106: =0.01*H72 -> 19648.092 | E106: =0.01*H72 -> 19648.092 | F106: =0.001*H72 -> 1964.8092 | G106: =0.005*H72 -> 9824.0461 | H106: =SUM(D106:G106) -> 51085.04 | I106: =H106/C106 -> 0.075462803 | J106: =I106*(1/'Assumptions and Parameters Pipe'!$C$6)*('Assumptions and Parameters Pipe'!$C$9/'Assumptions and Parameters Pipe'!$C$7) -> 0.11937619
A107: =C56 -> 609.6 | B107: =G56 -> 2305363.1 | C107: =I56 -> 841457.53 | D107: =0.01*H73 -> 21472.202 | E107: =0.01*H73 -> 21472.202 | F107: =0.001*H73 -> 2147.2202 | G107: =0.005*H73 -> 10736.101 | H107: =SUM(D107:G107) -> 55827.725 | I107: =H107/C107 -> 0.066346456 | J107: =I107*(1/'Assumptions and Parameters Pipe'!$C$6)*('Assumptions and Parameters Pipe'!$C$9/'Assumptions and Parameters Pipe'!$C$7) -> 0.10495485
A108: =C57 -> 660.4 | B108: =G57 -> 2816077.5 | C108: =I57 -> 1027868.3 | D108: =0.01*H74 -> 23380.875 | E108: =0.01*H74 -> 23380.875 | F108: =0.001*H74 -> 2338.0875 | G108: =0.005*H74 -> 11690.437 | H108: =SUM(D108:G108) -> 60790.275 | I108: =H108/C108 -> 0.059142086 | J108: =I108*(1/'Assumptions and Parameters Pipe'!$C$6)*('Assumptions and Parameters Pipe'!$C$9/'Assumptions and Parameters Pipe'!$C$7) -> 0.093558102
A109: =C58 -> 711.2 | B109: =G58 -> 3389271.1 | C109: =I58 -> 1237084 | D109: =0.01*H75 -> 25383.924 | E109: =0.01*H75 -> 25383.924 | F109: =0.001*H75 -> 2538.3924 | G109: =0.005*H75 -> 12691.962 | H109: =SUM(D109:G109) -> 65998.202 | I109: =H109/C109 -> 0.053349816 | J109: =I109*(1/'Assumptions and Parameters Pipe'!$C$6)*('Assumptions and Parameters Pipe'!$C$9/'Assumptions and Parameters Pipe'!$C$7) -> 0.084395189
A110: =C59 -> 762 | B110: =G59 -> 4027303.6 | C110: =I59 -> 1469965.8 | D110: =0.01*H76 -> 27492.645 | E110: =0.01*H76 -> 27492.645 | F110: =0.001*H76 -> 2749.2645 | G110: =0.005*H76 -> 13746.322 | H110: =SUM(D110:G110) -> 71480.876 | I110: =H110/C110 -> 0.048627577 | J110: =I110*(1/'Assumptions and Parameters Pipe'!$C$6)*('Assumptions and Parameters Pipe'!$C$9/'Assumptions and Parameters Pipe'!$C$7) -> 0.07692498
A111: =C60 -> 812.8 | B111: =G60 -> 4732451.6 | C111: =I60 -> 1727344.8 | D111: =0.01*H77 -> 29720.041 | E111: =0.01*H77 -> 29720.041 | F111: =0.001*H77 -> 2972.0041 | G111: =0.005*H77 -> 14860.021 | H111: =SUM(D111:G111) -> 77272.107 | I111: =H111/C111 -> 0.044734615 | J111: =I111*(1/'Assumptions and Parameters Pipe'!$C$6)*('Assumptions and Parameters Pipe'!$C$9/'Assumptions and Parameters Pipe'!$C$7) -> 0.070766623

Sheet Assumptions and Parameter Comp
A1: Source Assumptions and Core Equations
A3: Thermodynamic Compressor Assumptions
A4: Category | B4: Parameter | C4: Value | D4: Unit | E4: Source location | F4: Status/ note
A5: Gas property | B5: Hydrogen molar mass | C5: 0.002016 | D5: kg/mol | E5: Transition Accelerator compression brief | F5: Used to convert hydrogen mass flow to molar flow.
A6: Gas property | B6: Heat-capacity ratio | C6: 1.405 | D6: dimensionless | E6: Transition Accelerator compression brief | F6: Ratio of Cp to Cv for hydrogen under the assumed operating conditions.
A7: Gas property | B7: Compressibility factor | C7: 1.03 | D7: dimensionless | E7: Wei thesis / workbook methodology | F7: Average value over the selected 28-to-70 bar compression range. Reassess if pressure or temperature assumptions change.
A8: Thermodynamic | B8: Universal gas constant | C8: 8.314 | D8: J/(mol·K) | E8: Transition Accelerator compression brief | F8: Unit basis must remain consistent with molar flow and temperature in the compressor power equation.
A9: Thermodynamic | B9: Suction temperature | C9: 289 | D9: K | E9: Wei thesis | F9: Compressor inlet temperature. Complete intercooling returns hydrogen to this temperature after each stage.
A10: Pressure | B10: Suction pressure | C10: 28 | D10: bar absolute | E10: Wei thesis / workbook methodology | F10: Matches the outlet pressure of the associated pipeline segment.
A11: Pressure | B11: Discharge pressure | C11: 70 | D11: bar absolute | E11: Transition Accelerator pipeline design / Wei thesis | F11: Matches the inlet pressure of the following pipeline segment.
A12: Staging | B12: Maximum pressure ratio per stage | C12: 2.1 | D12: ratio | E12: Transition Accelerator compression brief | F12: Used to calculate the minimum number of compression stages.
A13: Staging | B13: Equal pressure ratio across stages | C13: TRUE | D13: Boolean | E13: Transition Accelerator compression brief | F13: Assumes each stage applies the same pressure ratio.
A14: Staging | B14: Complete intercooling | C14: TRUE | D14: Boolean | E14: Transition Accelerator compression brief | F14: Hydrogen is cooled to the initial suction temperature after each stage.
A15: Staging | B15: Intercooler pressure drop | C15: 0 | D15: fraction | E15: Transition Accelerator compression brief | F15: Idealized assumption; no pressure loss between stages.
A16: Efficiency | B16: Electric motor efficiency | C16: 0.95 | D16: fraction | E16: Transition Accelerator compression brief | F16: Converts compressor shaft power to electrical input power.
A17: Efficiency | B17: Reference isentropic efficiency | C17: 0.8 | D17: fraction | E17: Transition Accelerator compression brief | F17: Source reference value for large pipeline compressors.
A18: Efficiency | B18: Maximum isentropic efficiency | C18: 0.88 | D18: fraction | E18: Wei thesis | F18: Upper bound used in the capacity-dependent efficiency relationship.
A19: Equipment sizing | B19: Maximum rated power per compressor unit | C19: 16000 | D19: kW/unit | E19: Transition Accelerator compression brief | F19: Required station power above this value must be divided among multiple compressor units.
A20: Equipment sizing | B20: Number of operating compressor units | C20: Ceiling(P_station / 16000) | D20: units | E20: Derived workbook equation | F20: Parallel units are sized so that no individual unit exceeds 16 MW.
A21: Equipment sizing | B21: Rated power per compressor unit | C21: P_station / n_units | D21: kW/unit | E21: Derived workbook equation | F21: Equal sizing across operating units unless an alternative configuration is introduced.
A22: Equipment sizing | B22: Standby compressor units | C22: 0 | D22: units | E22: Workbook methodology | F22: No N+1 redundancy included in the base case. Add only as a separate reliability assumption.
A23: Segment configuration | B23: Reference pipeline segment length | C23: 250 | D23: km | E23: Wei thesis | F23: One recompression station is associated with each 250 km pipeline segment.
A24: Segment configuration | B24: Compressor stations per segment | C24: 1 | D24: station/segment | E24: Workbook methodology | F24: Used to normalize station CAPEX, fixed OPEX, and electricity intensity by distance.
A25: Temporal | B25: Days per year | C25: 365 | D25: days/year | E25: Workbook convention | F25: Used to convert daily hydrogen capacity to annual capacity.
A26: Temporal | B26: Hours per day | C26: 24 | D26: hours/day | E26: Workbook convention | F26: Used to calculate daily compressor electricity consumption.
A27: Temporal | B27: Hours per year | C27: 8760 | D27: hours/year | E27: Workbook convention | F27: Used only where annual full-load operation is explicitly required.
A30: Compressor Cost Assumptions
A31: Category | B31: Parameter | C31: Value | D31: Unit | E31: Source location | F31: Status/ note
A32: CAPEX | B32: Uninstalled cost coefficient | C32: 3083.3 | D32: 2019 CAD coefficient | E32: https://transitionaccelerator.ca/wp-content/uploads/2023/04/TA-Technical-Brief-1.1_TEEA-Hydrogen-Compression_PUBLISHED.pdf | F32: Applied as UC = 3083.3 × P_unit^0.8335, where rated motor power is in kW. Published coefficient already incorporates source escalation and USD-to-CAD conversion.
A33: CAPEX | B33: Scale exponent | C33: 0.8335 | D33: dimensionless | E33: https://transitionaccelerator.ca/wp-content/uploads/2023/04/TA-Technical-Brief-1.1_TEEA-Hydrogen-Compression_PUBLISHED.pdf | F33: Economies-of-scale exponent for the large pipeline-compressor correlation.
A34: CAPEX | B34: Installation factor | C34: 2 | D34: multiplier | E34: https://transitionaccelerator.ca/wp-content/uploads/2023/04/TA-Technical-Brief-1.1_TEEA-Hydrogen-Compression_PUBLISHED.pdf | F34: Converts uninstalled compressor cost to total installed cost: TIC = UC × IF.
A35: CAPEX | B35: Compressor unit lifetime | C35: 15 | D35: years | E35: https://transitionaccelerator.ca/wp-content/uploads/2023/04/TA-Technical-Brief-1.1_TEEA-Hydrogen-Compression_PUBLISHED.pdf | F35: Use as physical technology lifetime for TEMOA. Do not embed a CRF in CostInvest.
A36: CAPEX | B36: Published source currency year | C36: 2019 | D36: year | E36: https://transitionaccelerator.ca/wp-content/uploads/2023/04/TA-Technical-Brief-1.1_TEEA-Hydrogen-Compression_PUBLISHED.pdf | F36: Published compressor cost correlation is reported in 2019 CAD.
A37: CAPEX | B37: Target workbook currency year | C37: 2020 | D37: year | E37: Workbook methodology | F37: All compressor CAPEX and OPEX outputs are converted to real 2020 CAD before normalization.
A38: Indirect CAPEX | B38: Site preparation fraction | C38: 0.05 | D38: fraction of TIC | E38: Wei thesis, Section 2.5.4.2 | F38: Added to compressor TIC when reproducing the Wei implementation.
A39: Indirect CAPEX | B39: Engineering and design fraction | C39: 0.1 | D39: fraction of TIC | E39: Wei thesis, Section 2.5.4.2 | F39: Added to compressor TIC when reproducing the Wei implementation.
A40: Indirect CAPEX | B40: Project contingency fraction | C40: 0.1 | D40: fraction of TIC | E40: Wei thesis, Section 2.5.4.2 | F40: Added to compressor TIC when reproducing the Wei implementation.
A41: Indirect CAPEX | B41: Permitting fraction | C41: 0.03 | D41: fraction of TIC | E41: Wei thesis, Section 2.5.4.2 | F41: One-time capital permitting cost. Distinct from annual licensing and permitting OPEX.
A42: Indirect CAPEX | B42: Total indirect CAPEX fraction | C42: 0.28 | D42: fraction of TIC | E42: Wei thesis, Section 2.5.4.2 | F42: Sum of site preparation, engineering and design, contingency, and permitting.
A43: Indirect CAPEX | B43: Total capital investment | C43: TIC × 1.28 | D43: 2019 CAD | E43: Wei thesis, Equation 2.19 and Section 2.5.4.2 | F43: TCI = TIC plus 28% indirect capital costs under the thesis implementation.
A44: Economic and temporal | B44: GDP Deflator 2019 | C44: 103.3 | D44: price index | E44: https://www150.statcan.gc.ca/t1/tbl1/en/tv.action?pid=3610013001&pickMembers%5B0%5D=2.1&cubeTimeFrame.startYear=2009&cubeTimeFrame.endYear=2020&referencePeriods=20090101%2C20200101 | F44: 2017 base-year convention. Use the same GDP implicit price-index series for both years.
A45: Economic and temporal | B45: GDP Deflator 2020 | C45: 105 | D45: price index | E45: https://www150.statcan.gc.ca/t1/tbl1/en/tv.action?pid=3610013001&pickMembers%5B0%5D=2.1&cubeTimeFrame.startYear=2009&cubeTimeFrame.endYear=2020&referencePeriods=20090101%2C20200101 | F45: 2017 base-year convention. Target price-year index.
A46: Economic and temporal | B46: 2019-to-2020 escalation factor | C46: 105 / 103.3 | D46: multiplier | E46: Derived from Statistics Canada GDP deflators | F46: Apply to costs already expressed in 2019 CAD: Cost_2020CAD = Cost_2019CAD × 105 / 103.3.
A47: Labour OPEX | B47: Annual direct labour-hour coefficient | C47: 288 | D47: hours/year | E47: https://transitionaccelerator.ca/wp-content/uploads/2023/04/TA-Technical-Brief-1.1_TEEA-Hydrogen-Compression_PUBLISHED.pdf | F47: Used in annual labour hours = 288 × (x / 100000)^0.25, where x is compressor design capacity in kg H2/day.
A48: Labour OPEX | B48: Labour scaling exponent | C48: 0.25 | D48: dimensionless | E48: https://transitionaccelerator.ca/wp-content/uploads/2023/04/TA-Technical-Brief-1.1_TEEA-Hydrogen-Compression_PUBLISHED.pdf | F48: Controls sublinear scaling of annual compressor labour requirements with design capacity.
A49: Labour OPEX | B49: Labour capacity denominator | C49: 100000 | D49: kg H2/day | E49: https://transitionaccelerator.ca/wp-content/uploads/2023/04/TA-Technical-Brief-1.1_TEEA-Hydrogen-Compression_PUBLISHED.pdf | F49: Reference capacity used in the compressor labour-hours equation.
A50: Labour OPEX | B50: Direct labour rate | C50: 49.6 | D50: 2019 CAD/hour | E50: Wei thesis, Section 2.5.4.2 | F50: Multiply by annual direct labour hours. Convert to the target currency year using an appropriate labour-cost index or the workbook conversion convention.
A51: Labour OPEX | B51: Indirect labour factor | C51: 0.5 | D51: fraction of direct labour cost | E51: https://transitionaccelerator.ca/wp-content/uploads/2023/04/TA-Technical-Brief-1.1_TEEA-Hydrogen-Compression_PUBLISHED.pdf | F51: Represents overhead such as head-office and non-operating personnel costs.
A52: Labour OPEX | B52: Annual direct labour cost | C52: 288 × (x / 100000)^0.25 × labour rate | D52: currency/year | E52: https://transitionaccelerator.ca/wp-content/uploads/2023/04/TA-Technical-Brief-1.1_TEEA-Hydrogen-Compression_PUBLISHED.pdf | F52: x is compressor design capacity in kg H2/day.
A53: Labour OPEX | B53: Annual indirect labour cost | C53: Direct labour cost × 0.50 | D53: currency/year | E53: https://transitionaccelerator.ca/wp-content/uploads/2023/04/TA-Technical-Brief-1.1_TEEA-Hydrogen-Compression_PUBLISHED.pdf | F53: Annual overhead labour expense.
A54: Fixed OPEX | B54: Compressor maintenance and repairs fraction | C54: 0.04 | D54: fraction of TIC/year | E54: https://transitionaccelerator.ca/wp-content/uploads/2023/04/TA-Technical-Brief-1.1_TEEA-Hydrogen-Compression_PUBLISHED.pdf | F54: Annual operating, maintenance, and repair cost is 4% of total installed cost, not TCI.
A55: Fixed OPEX | B55: Insurance fraction | C55: 0.01 | D55: fraction of TCI/year | E55: https://transitionaccelerator.ca/wp-content/uploads/2023/04/TA-Technical-Brief-1.1_TEEA-Hydrogen-Compression_PUBLISHED.pdf | F55: Annual insurance cost is 1% of total capital investment.
A56: Fixed OPEX | B56: Property tax fraction | C56: 0.01 | D56: fraction of TCI/year | E56: https://transitionaccelerator.ca/wp-content/uploads/2023/04/TA-Technical-Brief-1.1_TEEA-Hydrogen-Compression_PUBLISHED.pdf | F56: Annual property-tax cost is 1% of total capital investment.
A57: Fixed OPEX | B57: Licensing and permitting fraction | C57: 0.001 | D57: fraction of TCI/year | E57: https://transitionaccelerator.ca/wp-content/uploads/2023/04/TA-Technical-Brief-1.1_TEEA-Hydrogen-Compression_PUBLISHED.pdf | F57: Recurring annual licensing and permitting cost. Distinct from the 3% one-time capital permitting allowance.
A58: Fixed OPEX | B58: Compressor maintenance | C58: TIC × 0.04 | D58: currency/year | E58: https://transitionaccelerator.ca/wp-content/uploads/2023/04/TA-Technical-Brief-1.1_TEEA-Hydrogen-Compression_PUBLISHED.pdf | F58: Calculated annual maintenance and repairs.
A59: Fixed OPEX | B59: Insurance | C59: TCI × 0.01 | D59: currency/year | E59: https://transitionaccelerator.ca/wp-content/uploads/2023/04/TA-Technical-Brief-1.1_TEEA-Hydrogen-Compression_PUBLISHED.pdf | F59: Calculated annual insurance cost.
A60: Fixed OPEX | B60: Property tax | C60: TCI × 0.01 | D60: currency/year | E60: https://transitionaccelerator.ca/wp-content/uploads/2023/04/TA-Technical-Brief-1.1_TEEA-Hydrogen-Compression_PUBLISHED.pdf | F60: Calculated annual property-tax cost.
A61: Fixed OPEX | B61: Licensing and permitting | C61: TCI × 0.001 | D61: currency/year | E61: https://transitionaccelerator.ca/wp-content/uploads/2023/04/TA-Technical-Brief-1.1_TEEA-Hydrogen-Compression_PUBLISHED.pdf | F61: Calculated recurring licensing and permitting expense.
A62: Fixed OPEX | B62: Operator labour | C62: Direct labour cost + indirect labour cost | D62: currency/year | E62: https://transitionaccelerator.ca/wp-content/uploads/2023/04/TA-Technical-Brief-1.1_TEEA-Hydrogen-Compression_PUBLISHED.pdf | F62: Capacity-dependent annual labour obligation. Keep separate from TCI-based fixed OPEX for auditing.
A63: Fixed OPEX | B63: Other non-energy OPEX | C63: Insurance + property tax + licensing and permitting + maintenance and repairs | D63: currency/year | E63: https://transitionaccelerator.ca/wp-content/uploads/2023/04/TA-Technical-Brief-1.1_TEEA-Hydrogen-Compression_PUBLISHED.pdf | F63: Non-labour annual fixed OPEX.
A64: Fixed OPEX | B64: Total non-energy OPEX | C64: Direct labour + indirect labour + maintenance and repairs + insurance + property tax + licensing and permitting | D64: currency/year | E64: https://transitionaccelerator.ca/wp-content/uploads/2023/04/TA-Technical-Brief-1.1_TEEA-Hydrogen-Compression_PUBLISHED.pdf | F64: Cannot be represented by one universal percentage because labour depends on capacity, maintenance uses TIC, and the other fixed costs use TCI.
A65: Normalization | B65: Source availability factor | C65: 0.9 | D65: fraction | E65: https://transitionaccelerator.ca/wp-content/uploads/2023/04/TA-Technical-Brief-1.1_TEEA-Hydrogen-Compression_PUBLISHED.pdf | F65: Used by the technical brief when normalizing annual costs per kg H2. Do not automatically embed this in TEMOA costs if activity is modelled endogenously.
A66: Normalization | B66: Days per year | C66: 365 | D66: days/year | E66: Workbook convention | F66: Used to convert daily design capacity to annual throughput.
A67: Efficiency | B67: Capacity-dependent isentropic-efficiency equation | C67: NOT CONSIDERED UNTIL WE HAVE GRID CONNECTION OPTION | D67: dimensionless | E67: Wei thesis / workbook adaptation | F67: Document the independent variable, lower bound, upper bound, and any breakpoint or regression method.

Sheet Transition Accelerator Compress
A1: General Overview
A2: Reconstructs the hydrogen compressor thermodynamic, equipment-sizing, capital-cost, operating-cost, and electricity-consumption calculations for each pipeline capacity case. It links compressor flow cases to the corresponding pipeline design cases, divides required station power among physically allowable compressor units, converts source-year costs to the workbook currency basis, and normalizes compressor CAPEX, fixed OPEX, labour OPEX, and electricity requirements by capacity and reference segment length for combination with the pipeline subsystem.
A5: Notes: | B5: Multistage compressor assumptions:
A6: This is a representative model for a compressor associated with 250km long H2 pipeline segments | B6: i. the work is equal at each stage
A7: Parameters must be adjusted if another distance is chosen (see previous worksheet) | B7: ii. Pressure ratio per stage is equal
A8: Units have been normalized per km to ensure edge distance can be multiplied | B8: iii. Temperature of gas in intercoolers is cooled to original suction temperature of first stage
A9: Current model Assumed Nominal pipeline size = inner diameter | B9: iv. There is no pressure drop or heat losses that occur in intercoolers between stages
A10: Currently, an isentropic multistage reciprocating piston compressor is considered as the reference | B10: v. Isentropic efficiency factor (n,isen) was capped at 0.88 as a performance cap given that curren literature values suggest 0.80 as the current hard cap.
A11: The model uses indirect capital costs of 40% of total investment costs but only 28% were categorized in the accelerator document. This should be treated using sensitvity
A14: Cost Assumptions
A15: Factor | B15: Default Value | C15: Units | D15: Notes | E15: Source
A16: Exchange rate | B16: 0.75 | C16: USD/CAD | D16: 2019 average exchange rate used by the source to convert the underlying compressor cost correlation from USD to CAD. Already embedded in the published 3083.3 coefficient; do not apply again. | E16: The Techno-Economics of Hydrogen Compression, Table 4.2
A17: CEPCI escalation factor | B17: 1.179 | C17: multiplier | D17: Calculated as 619.2 / 525.4 to escalate the underlying 2007 equipment-cost correlation to 2019. Already embedded in the published 3083.3 coefficient; retain only for provenance. | E17: The Techno-Economics of Hydrogen Compression, Table 4.2
A18: Discount rate | B18: 0.08 | C18: fraction | D18: Source weighted-average cost of capital used to calculate the capital recovery factor and reproduce levelized compressor costs. Do not embed this annualization in TEMOA CostInvest. | E18: The Techno-Economics of Hydrogen Compression, Table 4.2
A19: Project lifetime | B19: 15 | C19: years | D19: Source compressor economic lifetime used in the capital recovery factor. Use as the compressor technology lifetime in TEMOA unless a different physical lifetime is selected. | E19: The Techno-Economics of Hydrogen Compression, Table 4.2
A20: Source availability factor | B20: 0.9 | C20: fraction | D20: Source assumption used to calculate annual hydrogen throughput and levelized compressor costs. Represents approximately 10% downtime for maintenance and unplanned outages. | E20: The Techno-Economics of Hydrogen Compression, Section 4.2 and Table 4.2
A21: Workbook design-capacity factor | B21: 1 | C21: fraction | D21: Workbook convention used when annual design capacity is calculated as daily capacity × 365. This is not the source availability assumption and should not constrain endogenous TEMOA activity. | E21: Workbook methodology
A22: Scale exponent | B22: 0.8335 | C22: dimensionless | D22: Exponent in the pipeline-compressor uninstalled-cost relationship: UC = 3083.3 × P^0.8335. Power must be entered in kW. | E22: The Techno-Economics of Hydrogen Compression, Table 4.1
A23: Installation factor | B23: 2 | C23: multiplier | D23: Converts uninstalled compressor equipment cost to total installed cost: TIC = UC × 2. | E23: The Techno-Economics of Hydrogen Compression, Table 4.1
A24: Annual calendar hours | B24: =24*365 -> 8760 | C24: hours/year | D24: Used only for annual full-load electricity calculations. Physical electricity intensity should normally be calculated directly from rated power and hydrogen throughput. | E24: Workbook convention
A25: Electricity price | B25: 0.11 | C25: 2019 CAD/kWh_e | D25: Alberta industrial electricity price used to reproduce source compressor energy OPEX. Prefer mapping compressor electricity as a physical input coefficient in TEMOA rather than embedding this price in CostVariable. | E25: The Techno-Economics of Hydrogen Compression, Table 4.2
A26: Target workbook currency year | B26: 2020 | C26: year | D26: Final compressor CAPEX and non-energy OPEX are converted from 2019 CAD to real 2020 CAD using the selected workbook escalation convention. | E26: Workbook methodology
A27: GDP deflator 2019 | B27: 103.3 | C27: price index | D27: Source-year index for converting 2019 CAD compressor costs to the workbook target price year. Uses the selected Statistics Canada GDP implicit price-index series. | E27: Statistics Canada Table 36-10-0130-01
A28: GDP deflator 2020 | B28: 105 | C28: price index | D28: Target-year index for expressing compressor costs in real 2020 CAD. | E28: Statistics Canada Table 36-10-0130-01
A31: Model Input Paramters
A32: Variable | B32: Description | C32: Default Value | D32: Unit | E32: Status | F32: Notes | G32: Source
A33: M_H2 | B33: Hydrogen molar mass | C33: 0.002 | D33: kg/mol | E33: Input | F33: Use 0.002016 kg/mol rather than 0.002 kg/mol unless reproducing a rounded source calculation. This converts hydrogen mass flow to molar flow. | G33: Transition Accelerator compression brief; standard physical constant
A34: k | B34: Ratio of hydrogen specific heat at constant pressure to specific heat at constant volume, Cp/Cv | C34: 1.405 | D34: dimensionless | E34: Input | F34: Assumed constant over the selected compressor operating range. The Transition Accelerator brief commonly rounds this value to 1.41; retain 1.405 if used consistently in all calculations. | G34: Transition Accelerator compression brief
A35: Z | B35: Average hydrogen compressibility factor | C35: 1.03 | D35: dimensionless | E35: Input | F35: Average value used over the assumed pressure and temperature range. Recalculate or test sensitivity if suction pressure, discharge pressure, or temperature changes materially. | G35: Wei thesis, Section 2.5.2; pipeline-model assumption
A36: r_stage,max | B36: Maximum allowable compression ratio per stage | C36: 2.1 | D36: dimensionless | E36: Input | F36: Used to determine the minimum number of compressor stages. The compression brief notes that feasible ratios vary by compressor type; 2.1 is the selected pipeline-compressor assumption, not a universal limit. | G36: Transition Accelerator compression brief
A37: T_suction | B37: Compressor suction temperature | C37: 289 | D37: K | E37: Input | F37: Assumed approximately equal to ambient temperature. Under complete intercooling, hydrogen is returned to this temperature between stages. | G37: Wei thesis; workbook assumption
A38: R | B38: Universal gas constant | C38: 8.314 | D38: J/(mol·K) | E38: Input | F38: Unit basis must remain consistent with molar flow in mol/s and compressor power in watts. | G38: Transition Accelerator compression brief; standard physical constant
A39: P_suction | B39: Compressor suction pressure | C39: 28 | D39: bar absolute | E39: Input | F39: Matches the outlet pressure of the associated 250 km pipeline segment. This is an adaptation from the Wei thesis; the Transition Accelerator pipeline case study uses a different suction pressure in its reference compressor case. | G39: Wei thesis, Section 2.5.2
A40: P_discharge | B40: Compressor discharge pressure | C40: 70 | D40: bar absolute | E40: Input | F40: Matches the inlet pressure of the following pipeline segment. Used with suction pressure to calculate the overall compression ratio. | G40: Transition Accelerator pipeline brief; Wei thesis
A41: eta_motor | B41: Electric motor efficiency | C41: 0.95 | D41: fraction | E41: Input | F41: Converts compressor shaft power to required electrical input power: P_electric = P_shaft / eta_motor. | G41: Transition Accelerator compression brief
A43: Dervied Model Units
A46: Derived Model Units
A47: Variable | B47: Description | C47: Default Value | D47: Units | E47: Status | F47: Notes | G47: Source
A48: r_p | B48: Overall compression ratio | C48: =C40/C39 -> 2.5 | D48: dimensionless | E48: Derived | F48: P_discharge / P_suction = 70 / 28. | G48: Derived workbook calculation
A49: N_raw | B49: Unrounded number of compressor stages | C49: =(LOG10(C40/C39))/(LOG10(C36)) -> 1.2349975 | D49: stages | E49: Derived | F49: LN(r_p) / LN(r_stage,max). | G49: Derived workbook calculation
A50: N_stages | B50: Integer number of compressor stages | C50: =ROUNDUP(C49, 0) -> 2 | D50: stages | E50: Derived | F50: CEILING(N_raw,1). Rounded upward so the selected maximum compression ratio per stage is not exceeded. | G50: Derived workbook calculation
A53: Transmission Pipeline Capacity Summary
A54: Pipeline sizes (inch, inner diameter) | B54: Required pipeline Thickness (mm) | C54: Pipeline sizes (mm, inner diameter) | D54: Gas flow rate (Sm^3/day) | E54: Daily Capacity (kg H2 / day)
A55: ='Transition Accelerator Pipe'!B48 -> 8 | B55: ='Transition Accelerator Pipe'!D48 -> 2.0450886 | C55: ='Transition Accelerator Pipe'!C48 -> 203.2 | D55: ='Transition Accelerator Pipe'!F48 -> 1773250.7 | E55: ='Transition Accelerator Pipe'!G48 -> 147889.11
A56: ='Transition Accelerator Pipe'!B49 -> 10 | B56: ='Transition Accelerator Pipe'!D49 -> 2.5563607 | C56: ='Transition Accelerator Pipe'!C49 -> 254 | D56: ='Transition Accelerator Pipe'!F49 -> 3097741.6 | E56: ='Transition Accelerator Pipe'!G49 -> 258351.65
A57: ='Transition Accelerator Pipe'!B50 -> 12 | B57: ='Transition Accelerator Pipe'!D50 -> 3.0676329 | C57: ='Transition Accelerator Pipe'!C50 -> 304.8 | D57: ='Transition Accelerator Pipe'!F50 -> 4886504.5 | E57: ='Transition Accelerator Pipe'!G50 -> 407534.47
A58: ='Transition Accelerator Pipe'!B51 -> 14 | B58: ='Transition Accelerator Pipe'!D51 -> 3.578905 | C58: ='Transition Accelerator Pipe'!C51 -> 355.6 | D58: ='Transition Accelerator Pipe'!F51 -> 7183982.6 | E58: ='Transition Accelerator Pipe'!G51 -> 599144.15
A59: ='Transition Accelerator Pipe'!B52 -> 16 | B59: ='Transition Accelerator Pipe'!D52 -> 4.0901771 | C59: ='Transition Accelerator Pipe'!C52 -> 406.4 | D59: ='Transition Accelerator Pipe'!F52 -> 10031021 | E59: ='Transition Accelerator Pipe'!G52 -> 836587.15
A60: ='Transition Accelerator Pipe'!B53 -> 18 | B60: ='Transition Accelerator Pipe'!D53 -> 4.6014493 | C60: ='Transition Accelerator Pipe'!C53 -> 457.2 | D60: ='Transition Accelerator Pipe'!F53 -> 13465623 | E60: ='Transition Accelerator Pipe'!G53 -> 1123032.9
A61: ='Transition Accelerator Pipe'!B54 -> 20 | B61: ='Transition Accelerator Pipe'!D54 -> 5.1127214 | C61: ='Transition Accelerator Pipe'!C54 -> 508 | D61: ='Transition Accelerator Pipe'!F54 -> 17523473 | E61: ='Transition Accelerator Pipe'!G54 -> 1461457.6
A62: ='Transition Accelerator Pipe'!B55 -> 22 | B62: ='Transition Accelerator Pipe'!D55 -> 5.6239936 | C62: ='Transition Accelerator Pipe'!C55 -> 558.8 | D62: ='Transition Accelerator Pipe'!F55 -> 22238315 | E62: ='Transition Accelerator Pipe'!G55 -> 1854675.5
A63: ='Transition Accelerator Pipe'!B56 -> 24 | B63: ='Transition Accelerator Pipe'!D56 -> 6.1352657 | C63: ='Transition Accelerator Pipe'!C56 -> 609.6 | D63: ='Transition Accelerator Pipe'!F56 -> 27642243 | E63: ='Transition Accelerator Pipe'!G56 -> 2305363.1
A64: ='Transition Accelerator Pipe'!B57 -> 26 | B64: ='Transition Accelerator Pipe'!D57 -> 6.6465378 | C64: ='Transition Accelerator Pipe'!C57 -> 660.4 | D64: ='Transition Accelerator Pipe'!F57 -> 33765917 | E64: ='Transition Accelerator Pipe'!G57 -> 2816077.5
A65: ='Transition Accelerator Pipe'!B58 -> 28 | B65: ='Transition Accelerator Pipe'!D58 -> 7.15781 | C65: ='Transition Accelerator Pipe'!C58 -> 711.2 | D65: ='Transition Accelerator Pipe'!F58 -> 40638743 | E65: ='Transition Accelerator Pipe'!G58 -> 3389271.1
A66: ='Transition Accelerator Pipe'!B59 -> 30 | B66: ='Transition Accelerator Pipe'!D59 -> 7.6690821 | C66: ='Transition Accelerator Pipe'!C59 -> 762 | D66: ='Transition Accelerator Pipe'!F59 -> 48289012 | E66: ='Transition Accelerator Pipe'!G59 -> 4027303.6
A67: ='Transition Accelerator Pipe'!B60 -> 32 | B67: ='Transition Accelerator Pipe'!D60 -> 8.1803543 | C67: ='Transition Accelerator Pipe'!C60 -> 812.8 | D67: ='Transition Accelerator Pipe'!F60 -> 56744024 | E67: ='Transition Accelerator Pipe'!G60 -> 4732451.6
A69: Transmission Pipeline H2 Compressor Power Estimation (for a 250km pipe)
A70: Molar flow (mol H2/s) | B70: Isentropic efficiency factor (n,isen) | C70: Power, compressor (kW) | D70: Rated compressor Power (kW) | E70: Energy Intensity (kWh /kg H2) | F70: Energy Intensity (MWh /t H2)
A71: =(E55)/($C$33*24*60*60) -> 855.83977 | B71: =0.0682*LOG10(A71)+0.628 -> 0.82798917 | C71: =($C$50*($C$34/($C$34-1))*($C$35/B71)*$C$37*A71*$C$38*((($C$40/$C$39)^(($C$34-1)/($C$34*$C$50)))-1))/1000 -> 2505.7568 | D71: =C71/$C$41 -> 2637.6387 | E71: =(D71*24)/E55 -> 0.42804591 | F71: =E71*(1000/1000) -> 0.42804591
A72: =(E56)/($C$33*24*60*60) -> 1495.0906 | B72: =0.0682*LOG10(A72)+0.628 -> 0.84451232 | C72: =($C$50*($C$34/($C$34-1))*($C$35/B72)*$C$37*A72*$C$38*((($C$40/$C$39)^(($C$34-1)/($C$34*$C$50)))-1))/1000 -> 4291.7322 | D72: =C72/$C$41 -> 4517.6128 | E72: =(D72*24)/E56 -> 0.41967105 | F72: =E72*(1000/1000) -> 0.41967105
A73: =(E57)/($C$33*24*60*60) -> 2358.4171 | B73: =0.0682*LOG10(A73)+0.628 -> 0.85801273 | C73: =($C$50*($C$34/($C$34-1))*($C$35/B73)*$C$37*A73*$C$38*((($C$40/$C$39)^(($C$34-1)/($C$34*$C$50)))-1))/1000 -> 6663.4323 | D73: =C73/$C$41 -> 7014.1393 | E73: =(D73*24)/E57 -> 0.41306774 | F73: =E73*(1000/1000) -> 0.41306774
A74: =(E58)/($C$33*24*60*60) -> 3467.2694 | B74: =0.0682*LOG10(A74)+0.628 -> 0.86942715 | C74: =($C$50*($C$34/($C$34-1))*($C$35/B74)*$C$37*A74*$C$38*((($C$40/$C$39)^(($C$34-1)/($C$34*$C$50)))-1))/1000 -> 9667.7518 | D74: =C74/$C$41 -> 10176.581 | E74: =(D74*24)/E58 -> 0.40764471 | F74: =E74*(1000/1000) -> 0.40764471
A75: =(E59)/($C$33*24*60*60) -> 4841.3608 | B75: =0.0682*LOG10(A75)+0.628 -> 0.87931478 | C75: =($C$50*($C$34/($C$34-1))*($C$35/B75)*$C$37*A75*$C$38*((($C$40/$C$39)^(($C$34-1)/($C$34*$C$50)))-1))/1000 -> 13347.324 | D75: =C75/$C$41 -> 14049.814 | E75: =(D75*24)/E59 -> 0.40306086 | F75: =E75*(1000/1000) -> 0.40306086
A76: =(E60)/($C$33*24*60*60) -> 6499.0333 | B76: 0.88 | C76: =($C$50*($C$34/($C$34-1))*($C$35/B76)*$C$37*A76*$C$38*((($C$40/$C$39)^(($C$34-1)/($C$34*$C$50)))-1))/1000 -> 17903.469 | D76: =C76/$C$41 -> 18845.757 | E76: =(D76*24)/E60 -> 0.40274702 | F76: =E76*(1000/1000) -> 0.40274702
A77: =(E61)/($C$33*24*60*60) -> 8457.5093 | B77: 0.88 | C77: =($C$50*($C$34/($C$34-1))*($C$35/B77)*$C$37*A77*$C$38*((($C$40/$C$39)^(($C$34-1)/($C$34*$C$50)))-1))/1000 -> 23298.659 | D77: =C77/$C$41 -> 24524.904 | E77: =(D77*24)/E61 -> 0.40274702 | F77: =E77*(1000/1000) -> 0.40274702
A78: =(E62)/($C$33*24*60*60) -> 10733.076 | B78: 0.88 | C78: =($C$50*($C$34/($C$34-1))*($C$35/B78)*$C$37*A78*$C$38*((($C$40/$C$39)^(($C$34-1)/($C$34*$C$50)))-1))/1000 -> 29567.366 | D78: =C78/$C$41 -> 31123.543 | E78: =(D78*24)/E62 -> 0.40274702 | F78: =E78*(1000/1000) -> 0.40274702
A79: =(E63)/($C$33*24*60*60) -> 13341.222 | B79: 0.88 | C79: =($C$50*($C$34/($C$34-1))*($C$35/B79)*$C$37*A79*$C$38*((($C$40/$C$39)^(($C$34-1)/($C$34*$C$50)))-1))/1000 -> 36752.259 | D79: =C79/$C$41 -> 38686.588 | E79: =(D79*24)/E63 -> 0.40274702 | F79: =E79*(1000/1000) -> 0.40274702
A80: =(E64)/($C$33*24*60*60) -> 16296.745 | B80: 0.88 | C80: =($C$50*($C$34/($C$34-1))*($C$35/B80)*$C$37*A80*$C$38*((($C$40/$C$39)^(($C$34-1)/($C$34*$C$50)))-1))/1000 -> 44894.103 | D80: =C80/$C$41 -> 47256.951 | E80: =(D80*24)/E64 -> 0.40274702 | F80: =E80*(1000/1000) -> 0.40274702
A81: =(E65)/($C$33*24*60*60) -> 19613.838 | B81: 0.88 | C81: =($C$50*($C$34/($C$34-1))*($C$35/B81)*$C$37*A81*$C$38*((($C$40/$C$39)^(($C$34-1)/($C$34*$C$50)))-1))/1000 -> 54031.996 | D81: =C81/$C$41 -> 56875.785 | E81: =(D81*24)/E65 -> 0.40274702 | F81: =E81*(1000/1000) -> 0.40274702
A82: =(E66)/($C$33*24*60*60) -> 23306.155 | B82: 0.88 | C82: =($C$50*($C$34/($C$34-1))*($C$35/B82)*$C$37*A82*$C$38*((($C$40/$C$39)^(($C$34-1)/($C$34*$C$50)))-1))/1000 -> 64203.554 | D82: =C82/$C$41 -> 67582.688 | E82: =(D82*24)/E66 -> 0.40274702 | F82: =E82*(1000/1000) -> 0.40274702
A83: =(E67)/($C$33*24*60*60) -> 27386.873 | B83: 0.88 | C83: =($C$50*($C$34/($C$34-1))*($C$35/B83)*$C$37*A83*$C$38*((($C$40/$C$39)^(($C$34-1)/($C$34*$C$50)))-1))/1000 -> 75445.072 | D83: =C83/$C$41 -> 79415.865 | E83: =(D83*24)/E67 -> 0.40274702 | F83: =E83*(1000/1000) -> 0.40274702
A86: High flow rate - Moderate Compression Ratio H2 Compression CAPEX
A87: Pipeline sizes (inch, inner diameter) | B87: Daily Capacity (kg H2 / day) | C87: Rated compressor Power (kW) | D87: Uninstalled Costs ($ 2019 CAD / compressor station) | E87: Total Installed Costs ($ 2019 CAD / compressor station) | F87: Total Capital Investments ($ 2019 CAD / compressor station) | G87: Total Capital Investments ($ 2019 CAD / km) | H87: Total Capital Investments ($ 2020 CAD / km)
A88: ='Transition Accelerator Pipe'!B48 -> 8 | B88: =E55 -> 147889.11 | C88: =D71 -> 2637.6387 | D88: =3083.35*(C88^$B$22) -> 2190815.4 | E88: =D88*$B$23 -> 4381630.8 | F88: =E88+(E88*'Assumptions and Parameters Pipe'!$C$11) -> 6134283.2 | G88: =F88/'Transition Accelerator Pipe'!$C$39 -> 24537.329 | H88: =G88*('Assumptions and Parameters Pipe'!$C$9/'Assumptions and Parameters Pipe'!$C$8) -> 24941.138
A89: ='Transition Accelerator Pipe'!B49 -> 10 | B89: =E56 -> 258351.65 | C89: =D72 -> 4517.6128 | D89: =3083.35*(C89^$B$22) -> 3430753.2 | E89: =D89*$B$23 -> 6861506.5 | F89: =E89+(E89*'Assumptions and Parameters Pipe'!$C$11) -> 9606109.1 | G89: =F89/'Transition Accelerator Pipe'!$C$39 -> 38424.744 | H89: =G89*('Assumptions and Parameters Pipe'!$C$9/'Assumptions and Parameters Pipe'!$C$8) -> 39057.097
A90: ='Transition Accelerator Pipe'!B50 -> 12 | B90: =E57 -> 407534.47 | C90: =D73 -> 7014.1393 | D90: =3083.35*(C90^$B$22) -> 4950424.9 | E90: =D90*$B$23 -> 9900849.8 | F90: =E90+(E90*'Assumptions and Parameters Pipe'!$C$11) -> 13861190 | G90: =F90/'Transition Accelerator Pipe'!$C$39 -> 55445.202 | H90: =G90*('Assumptions and Parameters Pipe'!$C$9/'Assumptions and Parameters Pipe'!$C$8) -> 56357.66
A91: ='Transition Accelerator Pipe'!B51 -> 14 | B91: =E58 -> 599144.15 | C91: =D74 -> 10176.581 | D91: =3083.35*(C91^$B$22) -> 6750858.4 | E91: =D91*$B$23 -> 13501717 | F91: =E91+(E91*'Assumptions and Parameters Pipe'!$C$11) -> 18902404 | G91: =F91/'Transition Accelerator Pipe'!$C$39 -> 75610.219 | H91: =G91*('Assumptions and Parameters Pipe'!$C$9/'Assumptions and Parameters Pipe'!$C$8) -> 76854.531
A92: ='Transition Accelerator Pipe'!B52 -> 16 | B92: =E59 -> 836587.15 | C92: =D75 -> 14049.814 | D92: =3083.35*(C92^$B$22) -> 8832959.8 | E92: =D92*$B$23 -> 17665920 | F92: =E92+(E92*'Assumptions and Parameters Pipe'!$C$11) -> 24732288 | G92: =F92/'Transition Accelerator Pipe'!$C$39 -> 98929.942 | H92: =G92*('Assumptions and Parameters Pipe'!$C$9/'Assumptions and Parameters Pipe'!$C$8) -> 100558.02
A93: ='Transition Accelerator Pipe'!B53 -> 18 | B93: =E60 -> 1123032.9 | C93: =D76 -> 18845.757 | D93: =3083.35*(C93^$B$22) -> 11282708 | E93: =D93*$B$23 -> 22565416 | F93: =E93+(E93*'Assumptions and Parameters Pipe'!$C$11) -> 31591583 | G93: =F93/'Transition Accelerator Pipe'!$C$39 -> 126367.34 | H93: =G93*('Assumptions and Parameters Pipe'!$C$9/'Assumptions and Parameters Pipe'!$C$8) -> 128446.96
A94: ='Transition Accelerator Pipe'!B54 -> 20 | B94: =E61 -> 1461457.6 | C94: =D77 -> 24524.904 | D94: =3083.35*(C94^$B$22) -> 14052724 | E94: =D94*$B$23 -> 28105448 | F94: =E94+(E94*'Assumptions and Parameters Pipe'!$C$11) -> 39347628 | G94: =F94/'Transition Accelerator Pipe'!$C$39 -> 157391.77 | H94: =G94*('Assumptions and Parameters Pipe'!$C$9/'Assumptions and Parameters Pipe'!$C$8) -> 159981.95
A95: ='Transition Accelerator Pipe'!B55 -> 22 | B95: =E62 -> 1854675.5 | C95: =D78 -> 31123.543 | D95: =3083.35*(C95^$B$22) -> 17140068 | E95: =D95*$B$23 -> 34280135 | F95: =E95+(E95*'Assumptions and Parameters Pipe'!$C$11) -> 47992189 | G95: =F95/'Transition Accelerator Pipe'!$C$39 -> 191970.29 | H95: =G95*('Assumptions and Parameters Pipe'!$C$9/'Assumptions and Parameters Pipe'!$C$8) -> 195129.53
A96: ='Transition Accelerator Pipe'!B56 -> 24 | B96: =E63 -> 2305363.1 | C96: =D79 -> 38686.588 | D96: =3083.35*(C96^$B$22) -> 20547285 | E96: =D96*$B$23 -> 41094570 | F96: =E96+(E96*'Assumptions and Parameters Pipe'!$C$11) -> 57532398 | G96: =F96/'Transition Accelerator Pipe'!$C$39 -> 230131.43 | H96: =G96*('Assumptions and Parameters Pipe'!$C$9/'Assumptions and Parameters Pipe'!$C$8) -> 233918.69
A97: ='Transition Accelerator Pipe'!B57 -> 26 | B97: =E64 -> 2816077.5 | C97: =D80 -> 47256.951 | D97: =3083.35*(C97^$B$22) -> 24276719 | E97: =D97*$B$23 -> 48553437 | F97: =E97+(E97*'Assumptions and Parameters Pipe'!$C$11) -> 67974812 | G97: =F97/'Transition Accelerator Pipe'!$C$39 -> 271901.42 | H97: =G97*('Assumptions and Parameters Pipe'!$C$9/'Assumptions and Parameters Pipe'!$C$8) -> 276376.08
A98: ='Transition Accelerator Pipe'!B58 -> 28 | B98: =E65 -> 3389271.1 | C98: =D81 -> 56875.785 | D98: =3083.35*(C98^$B$22) -> 28330538 | E98: =D98*$B$23 -> 56661075 | F98: =E98+(E98*'Assumptions and Parameters Pipe'!$C$11) -> 79325506 | G98: =F98/'Transition Accelerator Pipe'!$C$39 -> 317304.56 | H98: =G98*('Assumptions and Parameters Pipe'!$C$9/'Assumptions and Parameters Pipe'!$C$8) -> 322526.42
A99: ='Transition Accelerator Pipe'!B59 -> 30 | B99: =E66 -> 4027303.6 | C99: =D82 -> 67582.688 | D99: =3083.35*(C99^$B$22) -> 32710764 | E99: =D99*$B$23 -> 65421527 | F99: =E99+(E99*'Assumptions and Parameters Pipe'!$C$11) -> 91590138 | G99: =F99/'Transition Accelerator Pipe'!$C$39 -> 366363.49 | H99: =G99*('Assumptions and Parameters Pipe'!$C$9/'Assumptions and Parameters Pipe'!$C$8) -> 372392.7
A100: ='Transition Accelerator Pipe'!B60 -> 32 | B100: =E67 -> 4732451.6 | C100: =D83 -> 79415.865 | D100: =3083.35*(C100^$B$22) -> 37419289 | E100: =D100*$B$23 -> 74838579 | F100: =E100+(E100*'Assumptions and Parameters Pipe'!$C$11) -> 1.0477401e+08 | G100: =F100/'Transition Accelerator Pipe'!$C$39 -> 419099.4 | H100: =G100*('Assumptions and Parameters Pipe'!$C$9/'Assumptions and Parameters Pipe'!$C$8) -> 425996.48
A103: High flow rate - Moderate Compression Ratio H2 Compression Energy OPEX, Variable (note: this is a placeholder until we use an internal ELC_GRID technology to link to provincial grid pricing)
A104: Pipeline sizes (inch, inner diameter) | B104: Daily Capacity (kg H2 / day) | C104: Annual Capacity (t H2 / yr) | D104: Rated compressor Power (kW) | E104: Electrical Energy Cost ($ 2019 CAD / yr) | F104: Electrical Energy Cost ($ 2020 CAD / yr) | G104: Electrical Energy Cost ($ 2020 CAD / t H2*km)
A105: =A55 -> 8 | B105: =E55 -> 147889.11 | C105: =B105/(1000/365) -> 53979.526 | D105: =D71 -> 2637.6387 | E105: =D105*24*365*$B$25*$B$21 -> 2541628.7 | F105: =E105*('Assumptions and Parameters Pipe'!$C$9/'Assumptions and Parameters Pipe'!$C$8) -> 2583456.1 | G105: =(F105/C105)/'Transition Accelerator Pipe'!$C$39 -> 0.19144123
A106: =A56 -> 10 | B106: =E56 -> 258351.65 | C106: =B106/(1000/365) -> 94298.351 | D106: =D72 -> 4517.6128 | E106: =D106*24*365*$B$25*$B$21 -> 4353171.7 | F106: =E106*('Assumptions and Parameters Pipe'!$C$9/'Assumptions and Parameters Pipe'!$C$8) -> 4424811.5 | G106: =(F106/C106)/'Transition Accelerator Pipe'!$C$39 -> 0.18769562
A107: =A57 -> 12 | B107: =E57 -> 407534.47 | C107: =B107/(1000/365) -> 148750.08 | D107: =D73 -> 7014.1393 | E107: =D107*24*365*$B$25*$B$21 -> 6758824.6 | F107: =E107*('Assumptions and Parameters Pipe'!$C$9/'Assumptions and Parameters Pipe'!$C$8) -> 6870054 | G107: =(F107/C107)/'Transition Accelerator Pipe'!$C$39 -> 0.18474233
A108: =A58 -> 14 | B108: =E58 -> 599144.15 | C108: =B108/(1000/365) -> 218687.62 | D108: =D74 -> 10176.581 | E108: =D108*24*365*$B$25*$B$21 -> 9806153.3 | F108: =E108*('Assumptions and Parameters Pipe'!$C$9/'Assumptions and Parameters Pipe'!$C$8) -> 9967532.4 | G108: =(F108/C108)/'Transition Accelerator Pipe'!$C$39 -> 0.1823169
A109: =A59 -> 16 | B109: =E59 -> 836587.15 | C109: =B109/(1000/365) -> 305354.31 | D109: =D75 -> 14049.814 | E109: =D109*24*365*$B$25*$B$21 -> 13538401 | F109: =E109*('Assumptions and Parameters Pipe'!$C$9/'Assumptions and Parameters Pipe'!$C$8) -> 13761201 | G109: =(F109/C109)/'Transition Accelerator Pipe'!$C$39 -> 0.18026681
A110: =A60 -> 18 | B110: =E60 -> 1123032.9 | C110: =B110/(1000/365) -> 409907.03 | D110: =D76 -> 18845.757 | E110: =D110*24*365*$B$25*$B$21 -> 18159772 | F110: =E110*('Assumptions and Parameters Pipe'!$C$9/'Assumptions and Parameters Pipe'!$C$8) -> 18458625 | G110: =(F110/C110)/'Transition Accelerator Pipe'!$C$39 -> 0.18012644
A111: =A61 -> 20 | B111: =E61 -> 1461457.6 | C111: =B111/(1000/365) -> 533432.03 | D111: =D77 -> 24524.904 | E111: =D111*24*365*$B$25*$B$21 -> 23632197 | F111: =E111*('Assumptions and Parameters Pipe'!$C$9/'Assumptions and Parameters Pipe'!$C$8) -> 24021111 | G111: =(F111/C111)/'Transition Accelerator Pipe'!$C$39 -> 0.18012644
A112: =A62 -> 22 | B112: =E62 -> 1854675.5 | C112: =B112/(1000/365) -> 676956.56 | D112: =D78 -> 31123.543 | E112: =D112*24*365*$B$25*$B$21 -> 29990646 | F112: =E112*('Assumptions and Parameters Pipe'!$C$9/'Assumptions and Parameters Pipe'!$C$8) -> 30484200 | G112: =(F112/C112)/'Transition Accelerator Pipe'!$C$39 -> 0.18012644
A113: =A63 -> 24 | B113: =E63 -> 2305363.1 | C113: =B113/(1000/365) -> 841457.53 | D113: =D79 -> 38686.588 | E113: =D113*24*365*$B$25*$B$21 -> 37278396 | F113: =E113*('Assumptions and Parameters Pipe'!$C$9/'Assumptions and Parameters Pipe'!$C$8) -> 37891884 | G113: =(F113/C113)/'Transition Accelerator Pipe'!$C$39 -> 0.18012644
A114: =A64 -> 26 | B114: =E64 -> 2816077.5 | C114: =B114/(1000/365) -> 1027868.3 | D114: =D80 -> 47256.951 | E114: =D114*24*365*$B$25*$B$21 -> 45536798 | F114: =E114*('Assumptions and Parameters Pipe'!$C$9/'Assumptions and Parameters Pipe'!$C$8) -> 46286193 | G114: =(F114/C114)/'Transition Accelerator Pipe'!$C$39 -> 0.18012644
A115: =A65 -> 28 | B115: =E65 -> 3389271.1 | C115: =B115/(1000/365) -> 1237084 | D115: =D81 -> 56875.785 | E115: =D115*24*365*$B$25*$B$21 -> 54805507 | F115: =E115*('Assumptions and Parameters Pipe'!$C$9/'Assumptions and Parameters Pipe'!$C$8) -> 55707436 | G115: =(F115/C115)/'Transition Accelerator Pipe'!$C$39 -> 0.18012644
A116: =A66 -> 30 | B116: =E66 -> 4027303.6 | C116: =B116/(1000/365) -> 1469965.8 | D116: =D82 -> 67582.688 | E116: =D116*24*365*$B$25*$B$21 -> 65122678 | F116: =E116*('Assumptions and Parameters Pipe'!$C$9/'Assumptions and Parameters Pipe'!$C$8) -> 66194397 | G116: =(F116/C116)/'Transition Accelerator Pipe'!$C$39 -> 0.18012644
...

Sheet Normalized Transmission Costs
A1: Distribution Cost-Capacity CAPEX Estimation
A2: Pipeline sizes (inch, inner diameter) | B2: Gas flow rate (Sm^3/day) | C2: Daily Capacity (kg H2 / day) | D2: Annual Capacity (t H2 / year) | E2: Total Capital Investments, pipe ($ 2020 CAD / km) | F2: Total Capital Investments, compressor ($ 2020 CAD / km) | G2: Total CAPEX ($ 2020 CAD / km)
A3: ='Transition Accelerator Pipe'!B48 -> 8 | B3: ='Transition Accelerator Pipe'!F48 -> 1773250.7 | C3: ='Transition Accelerator Pipe'!G48 -> 147889.11 | D3: ='Transition Accelerator Pipe'!I48 -> 53979.526 | E3: ='Transition Accelerator Pipe'!I65 -> 1369179.9 | F3: ='Transition Accelerator Compress'!H88 -> 24941.138 | G3: =SUM(E3:F3) -> 1394121
A4: ='Transition Accelerator Pipe'!B49 -> 10 | B4: ='Transition Accelerator Pipe'!F49 -> 3097741.6 | C4: ='Transition Accelerator Pipe'!G49 -> 258351.65 | D4: ='Transition Accelerator Pipe'!I49 -> 94298.351 | E4: ='Transition Accelerator Pipe'!I66 -> 1593404 | F4: ='Transition Accelerator Compress'!H89 -> 39057.097 | G4: =SUM(E4:F4) -> 1632461.1
A5: ='Transition Accelerator Pipe'!B50 -> 12 | B5: ='Transition Accelerator Pipe'!F50 -> 4886504.5 | C5: ='Transition Accelerator Pipe'!G50 -> 407534.47 | D5: ='Transition Accelerator Pipe'!I50 -> 148750.08 | E5: ='Transition Accelerator Pipe'!I67 -> 1824570.5 | F5: ='Transition Accelerator Compress'!H90 -> 56357.66 | G5: =SUM(E5:F5) -> 1880928.2
A6: ='Transition Accelerator Pipe'!B51 -> 14 | B6: ='Transition Accelerator Pipe'!F51 -> 7183982.6 | C6: ='Transition Accelerator Pipe'!G51 -> 599144.15 | D6: ='Transition Accelerator Pipe'!I51 -> 218687.62 | E6: ='Transition Accelerator Pipe'!I68 -> 2063258.7 | F6: ='Transition Accelerator Compress'!H91 -> 76854.531 | G6: =SUM(E6:F6) -> 2140113.3
A7: ='Transition Accelerator Pipe'!B52 -> 16 | B7: ='Transition Accelerator Pipe'!F52 -> 10031021 | C7: ='Transition Accelerator Pipe'!G52 -> 836587.15 | D7: ='Transition Accelerator Pipe'!I52 -> 305354.31 | E7: ='Transition Accelerator Pipe'!I69 -> 2310135.5 | F7: ='Transition Accelerator Compress'!H92 -> 100558.02 | G7: =SUM(E7:F7) -> 2410693.6
A8: ='Transition Accelerator Pipe'!B53 -> 18 | B8: ='Transition Accelerator Pipe'!F53 -> 13465623 | C8: ='Transition Accelerator Pipe'!G53 -> 1123032.9 | D8: ='Transition Accelerator Pipe'!I53 -> 409907.03 | E8: ='Transition Accelerator Pipe'!I70 -> 2565968.7 | F8: ='Transition Accelerator Compress'!H93 -> 128446.96 | G8: =SUM(E8:F8) -> 2694415.6
A9: ='Transition Accelerator Pipe'!B54 -> 20 | B9: ='Transition Accelerator Pipe'!F54 -> 17523473 | C9: ='Transition Accelerator Pipe'!G54 -> 1461457.6 | D9: ='Transition Accelerator Pipe'!I54 -> 533432.03 | E9: ='Transition Accelerator Pipe'!I71 -> 2831641.9 | F9: ='Transition Accelerator Compress'!H94 -> 159981.95 | G9: =SUM(E9:F9) -> 2991623.9
A10: ='Transition Accelerator Pipe'!B55 -> 22 | B10: ='Transition Accelerator Pipe'!F55 -> 22238315 | C10: ='Transition Accelerator Pipe'!G55 -> 1854675.5 | D10: ='Transition Accelerator Pipe'!I55 -> 676956.56 | E10: ='Transition Accelerator Pipe'!I72 -> 3108172.8 | F10: ='Transition Accelerator Compress'!H95 -> 195129.53 | G10: =SUM(E10:F10) -> 3303302.3
A11: ='Transition Accelerator Pipe'!B56 -> 24 | B11: ='Transition Accelerator Pipe'!F56 -> 27642243 | C11: ='Transition Accelerator Pipe'!G56 -> 2305363.1 | D11: ='Transition Accelerator Pipe'!I56 -> 841457.53 | E11: ='Transition Accelerator Pipe'!I73 -> 3396732.5 | F11: ='Transition Accelerator Compress'!H96 -> 233918.69 | G11: =SUM(E11:F11) -> 3630651.2
A12: ='Transition Accelerator Pipe'!B57 -> 26 | B12: ='Transition Accelerator Pipe'!F57 -> 33765917 | C12: ='Transition Accelerator Pipe'!G57 -> 2816077.5 | D12: ='Transition Accelerator Pipe'!I57 -> 1027868.3 | E12: ='Transition Accelerator Pipe'!I74 -> 3698669.5 | F12: ='Transition Accelerator Compress'!H97 -> 276376.08 | G12: =SUM(E12:F12) -> 3975045.6
A13: ='Transition Accelerator Pipe'!B58 -> 28 | B13: ='Transition Accelerator Pipe'!F58 -> 40638743 | C13: ='Transition Accelerator Pipe'!G58 -> 3389271.1 | D13: ='Transition Accelerator Pipe'!I58 -> 1237084 | E13: ='Transition Accelerator Pipe'!I75 -> 4015536 | F13: ='Transition Accelerator Compress'!H98 -> 322526.42 | G13: =SUM(E13:F13) -> 4338062.4
A14: ='Transition Accelerator Pipe'!B59 -> 30 | B14: ='Transition Accelerator Pipe'!F59 -> 48289012 | C14: ='Transition Accelerator Pipe'!G59 -> 4027303.6 | D14: ='Transition Accelerator Pipe'!I59 -> 1469965.8 | E14: ='Transition Accelerator Pipe'!I76 -> 4349118.9 | F14: ='Transition Accelerator Compress'!H99 -> 372392.7 | G14: =SUM(E14:F14) -> 4721511.6
A15: ='Transition Accelerator Pipe'!B60 -> 32 | B15: ='Transition Accelerator Pipe'!F60 -> 56744024 | C15: ='Transition Accelerator Pipe'!G60 -> 4732451.6 | D15: ='Transition Accelerator Pipe'!I60 -> 1727344.8 | E15: ='Transition Accelerator Pipe'!I77 -> 4701475.4 | F15: ='Transition Accelerator Compress'!H100 -> 425996.48 | G15: =SUM(E15:F15) -> 5127471.9
A18: Distribution Cost-Capacity Variable OPEX Estimation
A19: Pipeline sizes (inch, inner diameter) | B19: Gas flow rate (Sm^3/day) | C19: Daily Capacity (kg H2 / day) | D19: Annual Capacity (t H2 / year) | E19: Electrical Energy Cost ($ 2020 CAD / t H2*km) | F19: Total Variable OPEX ($ 2020 CAD/ t H2*km) | G19: Total Variable OPEX ($ 2020 CAD/ km)
A20: ='Transition Accelerator Pipe'!B48 -> 8 | B20: ='Transition Accelerator Pipe'!F48 -> 1773250.7 | C20: ='Transition Accelerator Pipe'!G48 -> 147889.11 | D20: ='Transition Accelerator Pipe'!I48 -> 53979.526 | E20: ='Transition Accelerator Compress'!G105 -> 0.19144123 | F20: =SUM(E20) -> 0.19144123 | G20: =F20*D20 -> 10333.907
A21: ='Transition Accelerator Pipe'!B49 -> 10 | B21: ='Transition Accelerator Pipe'!F49 -> 3097741.6 | C21: ='Transition Accelerator Pipe'!G49 -> 258351.65 | D21: ='Transition Accelerator Pipe'!I49 -> 94298.351 | E21: ='Transition Accelerator Compress'!G106 -> 0.18769562 | F21: =SUM(E21) -> 0.18769562 | G21: =G20+F21*(D21-D20) -> 17901.574
A22: ='Transition Accelerator Pipe'!B50 -> 12 | B22: ='Transition Accelerator Pipe'!F50 -> 4886504.5 | C22: ='Transition Accelerator Pipe'!G50 -> 407534.47 | D22: ='Transition Accelerator Pipe'!I50 -> 148750.08 | E22: ='Transition Accelerator Compress'!G107 -> 0.18474233 | F22: =SUM(E22) -> 0.18474233 | G22: =G21+F22*(D22-D21) -> 27961.113
A23: ='Transition Accelerator Pipe'!B51 -> 14 | B23: ='Transition Accelerator Pipe'!F51 -> 7183982.6 | C23: ='Transition Accelerator Pipe'!G51 -> 599144.15 | D23: ='Transition Accelerator Pipe'!I51 -> 218687.62 | E23: ='Transition Accelerator Compress'!G108 -> 0.1823169 | F23: =SUM(E23) -> 0.1823169 | G23: =G22+F23*(D23-D22) -> 40711.908
A24: ='Transition Accelerator Pipe'!B52 -> 16 | B24: ='Transition Accelerator Pipe'!F52 -> 10031021 | C24: ='Transition Accelerator Pipe'!G52 -> 836587.15 | D24: ='Transition Accelerator Pipe'!I52 -> 305354.31 | E24: ='Transition Accelerator Compress'!G109 -> 0.18026681 | F24: =SUM(E24) -> 0.18026681 | G24: =G23+F24*(D24-D23) -> 56335.036
A25: ='Transition Accelerator Pipe'!B53 -> 18 | B25: ='Transition Accelerator Pipe'!F53 -> 13465623 | C25: ='Transition Accelerator Pipe'!G53 -> 1123032.9 | D25: ='Transition Accelerator Pipe'!I53 -> 409907.03 | E25: ='Transition Accelerator Compress'!G110 -> 0.18012644 | F25: =SUM(E25) -> 0.18012644 | G25: =G24+F25*(D25-D24) -> 75167.744
A26: ='Transition Accelerator Pipe'!B54 -> 20 | B26: ='Transition Accelerator Pipe'!F54 -> 17523473 | C26: ='Transition Accelerator Pipe'!G54 -> 1461457.6 | D26: ='Transition Accelerator Pipe'!I54 -> 533432.03 | E26: ='Transition Accelerator Compress'!G111 -> 0.18012644 | F26: =SUM(E26) -> 0.18012644 | G26: =G25+F26*(D26-D25) -> 97417.863
A27: ='Transition Accelerator Pipe'!B55 -> 22 | B27: ='Transition Accelerator Pipe'!F55 -> 22238315 | C27: ='Transition Accelerator Pipe'!G55 -> 1854675.5 | D27: ='Transition Accelerator Pipe'!I55 -> 676956.56 | E27: ='Transition Accelerator Compress'!G112 -> 0.18012644 | F27: =SUM(E27) -> 0.18012644 | G27: =G26+F27*(D27-D26) -> 123270.43
A28: ='Transition Accelerator Pipe'!B56 -> 24 | B28: ='Transition Accelerator Pipe'!F56 -> 27642243 | C28: ='Transition Accelerator Pipe'!G56 -> 2305363.1 | D28: ='Transition Accelerator Pipe'!I56 -> 841457.53 | E28: ='Transition Accelerator Compress'!G113 -> 0.18012644 | F28: =SUM(E28) -> 0.18012644 | G28: =G27+F28*(D28-D27) -> 152901.4
A29: ='Transition Accelerator Pipe'!B57 -> 26 | B29: ='Transition Accelerator Pipe'!F57 -> 33765917 | C29: ='Transition Accelerator Pipe'!G57 -> 2816077.5 | D29: ='Transition Accelerator Pipe'!I57 -> 1027868.3 | E29: ='Transition Accelerator Compress'!G114 -> 0.18012644 | F29: =SUM(E29) -> 0.18012644 | G29: =G28+F29*(D29-D28) -> 186478.91
A30: ='Transition Accelerator Pipe'!B58 -> 28 | B30: ='Transition Accelerator Pipe'!F58 -> 40638743 | C30: ='Transition Accelerator Pipe'!G58 -> 3389271.1 | D30: ='Transition Accelerator Pipe'!I58 -> 1237084 | E30: ='Transition Accelerator Compress'!G115 -> 0.18012644 | F30: =SUM(E30) -> 0.18012644 | G30: =G29+F30*(D30-D29) -> 224164.18
A31: ='Transition Accelerator Pipe'!B59 -> 30 | B31: ='Transition Accelerator Pipe'!F59 -> 48289012 | C31: ='Transition Accelerator Pipe'!G59 -> 4027303.6 | D31: ='Transition Accelerator Pipe'!I59 -> 1469965.8 | E31: ='Transition Accelerator Compress'!G116 -> 0.18012644 | F31: =SUM(E31) -> 0.18012644 | G31: =G30+F31*(D31-D30) -> 266112.36
A32: ='Transition Accelerator Pipe'!B60 -> 32 | B32: ='Transition Accelerator Pipe'!F60 -> 56744024 | C32: ='Transition Accelerator Pipe'!G60 -> 4732451.6 | D32: ='Transition Accelerator Pipe'!I60 -> 1727344.8 | E32: ='Transition Accelerator Compress'!G117 -> 0.18012644 | F32: =SUM(E32) -> 0.18012644 | G32: =G31+F32*(D32-D31) -> 312473.13
A35: Distribution Cost-Capacity Fixed OPEX Estimation
A36: Pipeline sizes (inch, inner diameter) | B36: Gas flow rate (Sm^3/day) | C36: Daily Capacity (kg H2 / day) | D36: Annual Capacity (t H2 / year) | E36: Total Labour Costs, pipe ($ 2020 CAD per year / km* t H2 per year capacity) | F36: Total Labour Costs, compressor ($ 2020 CAD per year / km* t H2 per year capacity) | G36: Total Fixed OPEX, pipe ($ 2020 CAD per year / km* t H2 per year capacity) | H36: Total Fixed OPEX, compressor ($ 2020 CAD per year / km* t H2 per year capacity) | I36: Total Fixed OPEX ($ 2020 CAD per year / km* t H2 per year capacity) | J36: Total Fixed OPEX ($ 2020 CAD per year / km* per year capacity)
A37: ='Transition Accelerator Pipe'!B48 -> 8 | B37: ='Transition Accelerator Pipe'!F48 -> 1773250.7 | C37: ='Transition Accelerator Pipe'!G48 -> 147889.11 | D37: ='Transition Accelerator Pipe'!I48 -> 53979.526 | E37: ='Transition Accelerator Pipe'!I82 -> 0.054135789 | F37: ='Transition Accelerator Compress'!I139 -> 0.0017798068 | G37: ='Transition Accelerator Pipe'!J99 -> 0.65948479 | H37: ='Transition Accelerator Compress'!J122 -> 0.028184935 | I37: =SUM(E37:H37) -> 0.74358532 | J37: =I37*D37 -> 40138.383
A38: ='Transition Accelerator Pipe'!B49 -> 10 | B38: ='Transition Accelerator Pipe'!F49 -> 3097741.6 | C38: ='Transition Accelerator Pipe'!G49 -> 258351.65 | D38: ='Transition Accelerator Pipe'!I49 -> 94298.351 | E38: ='Transition Accelerator Pipe'!I83 -> 0.035626913 | F38: ='Transition Accelerator Compress'!I140 -> 0.0011712958 | G38: ='Transition Accelerator Pipe'!J100 -> 0.43933435 | H38: ='Transition Accelerator Compress'!J123 -> 0.025265372 | I38: =SUM(E38:H38) -> 0.50139793 | J38: =J37+I38*(D38-D37) -> 60354.159
A39: ='Transition Accelerator Pipe'!B50 -> 12 | B39: ='Transition Accelerator Pipe'!F50 -> 4886504.5 | C39: ='Transition Accelerator Pipe'!G50 -> 407534.47 | D39: ='Transition Accelerator Pipe'!I50 -> 148750.08 | E39: ='Transition Accelerator Pipe'!I84 -> 0.025311236 | F39: ='Transition Accelerator Compress'!I141 -> 0.00083215024 | G39: ='Transition Accelerator Pipe'!J101 -> 0.31891636 | H39: ='Transition Accelerator Compress'!J124 -> 0.023111364 | I39: =SUM(E39:H39) -> 0.36817111 | J39: =J38+I39*(D39-D38) -> 80401.713
A40: ='Transition Accelerator Pipe'!B51 -> 14 | B40: ='Transition Accelerator Pipe'!F51 -> 7183982.6 | C40: ='Transition Accelerator Pipe'!G51 -> 599144.15 | D40: ='Transition Accelerator Pipe'!I51 -> 218687.62 | E40: ='Transition Accelerator Pipe'!I85 -> 0.018957808 | F40: ='Transition Accelerator Compress'!I142 -> 0.00062327041 | G40: ='Transition Accelerator Pipe'!J102 -> 0.245303 | H40: ='Transition Accelerator Compress'!J125 -> 0.021437549 | I40: =SUM(E40:H40) -> 0.28632162 | J40: =J39+I40*(D40-D39) -> 100426.34
A41: ='Transition Accelerator Pipe'!B52 -> 16 | B41: ='Transition Accelerator Pipe'!F52 -> 10031021 | C41: ='Transition Accelerator Pipe'!G52 -> 836587.15 | D41: ='Transition Accelerator Pipe'!I52 -> 305354.31 | E41: ='Transition Accelerator Pipe'!I86 -> 0.014758874 | F41: ='Transition Accelerator Compress'!I143 -> 0.00048522326 | G41: ='Transition Accelerator Pipe'!J103 -> 0.19670108 | H41: ='Transition Accelerator Compress'!J126 -> 0.020088269 | I41: =SUM(E41:H41) -> 0.23203345 | J41: =J40+I41*(D41-D40) -> 120535.91
A42: ='Transition Accelerator Pipe'!B53 -> 18 | B42: ='Transition Accelerator Pipe'!F53 -> 13465623 | C42: ='Transition Accelerator Pipe'!G53 -> 1123032.9 | D42: ='Transition Accelerator Pipe'!I53 -> 409907.03 | E42: ='Transition Accelerator Pipe'!I87 -> 0.011834291 | F42: ='Transition Accelerator Compress'!I144 -> 0.00038907259 | G42: ='Transition Accelerator Pipe'!J104 -> 0.16275687 | H42: ='Transition Accelerator Compress'!J127 -> 0.019114736 | I42: =SUM(E42:H42) -> 0.19409497 | J42: =J41+I42*(D42-D41) -> 140829.07
A43: ='Transition Accelerator Pipe'!B54 -> 20 | B43: ='Transition Accelerator Pipe'!F54 -> 17523473 | C43: ='Transition Accelerator Pipe'!G54 -> 1461457.6 | D43: ='Transition Accelerator Pipe'!I54 -> 533432.03 | E43: ='Transition Accelerator Pipe'!I88 -> 0.0097128561 | F43: ='Transition Accelerator Compress'!I145 -> 0.00031932678 | G43: ='Transition Accelerator Pipe'!J105 -> 0.138017 | H43: ='Transition Accelerator Compress'!J128 -> 0.018294551 | I43: =SUM(E43:H43) -> 0.16634374 | J43: =J42+I43*(D43-D42) -> 161376.68
A44: ='Transition Accelerator Pipe'!B55 -> 22 | B44: ='Transition Accelerator Pipe'!F55 -> 22238315 | C44: ='Transition Accelerator Pipe'!G55 -> 1854675.5 | D44: ='Transition Accelerator Pipe'!I55 -> 676956.56 | E44: ='Transition Accelerator Pipe'!I89 -> 0.0081233594 | F44: ='Transition Accelerator Compress'!I146 -> 0.00026706935 | G44: ='Transition Accelerator Pipe'!J106 -> 0.11937619 | H44: ='Transition Accelerator Compress'!J129 -> 0.017582962 | I44: =SUM(E44:H44) -> 0.14534958 | J44: =J43+I44*(D44-D43) -> 182237.91
A45: ='Transition Accelerator Pipe'!B56 -> 24 | B45: ='Transition Accelerator Pipe'!F56 -> 27642243 | C45: ='Transition Accelerator Pipe'!G56 -> 2305363.1 | D45: ='Transition Accelerator Pipe'!I56 -> 841457.53 | E45: ='Transition Accelerator Pipe'!I90 -> 0.0069005248 | F45: ='Transition Accelerator Compress'!I147 -> 0.00022686657 | G45: ='Transition Accelerator Pipe'!J107 -> 0.10495485 | H45: ='Transition Accelerator Compress'!J130 -> 0.016957528 | I45: =SUM(E45:H45) -> 0.12903976 | J45: =J44+I45*(D45-D44) -> 203465.08
A46: ='Transition Accelerator Pipe'!B57 -> 26 | B46: ='Transition Accelerator Pipe'!F57 -> 33765917 | C46: ='Transition Accelerator Pipe'!G57 -> 2816077.5 | D46: ='Transition Accelerator Pipe'!I57 -> 1027868.3 | E46: ='Transition Accelerator Pipe'!I91 -> 0.0059388611 | F46: ='Transition Accelerator Compress'!I148 -> 0.00019525023 | G46: ='Transition Accelerator Pipe'!J108 -> 0.093558102 | H46: ='Transition Accelerator Compress'!J131 -> 0.01640185 | I46: =SUM(E46:H46) -> 0.11609406 | J46: =J45+I46*(D46-D45) -> 225106.26
A47: ='Transition Accelerator Pipe'!B58 -> 28 | B47: ='Transition Accelerator Pipe'!F58 -> 40638743 | C47: ='Transition Accelerator Pipe'!G58 -> 3389271.1 | D47: ='Transition Accelerator Pipe'!I58 -> 1237084 | E47: ='Transition Accelerator Pipe'!I92 -> 0.0051684092 | F47: ='Transition Accelerator Compress'!I149 -> 0.0001699203 | G47: ='Transition Accelerator Pipe'!J109 -> 0.084395189 | H47: ='Transition Accelerator Compress'!J132 -> 0.015903619 | I47: =SUM(E47:H47) -> 0.10563714 | J47: =J46+I47*(D47-D46) -> 247207.2
A48: ='Transition Accelerator Pipe'!B59 -> 30 | B48: ='Transition Accelerator Pipe'!F59 -> 48289012 | C48: ='Transition Accelerator Pipe'!G59 -> 4027303.6 | D48: ='Transition Accelerator Pipe'!I59 -> 1469965.8 | E48: ='Transition Accelerator Pipe'!I93 -> 0.0045412545 | F48: ='Transition Accelerator Compress'!I150 -> 0.00014930152 | G48: ='Transition Accelerator Pipe'!J110 -> 0.07692498 | H48: ='Transition Accelerator Compress'!J133 -> 0.01545339 | I48: =SUM(E48:H48) -> 0.097068926 | J48: =J47+I48*(D48-D47) -> 269812.8
A49: ='Transition Accelerator Pipe'!B60 -> 32 | B49: ='Transition Accelerator Pipe'!F60 -> 56744024 | C49: ='Transition Accelerator Pipe'!G60 -> 4732451.6 | D49: ='Transition Accelerator Pipe'!I60 -> 1727344.8 | E49: ='Transition Accelerator Pipe'!I94 -> 0.0040236666 | F49: ='Transition Accelerator Compress'!I151 -> 0.00013228493 | G49: ='Transition Accelerator Pipe'!J111 -> 0.070766623 | H49: ='Transition Accelerator Compress'!J134 -> 0.015043774 | I49: =SUM(E49:H49) -> 0.089966349 | J49: =J48+I49*(D49-D48) -> 292968.25

Sheet Normalized CAPEX
A1: Pipeline sizes (inch, inner diameter) | B1: Annual Capacity (t H2 / year) | C1: Total CAPEX ($ 2020 CAD / km)
A2: ='Normalized Transmission Costs'!A3 -> 8 | B2: ='Normalized Transmission Costs'!D3 -> 53979.526 | C2: ='Normalized Transmission Costs'!G3 -> 1394121
A3: ='Normalized Transmission Costs'!A4 -> 10 | B3: ='Normalized Transmission Costs'!D4 -> 94298.351 | C3: ='Normalized Transmission Costs'!G4 -> 1632461.1
A4: ='Normalized Transmission Costs'!A5 -> 12 | B4: ='Normalized Transmission Costs'!D5 -> 148750.08 | C4: ='Normalized Transmission Costs'!G5 -> 1880928.2
A5: ='Normalized Transmission Costs'!A6 -> 14 | B5: ='Normalized Transmission Costs'!D6 -> 218687.62 | C5: ='Normalized Transmission Costs'!G6 -> 2140113.3
A6: ='Normalized Transmission Costs'!A7 -> 16 | B6: ='Normalized Transmission Costs'!D7 -> 305354.31 | C6: ='Normalized Transmission Costs'!G7 -> 2410693.6
A7: ='Normalized Transmission Costs'!A8 -> 18 | B7: ='Normalized Transmission Costs'!D8 -> 409907.03 | C7: ='Normalized Transmission Costs'!G8 -> 2694415.6
A8: ='Normalized Transmission Costs'!A9 -> 20 | B8: ='Normalized Transmission Costs'!D9 -> 533432.03 | C8: ='Normalized Transmission Costs'!G9 -> 2991623.9
A9: ='Normalized Transmission Costs'!A10 -> 22 | B9: ='Normalized Transmission Costs'!D10 -> 676956.56 | C9: ='Normalized Transmission Costs'!G10 -> 3303302.3
A10: ='Normalized Transmission Costs'!A11 -> 24 | B10: ='Normalized Transmission Costs'!D11 -> 841457.53 | C10: ='Normalized Transmission Costs'!G11 -> 3630651.2
A11: ='Normalized Transmission Costs'!A12 -> 26 | B11: ='Normalized Transmission Costs'!D12 -> 1027868.3 | C11: ='Normalized Transmission Costs'!G12 -> 3975045.6
A12: ='Normalized Transmission Costs'!A13 -> 28 | B12: ='Normalized Transmission Costs'!D13 -> 1237084 | C12: ='Normalized Transmission Costs'!G13 -> 4338062.4
A13: ='Normalized Transmission Costs'!A14 -> 30 | B13: ='Normalized Transmission Costs'!D14 -> 1469965.8 | C13: ='Normalized Transmission Costs'!G14 -> 4721511.6
A14: ='Normalized Transmission Costs'!A15 -> 32 | B14: ='Normalized Transmission Costs'!D15 -> 1727344.8 | C14: ='Normalized Transmission Costs'!G15 -> 5127471.9

Sheet Normalized Variable OPEX
A1: Pipeline sizes (inch, inner diameter) | B1: Annual Capacity (t H2 / year) | C1: Total Variable OPEX ($ 2020 CAD/ km)
A2: ='Normalized Transmission Costs'!A20 -> 8 | B2: ='Normalized Transmission Costs'!D20 -> 53979.526 | C2: ='Normalized Transmission Costs'!G20 -> 10333.907
A3: ='Normalized Transmission Costs'!A21 -> 10 | B3: ='Normalized Transmission Costs'!D21 -> 94298.351 | C3: ='Normalized Transmission Costs'!G21 -> 17901.574
A4: ='Normalized Transmission Costs'!A22 -> 12 | B4: ='Normalized Transmission Costs'!D22 -> 148750.08 | C4: ='Normalized Transmission Costs'!G22 -> 27961.113
A5: ='Normalized Transmission Costs'!A23 -> 14 | B5: ='Normalized Transmission Costs'!D23 -> 218687.62 | C5: ='Normalized Transmission Costs'!G23 -> 40711.908
A6: ='Normalized Transmission Costs'!A24 -> 16 | B6: ='Normalized Transmission Costs'!D24 -> 305354.31 | C6: ='Normalized Transmission Costs'!G24 -> 56335.036
A7: ='Normalized Transmission Costs'!A25 -> 18 | B7: ='Normalized Transmission Costs'!D25 -> 409907.03 | C7: ='Normalized Transmission Costs'!G25 -> 75167.744
A8: ='Normalized Transmission Costs'!A26 -> 20 | B8: ='Normalized Transmission Costs'!D26 -> 533432.03 | C8: ='Normalized Transmission Costs'!G26 -> 97417.863
A9: ='Normalized Transmission Costs'!A27 -> 22 | B9: ='Normalized Transmission Costs'!D27 -> 676956.56 | C9: ='Normalized Transmission Costs'!G27 -> 123270.43
A10: ='Normalized Transmission Costs'!A28 -> 24 | B10: ='Normalized Transmission Costs'!D28 -> 841457.53 | C10: ='Normalized Transmission Costs'!G28 -> 152901.4
A11: ='Normalized Transmission Costs'!A29 -> 26 | B11: ='Normalized Transmission Costs'!D29 -> 1027868.3 | C11: ='Normalized Transmission Costs'!G29 -> 186478.91
A12: ='Normalized Transmission Costs'!A30 -> 28 | B12: ='Normalized Transmission Costs'!D30 -> 1237084 | C12: ='Normalized Transmission Costs'!G30 -> 224164.18
A13: ='Normalized Transmission Costs'!A31 -> 30 | B13: ='Normalized Transmission Costs'!D31 -> 1469965.8 | C13: ='Normalized Transmission Costs'!G31 -> 266112.36
A14: ='Normalized Transmission Costs'!A32 -> 32 | B14: ='Normalized Transmission Costs'!D32 -> 1727344.8 | C14: ='Normalized Transmission Costs'!G32 -> 312473.13

Sheet Normalized Fixed OPEX
A1: Pipeline sizes (inch, inner diameter) | B1: Annual Capacity (t H2 / year) | C1: Total Fixed OPEX ($ 2020 CAD per year / km* per year capacity)
A2: ='Normalized Transmission Costs'!A37 -> 8 | B2: ='Normalized Transmission Costs'!D37 -> 53979.526 | C2: ='Normalized Transmission Costs'!J37 -> 40138.383
A3: ='Normalized Transmission Costs'!A38 -> 10 | B3: ='Normalized Transmission Costs'!D38 -> 94298.351 | C3: ='Normalized Transmission Costs'!J38 -> 60354.159
A4: ='Normalized Transmission Costs'!A39 -> 12 | B4: ='Normalized Transmission Costs'!D39 -> 148750.08 | C4: ='Normalized Transmission Costs'!J39 -> 80401.713
A5: ='Normalized Transmission Costs'!A40 -> 14 | B5: ='Normalized Transmission Costs'!D40 -> 218687.62 | C5: ='Normalized Transmission Costs'!J40 -> 100426.34
A6: ='Normalized Transmission Costs'!A41 -> 16 | B6: ='Normalized Transmission Costs'!D41 -> 305354.31 | C6: ='Normalized Transmission Costs'!J41 -> 120535.91
A7: ='Normalized Transmission Costs'!A42 -> 18 | B7: ='Normalized Transmission Costs'!D42 -> 409907.03 | C7: ='Normalized Transmission Costs'!J42 -> 140829.07
A8: ='Normalized Transmission Costs'!A43 -> 20 | B8: ='Normalized Transmission Costs'!D43 -> 533432.03 | C8: ='Normalized Transmission Costs'!J43 -> 161376.68
A9: ='Normalized Transmission Costs'!A44 -> 22 | B9: ='Normalized Transmission Costs'!D44 -> 676956.56 | C9: ='Normalized Transmission Costs'!J44 -> 182237.91
A10: ='Normalized Transmission Costs'!A45 -> 24 | B10: ='Normalized Transmission Costs'!D45 -> 841457.53 | C10: ='Normalized Transmission Costs'!J45 -> 203465.08
A11: ='Normalized Transmission Costs'!A46 -> 26 | B11: ='Normalized Transmission Costs'!D46 -> 1027868.3 | C11: ='Normalized Transmission Costs'!J46 -> 225106.26
A12: ='Normalized Transmission Costs'!A47 -> 28 | B12: ='Normalized Transmission Costs'!D47 -> 1237084 | C12: ='Normalized Transmission Costs'!J47 -> 247207.2
A13: ='Normalized Transmission Costs'!A48 -> 30 | B13: ='Normalized Transmission Costs'!D48 -> 1469965.8 | C13: ='Normalized Transmission Costs'!J48 -> 269812.8
A14: ='Normalized Transmission Costs'!A49 -> 32 | B14: ='Normalized Transmission Costs'!D49 -> 1727344.8 | C14: ='Normalized Transmission Costs'!J49 -> 292968.25
